{"cutoffs":[{"college_code":"C010","college_name":"Dr. M.V.Shetty College of Physiotherapy, Vidyanagar,Mangalore – 575013","course_name":"Bachelor of Physiotherapy","category":"3BG","seat_type":"ROK","rounds":{"2025_R1":47462,"2025_R2":61227,"2025_R3":107227},"min_rank":47462,"max_rank":107227},{"college_code":"C010","college_name":"Dr. M.V.Shetty College of Physiotherapy, Vidyanagar,Mangalore – 575013","course_name":"Bachelor of Physiotherapy","category":"GM","seat_type":"ROK","rounds":{"2025_R1":41010,"2025_R2":45761,"2025_R3":106996.5},"min_rank":41010,"max_rank":106996.5},{"college_code":"C010","college_name":"Dr. M.V.Shetty College of Physiotherapy, Vidyanagar,Mangalore – 575013","course_name":"Bachelor of Physiotherapy","category":"GMH","seat_type":"HK","rounds":{"2025_R1":57266,"2025_R2":52429,"2025_R3":197509},"min_rank":52429,"max_rank":197509},{"college_code":"C010","college_name":"Dr. M.V.Shetty College of Physiotherapy, Vidyanagar,Mangalore – 575013","course_name":"Bachelor of Physiotherapy","category":"GMR","seat_type":"ROK","rounds":{"2025_R1":42943,"2025_R2":56125,"2025_R3":157665},"min_rank":42943,"max_rank":157665},{"college_code":"C010","college_name":"Dr. M.V.Shetty College of Physiotherapy, Vidyanagar,Mangalore – 575013","course_name":"Bachelor of Physiotherapy","category":"SCG","seat_type":"ROK","rounds":{"2025_R1":64990,"2025_R2":115608,"2025_R3":166490},"min_rank":64990,"max_rank":166490}],"suggestions":{"Bachelor of Physiotherapy|3BG|ROK":{"similarCollege":{"college":"Vikram College of Physiotherapy, No.7, Paramahamsa Road, Yadavagiri, Mysore – 570020","college_code":"C101","branch":"Bachelor of Physiotherapy","category":"3BG"},"similarBranch":null},"Bachelor of Physiotherapy|GM|ROK":{"similarCollege":{"college":"Nargund College of Physiotherapy, Dattatreyanagar, 2nd Main Road, 100 ft Ring Road, BSK 3rd Stage, Bangalore – 560 085","college_code":"C032","branch":"Bachelor of Physiotherapy","category":"GM"},"similarBranch":null},"Bachelor of Physiotherapy|GMH|HK":{"similarCollege":{"college":"Sanjay Gandhi Institute of Trauma & Orthopaedics (Dept. of Physiotherapy), Byrasandra, Jayanagar East, Bangalore – 560 011 (Government)","college_code":"C001","branch":"Bachelor of Physiotherapy","category":"GMH"},"similarBranch":null},"Bachelor of Physiotherapy|GMR|ROK":{"similarCollege":{"college":"Shantha College of Physiotherapy, Peresandra, Chikkaballapur Taluk - 562104","college_code":"C100","branch":"Bachelor of Physiotherapy","category":"GMR"},"similarBranch":null},"Bachelor of Physiotherapy|SCG|ROK":{"similarCollege":{"college":"Sai Sidd College of Physiotherapy, No.254, Hebbal Industrial Area, Mysore – 570018","college_code":"C183","branch":"Bachelor of Physiotherapy","category":"SCG"},"similarBranch":null}}}