{"cutoffs":[{"college_code":"C177","college_name":"N E T College of Physiotherapy, Jainpete, Belthangady - 574214, Dakshina Kannada","course_name":"Bachelor of Physiotherapy","category":"GM","seat_type":"ROK","rounds":{"2025_R1":83546,"2025_R2":130088,"2025_R3":180176},"min_rank":83546,"max_rank":180176}],"suggestions":{"Bachelor of Physiotherapy|GM|ROK":{"similarCollege":{"college":"Surya College of Physiotherapy, No.96, Bommenahalli, Mandur Post, Old Madras Raod, Bangalore – 560 049","college_code":"C068","branch":"Bachelor of Physiotherapy","category":"GM"},"similarBranch":null}}}