{"cutoffs":[{"college_code":"C068","college_name":"Surya College of Physiotherapy, No.96, Bommenahalli, Mandur Post, Old Madras Raod, Bangalore – 560 049","course_name":"Bachelor of Physiotherapy","category":"GM","seat_type":"ROK","rounds":{"2025_R1":64599,"2025_R2":81233,"2025_R3":180421},"min_rank":64599,"max_rank":180421}],"suggestions":{"Bachelor of Physiotherapy|GM|ROK":{"similarCollege":{"college":"Sri Channegowda College of Physiotherapy, NH-75, Bypass, Near Railway Gate, Kogilahalli, Kolar – 563102","branch":"Bachelor of Physiotherapy","category":"GM"},"similarBranch":null}}}