{"cutoffs":[{"college_code":"X229","college_name":"KVC College of Allied Health Sciences, D.No - 247, A Block, 3rd Stage, Vijaynagar, Mysore-570017","course_name":"B.Sc Anaest, Oper.Theater","category":"GM","seat_type":"ROK","rounds":{"2025_R2":124129,"2025_R3":124129},"min_rank":124129,"max_rank":124129},{"college_code":"X229","college_name":"KVC College of Allied Health Sciences, D.No - 247, A Block, 3rd Stage, Vijaynagar, Mysore-570017","course_name":"B.Sc Anaest, Oper.Theater","category":"SCG","seat_type":"ROK","rounds":{"2025_R2":140780,"2025_R3":140780},"min_rank":140780,"max_rank":140780}],"suggestions":{"B.Sc Anaest, Oper.Theater|GM|ROK":{"similarCollege":{"college":"Apollo Apex College of Allied Health Sciences, #02, 3rd A cross road, 7th main, 6th block, Banashankari 3rd stage, Banashankari, Bengaluru","college_code":"X455","branch":"B.Sc Anaest, Oper.Theater","category":"GM"},"similarBranch":null},"B.Sc Anaest, Oper.Theater|SCG|ROK":{"similarCollege":{"college":"Mandya Institute of Medical Sciences, Mandya – 571 401","college_code":"X218","branch":"B.Sc Anaest, Oper.Theater","category":"SCG"},"similarBranch":null}}}