{"cutoffs":[{"college_code":"E314","college_name":"CAUVERY COLLEGE OF ENGINEERING KBL LAYOUT, ALANAHALLY MYSORE","course_name":"COMPUTER SCIENCE AND ENGG(ARTIFICIA L INTELLIGENCE AND MACHINE LEARNING)","category":"GM","seat_type":"ROK","rounds":{"2025_R2":141393,"2025_R3":258679},"min_rank":141393,"max_rank":258679},{"college_code":"E314","college_name":"CAUVERY COLLEGE OF ENGINEERING KBL LAYOUT, ALANAHALLY MYSORE","course_name":"COMPUTER SCIENCE AND ENGG(ARTIFICIAL INTELLIGENCE AND MACHINE LEARNING)","category":"1G","seat_type":"ROK","rounds":{"2025_R1":127148},"min_rank":127148,"max_rank":127148},{"college_code":"E314","college_name":"CAUVERY COLLEGE OF ENGINEERING KBL LAYOUT, ALANAHALLY MYSORE","course_name":"COMPUTER SCIENCE AND ENGG(ARTIFICIAL INTELLIGENCE AND MACHINE LEARNING)","category":"1H","seat_type":"ROK","rounds":{"2025_R1":137073},"min_rank":137073,"max_rank":137073},{"college_code":"E314","college_name":"CAUVERY COLLEGE OF ENGINEERING KBL LAYOUT, ALANAHALLY MYSORE","course_name":"COMPUTER SCIENCE AND ENGG(ARTIFICIAL INTELLIGENCE AND MACHINE LEARNING)","category":"2AG","seat_type":"ROK","rounds":{"2025_R1":109450},"min_rank":109450,"max_rank":109450},{"college_code":"E314","college_name":"CAUVERY COLLEGE OF ENGINEERING KBL LAYOUT, ALANAHALLY MYSORE","course_name":"COMPUTER SCIENCE AND ENGG(ARTIFICIAL INTELLIGENCE AND MACHINE LEARNING)","category":"2AR","seat_type":"ROK","rounds":{"2025_R1":117319},"min_rank":117319,"max_rank":117319},{"college_code":"E314","college_name":"CAUVERY COLLEGE OF ENGINEERING KBL LAYOUT, ALANAHALLY MYSORE","course_name":"COMPUTER SCIENCE AND ENGG(ARTIFICIAL INTELLIGENCE AND MACHINE LEARNING)","category":"3BG","seat_type":"ROK","rounds":{"2025_R1":99548},"min_rank":99548,"max_rank":99548},{"college_code":"E314","college_name":"CAUVERY COLLEGE OF ENGINEERING KBL LAYOUT, ALANAHALLY MYSORE","course_name":"COMPUTER SCIENCE AND ENGG(ARTIFICIAL INTELLIGENCE AND MACHINE LEARNING)","category":"GM","seat_type":"ROK","rounds":{"2025_R1":98508},"min_rank":98508,"max_rank":98508},{"college_code":"E314","college_name":"CAUVERY COLLEGE OF ENGINEERING KBL LAYOUT, ALANAHALLY MYSORE","course_name":"COMPUTER SCIENCE AND ENGG(ARTIFICIAL INTELLIGENCE AND MACHINE LEARNING)","category":"GMK","seat_type":"ROK","rounds":{"2025_R1":105352},"min_rank":105352,"max_rank":105352},{"college_code":"E314","college_name":"CAUVERY COLLEGE OF ENGINEERING KBL LAYOUT, ALANAHALLY MYSORE","course_name":"COMPUTER SCIENCE AND ENGG(ARTIFICIAL INTELLIGENCE AND MACHINE LEARNING)","category":"GMR","seat_type":"ROK","rounds":{"2025_R1":112496},"min_rank":112496,"max_rank":112496},{"college_code":"E314","college_name":"CAUVERY COLLEGE OF ENGINEERING KBL LAYOUT, ALANAHALLY MYSORE","course_name":"COMPUTER SCIENCE AND ENGG(ARTIFICIAL INTELLIGENCE AND MACHINE LEARNING)","category":"SCG","seat_type":"ROK","rounds":{"2025_R1":175933},"min_rank":175933,"max_rank":175933},{"college_code":"E314","college_name":"CAUVERY COLLEGE OF ENGINEERING KBL LAYOUT, ALANAHALLY MYSORE","course_name":"COMPUTER SCIENCE AND ENGG(ARTIFICIAL INTELLIGENCE AND MACHINE LEARNING)","category":"SCR","seat_type":"ROK","rounds":{"2025_R1":199529},"min_rank":199529,"max_rank":199529},{"college_code":"E314","college_name":"CAUVERY COLLEGE OF ENGINEERING KBL LAYOUT, ALANAHALLY MYSORE","course_name":"COMPUTER SCIENCE AND ENGG(ARTIFICIAL INTELLIGENCE AND MACHINE LEARNING)","category":"STG","seat_type":"ROK","rounds":{"2025_R1":167563},"min_rank":167563,"max_rank":167563},{"college_code":"E314","college_name":"CAUVERY COLLEGE OF ENGINEERING KBL LAYOUT, ALANAHALLY MYSORE","course_name":"COMPUTER SCIENCE AND ENGINEERING","category":"GM","seat_type":"ROK","rounds":{"2025_R1":91813,"2025_R2":130595,"2025_R3":257236},"min_rank":91813,"max_rank":257236},{"college_code":"E314","college_name":"CAUVERY COLLEGE OF ENGINEERING KBL LAYOUT, ALANAHALLY MYSORE","course_name":"COMPUTER SCIENCE AND ENGINEERING","category":"GMH","seat_type":"ROK","rounds":{"2025_R1":99137},"min_rank":99137,"max_rank":99137},{"college_code":"E314","college_name":"CAUVERY COLLEGE OF ENGINEERING KBL LAYOUT, ALANAHALLY MYSORE","course_name":"COMPUTER SCIENCE AND ENGINEERING","category":"SCH","seat_type":"ROK","rounds":{"2025_R1":191400},"min_rank":191400,"max_rank":191400},{"college_code":"E314","college_name":"CAUVERY COLLEGE OF ENGINEERING KBL LAYOUT, ALANAHALLY MYSORE","course_name":"COMPUTER SCIENCE AND ENGINEERING (CYBER SECURITY)","category":"GM","seat_type":"ROK","rounds":{"2025_R1":116858,"2025_R2":258715.5,"2025_R3":258715.5},"min_rank":116858,"max_rank":258715.5},{"college_code":"E314","college_name":"CAUVERY COLLEGE OF ENGINEERING KBL LAYOUT, ALANAHALLY MYSORE","course_name":"COMPUTER SCIENCE AND ENGINEERING (CYBER SECURITY)","category":"GMH","seat_type":"ROK","rounds":{"2025_R1":121818},"min_rank":121818,"max_rank":121818},{"college_code":"E314","college_name":"CAUVERY COLLEGE OF ENGINEERING KBL LAYOUT, ALANAHALLY MYSORE","course_name":"COMPUTER SCIENCE AND ENGINEERING (CYBER SECURITY)","category":"GMRH","seat_type":"ROK","rounds":{"2025_R1":122348},"min_rank":122348,"max_rank":122348},{"college_code":"E314","college_name":"CAUVERY COLLEGE OF ENGINEERING KBL LAYOUT, ALANAHALLY MYSORE","course_name":"COMPUTER SCIENCE AND ENGINEERING(D ATA SCIENCE)","category":"GM","seat_type":"ROK","rounds":{"2025_R2":240745,"2025_R3":240745},"min_rank":240745,"max_rank":240745},{"college_code":"E314","college_name":"CAUVERY COLLEGE OF ENGINEERING KBL LAYOUT, ALANAHALLY MYSORE","course_name":"COMPUTER SCIENCE AND ENGINEERING(DAT A SCIENCE)","category":"2AG","seat_type":"ROK","rounds":{"2025_R1":132030},"min_rank":132030,"max_rank":132030},{"college_code":"E314","college_name":"CAUVERY COLLEGE OF ENGINEERING KBL LAYOUT, ALANAHALLY MYSORE","course_name":"COMPUTER SCIENCE AND ENGINEERING(DAT A SCIENCE)","category":"2BG","seat_type":"ROK","rounds":{"2025_R1":121596},"min_rank":121596,"max_rank":121596},{"college_code":"E314","college_name":"CAUVERY COLLEGE OF ENGINEERING KBL LAYOUT, ALANAHALLY MYSORE","course_name":"COMPUTER SCIENCE AND ENGINEERING(DAT A SCIENCE)","category":"3AG","seat_type":"ROK","rounds":{"2025_R1":116335},"min_rank":116335,"max_rank":116335},{"college_code":"E314","college_name":"CAUVERY COLLEGE OF ENGINEERING KBL LAYOUT, ALANAHALLY MYSORE","course_name":"COMPUTER SCIENCE AND ENGINEERING(DAT A SCIENCE)","category":"3AR","seat_type":"ROK","rounds":{"2025_R1":129875},"min_rank":129875,"max_rank":129875},{"college_code":"E314","college_name":"CAUVERY COLLEGE OF ENGINEERING KBL LAYOUT, ALANAHALLY MYSORE","course_name":"COMPUTER SCIENCE AND ENGINEERING(DAT A SCIENCE)","category":"3BG","seat_type":"ROK","rounds":{"2025_R1":119371},"min_rank":119371,"max_rank":119371},{"college_code":"E314","college_name":"CAUVERY COLLEGE OF ENGINEERING KBL LAYOUT, ALANAHALLY MYSORE","course_name":"COMPUTER SCIENCE AND ENGINEERING(DAT A SCIENCE)","category":"3BR","seat_type":"ROK","rounds":{"2025_R1":128190},"min_rank":128190,"max_rank":128190},{"college_code":"E314","college_name":"CAUVERY COLLEGE OF ENGINEERING KBL LAYOUT, ALANAHALLY MYSORE","course_name":"COMPUTER SCIENCE AND ENGINEERING(DAT A SCIENCE)","category":"GM","seat_type":"ROK","rounds":{"2025_R1":115538},"min_rank":115538,"max_rank":115538},{"college_code":"E314","college_name":"CAUVERY COLLEGE OF ENGINEERING KBL LAYOUT, ALANAHALLY MYSORE","course_name":"COMPUTER SCIENCE AND ENGINEERING(DAT A SCIENCE)","category":"GMKH","seat_type":"HK","rounds":{"2025_R1":135128},"min_rank":135128,"max_rank":135128},{"college_code":"E314","college_name":"CAUVERY COLLEGE OF ENGINEERING KBL LAYOUT, ALANAHALLY MYSORE","course_name":"COMPUTER SCIENCE AND ENGINEERING(DAT A SCIENCE)","category":"GMKH","seat_type":"ROK","rounds":{"2025_R1":135128},"min_rank":135128,"max_rank":135128},{"college_code":"E314","college_name":"CAUVERY COLLEGE OF ENGINEERING KBL LAYOUT, ALANAHALLY MYSORE","course_name":"COMPUTER SCIENCE AND ENGINEERING(DAT A SCIENCE)","category":"GMR","seat_type":"ROK","rounds":{"2025_R1":124460},"min_rank":124460,"max_rank":124460},{"college_code":"E314","college_name":"CAUVERY COLLEGE OF ENGINEERING KBL LAYOUT, ALANAHALLY MYSORE","course_name":"COMPUTER SCIENCE AND ENGINEERING(DAT A SCIENCE)","category":"SCG","seat_type":"ROK","rounds":{"2025_R1":195423},"min_rank":195423,"max_rank":195423},{"college_code":"E314","college_name":"CAUVERY COLLEGE OF ENGINEERING KBL LAYOUT, ALANAHALLY MYSORE","course_name":"COMPUTER SCIENCE AND ENGINEERING(DAT A SCIENCE)","category":"STG","seat_type":"ROK","rounds":{"2025_R1":175985},"min_rank":175985,"max_rank":175985},{"college_code":"E314","college_name":"CAUVERY COLLEGE OF ENGINEERING KBL LAYOUT, ALANAHALLY MYSORE","course_name":"ELECTRONICS AND COMMUNICATIO N ENGG","category":"GM","seat_type":"ROK","rounds":{"2025_R2":236309,"2025_R3":235324},"min_rank":235324,"max_rank":236309},{"college_code":"E314","college_name":"CAUVERY COLLEGE OF ENGINEERING KBL LAYOUT, ALANAHALLY MYSORE","course_name":"ELECTRONICS AND COMMUNICATION ENGG","category":"1G","seat_type":"ROK","rounds":{"2025_R1":115827},"min_rank":115827,"max_rank":115827},{"college_code":"E314","college_name":"CAUVERY COLLEGE OF ENGINEERING KBL LAYOUT, ALANAHALLY MYSORE","course_name":"ELECTRONICS AND COMMUNICATION ENGG","category":"2AG","seat_type":"ROK","rounds":{"2025_R1":127713},"min_rank":127713,"max_rank":127713},{"college_code":"E314","college_name":"CAUVERY COLLEGE OF ENGINEERING KBL LAYOUT, ALANAHALLY MYSORE","course_name":"ELECTRONICS AND COMMUNICATION ENGG","category":"2AH","seat_type":"ROK","rounds":{"2025_R1":142776},"min_rank":142776,"max_rank":142776},{"college_code":"E314","college_name":"CAUVERY COLLEGE OF ENGINEERING KBL LAYOUT, ALANAHALLY MYSORE","course_name":"ELECTRONICS AND COMMUNICATION ENGG","category":"2AR","seat_type":"ROK","rounds":{"2025_R1":132425},"min_rank":132425,"max_rank":132425},{"college_code":"E314","college_name":"CAUVERY COLLEGE OF ENGINEERING KBL LAYOUT, ALANAHALLY MYSORE","course_name":"ELECTRONICS AND COMMUNICATION ENGG","category":"2BG","seat_type":"ROK","rounds":{"2025_R1":130070},"min_rank":130070,"max_rank":130070},{"college_code":"E314","college_name":"CAUVERY COLLEGE OF ENGINEERING KBL LAYOUT, ALANAHALLY MYSORE","course_name":"ELECTRONICS AND COMMUNICATION ENGG","category":"3AG","seat_type":"ROK","rounds":{"2025_R1":115186},"min_rank":115186,"max_rank":115186},{"college_code":"E314","college_name":"CAUVERY COLLEGE OF ENGINEERING KBL LAYOUT, ALANAHALLY MYSORE","course_name":"ELECTRONICS AND COMMUNICATION ENGG","category":"3BG","seat_type":"ROK","rounds":{"2025_R1":119625},"min_rank":119625,"max_rank":119625},{"college_code":"E314","college_name":"CAUVERY COLLEGE OF ENGINEERING KBL LAYOUT, ALANAHALLY MYSORE","course_name":"ELECTRONICS AND COMMUNICATION ENGG","category":"GM","seat_type":"ROK","rounds":{"2025_R1":111474},"min_rank":111474,"max_rank":111474},{"college_code":"E314","college_name":"CAUVERY COLLEGE OF ENGINEERING KBL LAYOUT, ALANAHALLY MYSORE","course_name":"ELECTRONICS AND COMMUNICATION ENGG","category":"GMH","seat_type":"ROK","rounds":{"2025_R1":129279},"min_rank":129279,"max_rank":129279},{"college_code":"E314","college_name":"CAUVERY COLLEGE OF ENGINEERING KBL LAYOUT, ALANAHALLY MYSORE","course_name":"ELECTRONICS AND COMMUNICATION ENGG","category":"GMK","seat_type":"ROK","rounds":{"2025_R1":112837},"min_rank":112837,"max_rank":112837},{"college_code":"E314","college_name":"CAUVERY COLLEGE OF ENGINEERING KBL LAYOUT, ALANAHALLY MYSORE","course_name":"ELECTRONICS AND COMMUNICATION ENGG","category":"GMR","seat_type":"ROK","rounds":{"2025_R1":115651},"min_rank":115651,"max_rank":115651},{"college_code":"E314","college_name":"CAUVERY COLLEGE OF ENGINEERING KBL LAYOUT, ALANAHALLY MYSORE","course_name":"ELECTRONICS AND COMMUNICATION ENGG","category":"SCG","seat_type":"ROK","rounds":{"2025_R1":165108},"min_rank":165108,"max_rank":165108},{"college_code":"E314","college_name":"CAUVERY COLLEGE OF ENGINEERING KBL LAYOUT, ALANAHALLY MYSORE","course_name":"ELECTRONICS AND COMMUNICATION ENGG","category":"SCR","seat_type":"ROK","rounds":{"2025_R1":223811},"min_rank":223811,"max_rank":223811},{"college_code":"E314","college_name":"CAUVERY COLLEGE OF ENGINEERING KBL LAYOUT, ALANAHALLY MYSORE","course_name":"ELECTRONICS AND COMMUNICATION ENGG","category":"STG","seat_type":"ROK","rounds":{"2025_R1":196077},"min_rank":196077,"max_rank":196077},{"college_code":"E314","college_name":"CAUVERY COLLEGE OF ENGINEERING KBL LAYOUT, ALANAHALLY MYSORE","course_name":"INFORMATION SCIENCE AND ENGINEERING","category":"GM","seat_type":"ROK","rounds":{"2025_R1":119909,"2025_R2":218938,"2025_R3":204547},"min_rank":119909,"max_rank":218938},{"college_code":"E314","college_name":"CAUVERY COLLEGE OF ENGINEERING KBL LAYOUT, ALANAHALLY MYSORE","course_name":"INFORMATION SCIENCE AND ENGINEERING","category":"GMH","seat_type":"ROK","rounds":{"2025_R1":130633},"min_rank":130633,"max_rank":130633}],"suggestions":{"COMPUTER SCIENCE AND ENGG(ARTIFICIA L INTELLIGENCE AND MACHINE LEARNING)|GM|ROK":{"similarCollege":{"college":"Smt. Kamala & Sri Venkappa M.Agadi College of Engineering & Technology, Gadag SAVANUR ROAD, GULAGANJIKOPPA,LAXMESHWAR DIST: GADAG","college_code":"E134","branch":"COMPUTER SCIENCE AND ENGG(ARTIFICIA L INTELLIGENCE AND MACHINE LEARNING)","category":"GM"},"similarBranch":{"college":"CAUVERY COLLEGE OF ENGINEERING KBL LAYOUT, ALANAHALLY MYSORE","college_code":"E314","branch":"COMPUTER SCIENCE AND ENGINEERING (CYBER SECURITY)","category":"GM"}},"COMPUTER SCIENCE AND ENGG(ARTIFICIAL INTELLIGENCE AND MACHINE LEARNING)|1G|ROK":{"similarCollege":{"college":"NAVKIS COLLEGE OF ENGINEERING, KIADB Industrial Area,Thimmanahally, Hassan P.B.NO. 55, NH-48, KIADB INDUSTRIAL AREA, THIMMANAHALLY, HASSAN-573201","college_code":"E189","branch":"COMPUTER SCIENCE AND ENGG(ARTIFICIAL INTELLIGENCE AND MACHINE LEARNING)","category":"1G"},"similarBranch":{"college":"CAUVERY COLLEGE OF ENGINEERING KBL LAYOUT, ALANAHALLY MYSORE","college_code":"E314","branch":"ELECTRONICS AND COMMUNICATION ENGG","category":"1G"}},"COMPUTER SCIENCE AND ENGG(ARTIFICIAL INTELLIGENCE AND MACHINE LEARNING)|1H|ROK":{"similarCollege":{"college":"V S M`s Somashekhar R Kothiwale Institute of Technology,Nippani, Belgaum. BASAV-VIDYA NAGAR,BELGAUM","college_code":"E207","branch":"COMPUTER SCIENCE AND ENGG(ARTIFICIAL INTELLIGENCE AND MACHINE LEARNING)","category":"1H"},"similarBranch":null},"COMPUTER SCIENCE AND ENGG(ARTIFICIAL INTELLIGENCE AND MACHINE LEARNING)|2AG|ROK":{"similarCollege":{"college":"RATHINAM INSTITUTE OF TECHNOLOGY DODDAKAMMANAHALLY VILLAGE, BEGUR HOBLI,","college_code":"E311","branch":"COMPUTER SCIENCE AND ENGG(ARTIFICIAL INTELLIGENCE AND MACHINE LEARNING)","category":"2AG"},"similarBranch":{"college":"CAUVERY COLLEGE OF ENGINEERING KBL LAYOUT, ALANAHALLY MYSORE","college_code":"E314","branch":"ELECTRONICS AND COMMUNICATION ENGG","category":"2AG"}},"COMPUTER SCIENCE AND ENGG(ARTIFICIAL INTELLIGENCE AND MACHINE LEARNING)|2AR|ROK":{"similarCollege":{"college":"HARSHA INSTITUTE OF TECHNOLOGY VARADANAYAKANA HALLY VILLAGE, NELAMANGALA TALUK,","college_code":"E313","branch":"COMPUTER SCIENCE AND ENGG(ARTIFICIAL INTELLIGENCE AND MACHINE LEARNING)","category":"2AR"},"similarBranch":{"college":"CAUVERY COLLEGE OF ENGINEERING KBL LAYOUT, ALANAHALLY MYSORE","college_code":"E314","branch":"ELECTRONICS AND COMMUNICATION ENGG","category":"2AR"}},"COMPUTER SCIENCE AND ENGG(ARTIFICIAL INTELLIGENCE AND MACHINE LEARNING)|3BG|ROK":{"similarCollege":{"college":"RATHINAM INSTITUTE OF TECHNOLOGY DODDAKAMMANAHALLY VILLAGE, BEGUR HOBLI,","college_code":"E311","branch":"COMPUTER SCIENCE AND ENGG(ARTIFICIAL INTELLIGENCE AND MACHINE LEARNING)","category":"3BG"},"similarBranch":{"college":"CAUVERY COLLEGE OF ENGINEERING KBL LAYOUT, ALANAHALLY MYSORE","college_code":"E314","branch":"COMPUTER SCIENCE AND ENGINEERING(DAT A SCIENCE)","category":"3BG"}},"COMPUTER SCIENCE AND ENGG(ARTIFICIAL INTELLIGENCE AND MACHINE LEARNING)|GM|ROK":{"similarCollege":{"college":"K V G College of Engineering, Sullia KURUNJIBHAG,","college_code":"E054","branch":"COMPUTER SCIENCE AND ENGG(ARTIFICIAL INTELLIGENCE AND MACHINE LEARNING)","category":"GM"},"similarBranch":{"college":"CAUVERY COLLEGE OF ENGINEERING KBL LAYOUT, ALANAHALLY MYSORE","college_code":"E314","branch":"ELECTRONICS AND COMMUNICATION ENGG","category":"GM"}},"COMPUTER SCIENCE AND ENGG(ARTIFICIAL INTELLIGENCE AND MACHINE LEARNING)|GMK|ROK":{"similarCollege":{"college":"HARSHA INSTITUTE OF TECHNOLOGY VARADANAYAKANA HALLY VILLAGE, NELAMANGALA TALUK,","college_code":"E313","branch":"COMPUTER SCIENCE AND ENGG(ARTIFICIAL INTELLIGENCE AND MACHINE LEARNING)","category":"GMK"},"similarBranch":{"college":"CAUVERY COLLEGE OF ENGINEERING KBL LAYOUT, ALANAHALLY MYSORE","college_code":"E314","branch":"ELECTRONICS AND COMMUNICATION ENGG","category":"GMK"}},"COMPUTER SCIENCE AND ENGG(ARTIFICIAL INTELLIGENCE AND MACHINE LEARNING)|GMR|ROK":{"similarCollege":{"college":"RATHINAM INSTITUTE OF TECHNOLOGY DODDAKAMMANAHALLY VILLAGE, BEGUR HOBLI,","college_code":"E311","branch":"COMPUTER SCIENCE AND ENGG(ARTIFICIAL INTELLIGENCE AND MACHINE LEARNING)","category":"GMR"},"similarBranch":{"college":"CAUVERY COLLEGE OF ENGINEERING KBL LAYOUT, ALANAHALLY MYSORE","college_code":"E314","branch":"ELECTRONICS AND COMMUNICATION ENGG","category":"GMR"}},"COMPUTER SCIENCE AND ENGG(ARTIFICIAL INTELLIGENCE AND MACHINE LEARNING)|SCG|ROK":{"similarCollege":{"college":"V S M`s Somashekhar R Kothiwale Institute of Technology,Nippani, Belgaum. BASAV-VIDYA NAGAR,BELGAUM","college_code":"E207","branch":"COMPUTER SCIENCE AND ENGG(ARTIFICIAL INTELLIGENCE AND MACHINE LEARNING)","category":"SCG"},"similarBranch":{"college":"CAUVERY COLLEGE OF ENGINEERING KBL LAYOUT, ALANAHALLY MYSORE","college_code":"E314","branch":"COMPUTER SCIENCE AND ENGINEERING(DAT A SCIENCE)","category":"SCG"}},"COMPUTER SCIENCE AND ENGG(ARTIFICIAL INTELLIGENCE AND MACHINE LEARNING)|SCR|ROK":{"similarCollege":{"college":"AKASH INTITUTE OF ENGINEERING AND TECHNOLOGY PRASANNAHALLI MAIN RAOD, AKKUPETE VILLAGE, KASABA HOBLI","college_code":"E300","branch":"COMPUTER SCIENCE AND ENGG(ARTIFICIAL INTELLIGENCE AND MACHINE LEARNING)","category":"SCR"},"similarBranch":{"college":"CAUVERY COLLEGE OF ENGINEERING KBL LAYOUT, ALANAHALLY MYSORE","college_code":"E314","branch":"ELECTRONICS AND COMMUNICATION ENGG","category":"SCR"}},"COMPUTER SCIENCE AND ENGG(ARTIFICIAL INTELLIGENCE AND MACHINE LEARNING)|STG|ROK":{"similarCollege":{"college":"K L S Viswanathrao Deshpande Institute of Technology, Haliyal UDYOG VIDYA NAGAR,DANDELI ROAD, HALIYAL-581329","college_code":"E135","branch":"COMPUTER SCIENCE AND ENGG(ARTIFICIAL INTELLIGENCE AND MACHINE LEARNING)","category":"STG"},"similarBranch":{"college":"CAUVERY COLLEGE OF ENGINEERING KBL LAYOUT, ALANAHALLY MYSORE","college_code":"E314","branch":"COMPUTER SCIENCE AND ENGINEERING(DAT A SCIENCE)","category":"STG"}},"COMPUTER SCIENCE AND ENGINEERING|GM|ROK":{"similarCollege":{"college":"M S Engineering College, Bangalore NAVARATHNA AGRAHARA, SADAHALLIPOST, NEAR BIAL, BANGALORE","college_code":"E127","branch":"COMPUTER SCIENCE AND ENGINEERING","category":"GM"},"similarBranch":{"college":"CAUVERY COLLEGE OF ENGINEERING KBL LAYOUT, ALANAHALLY MYSORE","college_code":"E314","branch":"COMPUTER SCIENCE AND ENGG(ARTIFICIA L INTELLIGENCE AND MACHINE LEARNING)","category":"GM"}},"COMPUTER SCIENCE AND ENGINEERING|GMH|ROK":{"similarCollege":{"college":"Moodalakatte Institute of Technology, Kundapura, Udupi MOODLAKATTE,KUNDAPURA TALUK,UDUPI DISTRICT","college_code":"E136","branch":"COMPUTER SCIENCE AND ENGINEERING","category":"GMH"},"similarBranch":{"college":"CAUVERY COLLEGE OF ENGINEERING KBL LAYOUT, ALANAHALLY MYSORE","college_code":"E314","branch":"COMPUTER SCIENCE AND ENGINEERING (CYBER SECURITY)","category":"GMH"}},"COMPUTER SCIENCE AND ENGINEERING|SCH|ROK":{"similarCollege":{"college":"Proudadevaraya Institute of Technology, Hospet SHAH BHAVARLAL BABULAL NAHAR CAMPUS,T.B.DAM ROAD, BESIDE TSP LIMITED,HOSPET - 583225,BELLARY DISTRICT","college_code":"E076","branch":"COMPUTER SCIENCE AND ENGINEERING","category":"SCH"},"similarBranch":null},"COMPUTER SCIENCE AND ENGINEERING (CYBER SECURITY)|GM|ROK":{"similarCollege":{"college":"NAVKIS COLLEGE OF ENGINEERING, KIADB Industrial Area,Thimmanahally, Hassan P.B.NO. 55, NH-48, KIADB INDUSTRIAL AREA, THIMMANAHALLY, HASSAN-573201","college_code":"E189","branch":"COMPUTER SCIENCE AND ENGINEERING (CYBER SECURITY)","category":"GM"},"similarBranch":{"college":"CAUVERY COLLEGE OF ENGINEERING KBL LAYOUT, ALANAHALLY MYSORE","college_code":"E314","branch":"COMPUTER SCIENCE AND ENGG(ARTIFICIAL INTELLIGENCE AND MACHINE LEARNING)","category":"GM"}},"COMPUTER SCIENCE AND ENGINEERING (CYBER SECURITY)|GMH|ROK":{"similarCollege":{"college":"Srinivas University SRINIVAS CAMPUS MUKKA MANGALURU","college_code":"E193","branch":"COMPUTER SCIENCE AND ENGINEERING (CYBER SECURITY)","category":"GMH"},"similarBranch":{"college":"CAUVERY COLLEGE OF ENGINEERING KBL LAYOUT, ALANAHALLY MYSORE","college_code":"E314","branch":"ELECTRONICS AND COMMUNICATION ENGG","category":"GMH"}},"COMPUTER SCIENCE AND ENGINEERING (CYBER SECURITY)|GMRH|ROK":{"similarCollege":{"college":"AKASH INTITUTE OF ENGINEERING AND TECHNOLOGY PRASANNAHALLI MAIN RAOD, AKKUPETE VILLAGE, KASABA HOBLI","college_code":"E300","branch":"COMPUTER SCIENCE AND ENGINEERING (CYBER SECURITY)","category":"GMRH"},"similarBranch":null},"COMPUTER SCIENCE AND ENGINEERING(D ATA SCIENCE)|GM|ROK":{"similarCollege":{"college":"Yenepoya Institute Of Technology, Mangalore VIDYANAGAR N.H 13THODAR MIJAR POST MOODBIDRI MANGALORE TQ","college_code":"E165","branch":"COMPUTER SCIENCE AND ENGINEERING(D ATA SCIENCE)","category":"GM"},"similarBranch":{"college":"CAUVERY COLLEGE OF ENGINEERING KBL LAYOUT, ALANAHALLY MYSORE","college_code":"E314","branch":"COMPUTER SCIENCE AND ENGINEERING","category":"GM"}},"COMPUTER SCIENCE AND ENGINEERING(DAT A SCIENCE)|2AG|ROK":{"similarCollege":{"college":"HARSHA INSTITUTE OF TECHNOLOGY VARADANAYAKANA HALLY VILLAGE, NELAMANGALA TALUK,","college_code":"E313","branch":"COMPUTER SCIENCE AND ENGINEERING(DAT A SCIENCE)","category":"2AG"},"similarBranch":{"college":"CAUVERY COLLEGE OF ENGINEERING KBL LAYOUT, ALANAHALLY MYSORE","college_code":"E314","branch":"COMPUTER SCIENCE AND ENGG(ARTIFICIAL INTELLIGENCE AND MACHINE LEARNING)","category":"2AG"}},"COMPUTER SCIENCE AND ENGINEERING(DAT A SCIENCE)|2BG|ROK":{"similarCollege":{"college":"Karavali Institute of Technology, Neermarga, Mangalore PADU POST, VIA PEDUMALE,NEERUMARGA,MANGALORE -575029","college_code":"E159","branch":"COMPUTER SCIENCE AND ENGINEERING(DAT A SCIENCE)","category":"2BG"},"similarBranch":{"college":"CAUVERY COLLEGE OF ENGINEERING KBL LAYOUT, ALANAHALLY MYSORE","college_code":"E314","branch":"ELECTRONICS AND COMMUNICATION ENGG","category":"2BG"}},"COMPUTER SCIENCE AND ENGINEERING(DAT A SCIENCE)|3AG|ROK":{"similarCollege":{"college":"Karavali Institute of Technology, Neermarga, Mangalore PADU POST, VIA PEDUMALE,NEERUMARGA,MANGALORE -575029","college_code":"E159","branch":"COMPUTER SCIENCE AND ENGINEERING(DAT A SCIENCE)","category":"3AG"},"similarBranch":{"college":"CAUVERY COLLEGE OF ENGINEERING KBL LAYOUT, ALANAHALLY MYSORE","college_code":"E314","branch":"ELECTRONICS AND COMMUNICATION ENGG","category":"3AG"}},"COMPUTER SCIENCE AND ENGINEERING(DAT A SCIENCE)|3AR|ROK":{"similarCollege":{"college":"R. V. College of Engineering, Bangalore(AUTONOMOUS) R.V. VIDYANIKETAN POST, MYSORE ROAD,BANGALORE","college_code":"E005","branch":"COMPUTER SCIENCE AND ENGINEERING(DAT A SCIENCE)","category":"3AR"},"similarBranch":null},"COMPUTER SCIENCE AND ENGINEERING(DAT A SCIENCE)|3BG|ROK":{"similarCollege":{"college":"Karavali Institute of Technology, Neermarga, Mangalore PADU POST, VIA PEDUMALE,NEERUMARGA,MANGALORE -575029","college_code":"E159","branch":"COMPUTER SCIENCE AND ENGINEERING(DAT A SCIENCE)","category":"3BG"},"similarBranch":{"college":"CAUVERY COLLEGE OF ENGINEERING KBL LAYOUT, ALANAHALLY MYSORE","college_code":"E314","branch":"ELECTRONICS AND COMMUNICATION ENGG","category":"3BG"}},"COMPUTER SCIENCE AND ENGINEERING(DAT A SCIENCE)|3BR|ROK":{"similarCollege":{"college":"RNS Institute of Technology, Bangalore (AUTONOMOUS) CHANNASANDRA,UTTARAHALLI -KENGERI MAIN ROAD,SUBRAMANYAPURA POST,BANGALORE","college_code":"E118","branch":"COMPUTER SCIENCE AND ENGINEERING(DAT A SCIENCE)","category":"3BR"},"similarBranch":null},"COMPUTER SCIENCE AND ENGINEERING(DAT A SCIENCE)|GM|ROK":{"similarCollege":{"college":"RATHINAM INSTITUTE OF TECHNOLOGY DODDAKAMMANAHALLY VILLAGE, BEGUR HOBLI,","college_code":"E311","branch":"COMPUTER SCIENCE AND ENGINEERING(DAT A SCIENCE)","category":"GM"},"similarBranch":{"college":"CAUVERY COLLEGE OF ENGINEERING KBL LAYOUT, ALANAHALLY MYSORE","college_code":"E314","branch":"INFORMATION SCIENCE AND ENGINEERING","category":"GM"}},"COMPUTER SCIENCE AND ENGINEERING(DAT A SCIENCE)|GMKH|HK":{"similarCollege":{"college":"Karavali Institute of Technology, Neermarga, Mangalore PADU POST, VIA PEDUMALE,NEERUMARGA,MANGALORE -575029","college_code":"E159","branch":"COMPUTER SCIENCE AND ENGINEERING(DAT A SCIENCE)","category":"GMKH"},"similarBranch":null},"COMPUTER SCIENCE AND ENGINEERING(DAT A SCIENCE)|GMKH|ROK":{"similarCollege":{"college":"Karavali Institute of Technology, Neermarga, Mangalore PADU POST, VIA PEDUMALE,NEERUMARGA,MANGALORE -575029","college_code":"E159","branch":"COMPUTER SCIENCE AND ENGINEERING(DAT A SCIENCE)","category":"GMKH"},"similarBranch":null},"COMPUTER SCIENCE AND ENGINEERING(DAT A SCIENCE)|GMR|ROK":{"similarCollege":{"college":"RATHINAM INSTITUTE OF TECHNOLOGY DODDAKAMMANAHALLY VILLAGE, BEGUR HOBLI,","college_code":"E311","branch":"COMPUTER SCIENCE AND ENGINEERING(DAT A SCIENCE)","category":"GMR"},"similarBranch":{"college":"CAUVERY COLLEGE OF ENGINEERING KBL LAYOUT, ALANAHALLY MYSORE","college_code":"E314","branch":"COMPUTER SCIENCE AND ENGG(ARTIFICIAL INTELLIGENCE AND MACHINE LEARNING)","category":"GMR"}},"COMPUTER SCIENCE AND ENGINEERING(DAT A SCIENCE)|SCG|ROK":{"similarCollege":{"college":"AKASH INTITUTE OF ENGINEERING AND TECHNOLOGY PRASANNAHALLI MAIN RAOD, AKKUPETE VILLAGE, KASABA HOBLI","college_code":"E300","branch":"COMPUTER SCIENCE AND ENGINEERING(DAT A SCIENCE)","category":"SCG"},"similarBranch":{"college":"CAUVERY COLLEGE OF ENGINEERING KBL LAYOUT, ALANAHALLY MYSORE","college_code":"E314","branch":"ELECTRONICS AND COMMUNICATION ENGG","category":"SCG"}},"COMPUTER SCIENCE AND ENGINEERING(DAT A SCIENCE)|STG|ROK":{"similarCollege":{"college":"GANDHI INSTITUTE OF TECHNOLOGY AND MANAGEMENT GITAM OFF CAMPUS BENGALURU NH 207, Nagadenehalli Doddaballapur taluk. Bengaluru-561203","college_code":"E255","branch":"COMPUTER SCIENCE AND ENGINEERING(DAT A SCIENCE)","category":"STG"},"similarBranch":{"college":"CAUVERY COLLEGE OF ENGINEERING KBL LAYOUT, ALANAHALLY MYSORE","college_code":"E314","branch":"ELECTRONICS AND COMMUNICATION ENGG","category":"STG"}},"ELECTRONICS AND COMMUNICATIO N ENGG|GM|ROK":{"similarCollege":{"college":"AKASH INTITUTE OF ENGINEERING AND TECHNOLOGY PRASANNAHALLI MAIN RAOD, AKKUPETE VILLAGE, KASABA HOBLI","college_code":"E300","branch":"ELECTRONICS AND COMMUNICATIO N ENGG","category":"GM"},"similarBranch":{"college":"CAUVERY COLLEGE OF ENGINEERING KBL LAYOUT, ALANAHALLY MYSORE","college_code":"E314","branch":"COMPUTER SCIENCE AND ENGINEERING(D ATA SCIENCE)","category":"GM"}},"ELECTRONICS AND COMMUNICATION ENGG|1G|ROK":{"similarCollege":{"college":"R.T.E. Soceity's Rural Engineering College, Hulkoti HULKOTI -582 205,GADAG","college_code":"E032","branch":"ELECTRONICS AND COMMUNICATION ENGG","category":"1G"},"similarBranch":{"college":"CAUVERY COLLEGE OF ENGINEERING KBL LAYOUT, ALANAHALLY MYSORE","college_code":"E314","branch":"COMPUTER SCIENCE AND ENGG(ARTIFICIAL INTELLIGENCE AND MACHINE LEARNING)","category":"1G"}},"ELECTRONICS AND COMMUNICATION ENGG|2AG|ROK":{"similarCollege":{"college":"G Madegowda Institute of Technology, Bharathinagara, Maddur, Mandya BHARATHINAGARA (K M DODDY) MADDUR TQ,MANDYA","college_code":"E210","branch":"ELECTRONICS AND COMMUNICATION ENGG","category":"2AG"},"similarBranch":{"college":"CAUVERY COLLEGE OF ENGINEERING KBL LAYOUT, ALANAHALLY MYSORE","college_code":"E314","branch":"COMPUTER SCIENCE AND ENGINEERING(DAT A SCIENCE)","category":"2AG"}},"ELECTRONICS AND COMMUNICATION ENGG|2AH|ROK":{"similarCollege":{"college":"Rajeev Institute of Technology, Hassan PLOT 1-D(P-1), GROWTH CENTRE, INDUSTRIAL AREA, BANGALORE MANGALORE BYPASS ROAD","college_code":"E177","branch":"ELECTRONICS AND COMMUNICATION ENGG","category":"2AH"},"similarBranch":null},"ELECTRONICS AND COMMUNICATION ENGG|2AR|ROK":{"similarCollege":{"college":"HARSHA INSTITUTE OF TECHNOLOGY VARADANAYAKANA HALLY VILLAGE, NELAMANGALA TALUK,","college_code":"E313","branch":"ELECTRONICS AND COMMUNICATION ENGG","category":"2AR"},"similarBranch":{"college":"CAUVERY COLLEGE OF ENGINEERING KBL LAYOUT, ALANAHALLY MYSORE","college_code":"E314","branch":"COMPUTER SCIENCE AND ENGG(ARTIFICIAL INTELLIGENCE AND MACHINE LEARNING)","category":"2AR"}},"ELECTRONICS AND COMMUNICATION ENGG|2BG|ROK":{"similarCollege":{"college":"Coorg Institute of Technology, Kunda, Ponnampet POST BOX NO.11,COORG","college_code":"E094","branch":"ELECTRONICS AND COMMUNICATION ENGG","category":"2BG"},"similarBranch":{"college":"CAUVERY COLLEGE OF ENGINEERING KBL LAYOUT, ALANAHALLY MYSORE","college_code":"E314","branch":"COMPUTER SCIENCE AND ENGINEERING(DAT A SCIENCE)","category":"2BG"}},"ELECTRONICS AND COMMUNICATION ENGG|3AG|ROK":{"similarCollege":{"college":"P A College of Engineering, Kairangal, Bantwala Tq,. Mangalore NADUPADAV, NEAR MANGALORE UNIVERSITY,MONTEPADAV POST, KAIRANGALA VILLAGE,BANTWAL-MANGALORE","college_code":"E055","branch":"ELECTRONICS AND COMMUNICATION ENGG","category":"3AG"},"similarBranch":{"college":"CAUVERY COLLEGE OF ENGINEERING KBL LAYOUT, ALANAHALLY MYSORE","college_code":"E314","branch":"COMPUTER SCIENCE AND ENGINEERING(DAT A SCIENCE)","category":"3AG"}},"ELECTRONICS AND COMMUNICATION ENGG|3BG|ROK":{"similarCollege":{"college":"Navodaya Institute of Technology, Raichur(AUTONOMOUS) NAVODAYA NAGAR, MANATRALAYAM ROAD, RAICHUR","college_code":"E176","branch":"ELECTRONICS AND COMMUNICATION ENGG","category":"3BG"},"similarBranch":{"college":"CAUVERY COLLEGE OF ENGINEERING KBL LAYOUT, ALANAHALLY MYSORE","college_code":"E314","branch":"COMPUTER SCIENCE AND ENGG(ARTIFICIAL INTELLIGENCE AND MACHINE LEARNING)","category":"3BG"}},"ELECTRONICS AND COMMUNICATION ENGG|GM|ROK":{"similarCollege":{"college":"P A College of Engineering, Kairangal, Bantwala Tq,. Mangalore NADUPADAV, NEAR MANGALORE UNIVERSITY,MONTEPADAV POST, KAIRANGALA VILLAGE,BANTWAL-MANGALORE","college_code":"E055","branch":"ELECTRONICS AND COMMUNICATION ENGG","category":"GM"},"similarBranch":{"college":"CAUVERY COLLEGE OF ENGINEERING KBL LAYOUT, ALANAHALLY MYSORE","college_code":"E314","branch":"COMPUTER SCIENCE AND ENGINEERING(DAT A SCIENCE)","category":"GM"}},"ELECTRONICS AND COMMUNICATION ENGG|GMH|ROK":{"similarCollege":{"college":"Government Engineering College,Naragund,Gadag","college_code":"E291","branch":"ELECTRONICS AND COMMUNICATION ENGG","category":"GMH"},"similarBranch":{"college":"CAUVERY COLLEGE OF ENGINEERING KBL LAYOUT, ALANAHALLY MYSORE","college_code":"E314","branch":"INFORMATION SCIENCE AND ENGINEERING","category":"GMH"}},"ELECTRONICS AND COMMUNICATION ENGG|GMK|ROK":{"similarCollege":{"college":"Government Engineering College, Karwar MAJALI VILLAGE, KARWAR TALUK, UTTARA KANNADA DIST, KARNATAKA -PIN 581345","college_code":"E194","branch":"ELECTRONICS AND COMMUNICATION ENGG","category":"GMK"},"similarBranch":{"college":"CAUVERY COLLEGE OF ENGINEERING KBL LAYOUT, ALANAHALLY MYSORE","college_code":"E314","branch":"COMPUTER SCIENCE AND ENGG(ARTIFICIAL INTELLIGENCE AND MACHINE LEARNING)","category":"GMK"}},"ELECTRONICS AND COMMUNICATION ENGG|GMR|ROK":{"similarCollege":{"college":"Akshaya Institute of Technology, Lingapura, Tumkur Dist. LINGAPURA","college_code":"E191","branch":"ELECTRONICS AND COMMUNICATION ENGG","category":"GMR"},"similarBranch":{"college":"CAUVERY COLLEGE OF ENGINEERING KBL LAYOUT, ALANAHALLY MYSORE","college_code":"E314","branch":"COMPUTER SCIENCE AND ENGINEERING(DAT A SCIENCE)","category":"GMR"}},"ELECTRONICS AND COMMUNICATION ENGG|SCG|ROK":{"similarCollege":{"college":"G Madegowda Institute of Technology, Bharathinagara, Maddur, Mandya BHARATHINAGARA (K M DODDY) MADDUR TQ,MANDYA","college_code":"E210","branch":"ELECTRONICS AND COMMUNICATION ENGG","category":"SCG"},"similarBranch":{"college":"CAUVERY COLLEGE OF ENGINEERING KBL LAYOUT, ALANAHALLY MYSORE","college_code":"E314","branch":"COMPUTER SCIENCE AND ENGG(ARTIFICIAL INTELLIGENCE AND MACHINE LEARNING)","category":"SCG"}},"ELECTRONICS AND COMMUNICATION ENGG|SCR|ROK":{"similarCollege":{"college":"Vemana Institute of Technology, Bangalore #1, MAHAYOGI VEMANA ROAD, 3RD BLOCK, KORMANGALA, BANGALORE -560034.","college_code":"E092","branch":"ELECTRONICS AND COMMUNICATION ENGG","category":"SCR"},"similarBranch":{"college":"CAUVERY COLLEGE OF ENGINEERING KBL LAYOUT, ALANAHALLY MYSORE","college_code":"E314","branch":"COMPUTER SCIENCE AND ENGG(ARTIFICIAL INTELLIGENCE AND MACHINE LEARNING)","category":"SCR"}},"ELECTRONICS AND COMMUNICATION ENGG|STG|ROK":{"similarCollege":{"college":"Amrutha Institute of Engineering & Management Science (AIEMS), Ramanagar BIDADI INDUSTRIAL AREA, OFF MYSORE ROAD, NEAR TOYOTA KIRLOSKAR MOTORS, BMRDA REGION, BANGALORE","college_code":"E168","branch":"ELECTRONICS AND COMMUNICATION ENGG","category":"STG"},"similarBranch":{"college":"CAUVERY COLLEGE OF ENGINEERING KBL LAYOUT, ALANAHALLY MYSORE","college_code":"E314","branch":"COMPUTER SCIENCE AND ENGG(ARTIFICIAL INTELLIGENCE AND MACHINE LEARNING)","category":"STG"}},"INFORMATION SCIENCE AND ENGINEERING|GM|ROK":{"similarCollege":{"college":"Smt. Kamala & Sri Venkappa M.Agadi College of Engineering & Technology, Gadag SAVANUR ROAD, GULAGANJIKOPPA,LAXMESHWAR DIST: GADAG","college_code":"E134","branch":"INFORMATION SCIENCE AND ENGINEERING","category":"GM"},"similarBranch":{"college":"CAUVERY COLLEGE OF ENGINEERING KBL LAYOUT, ALANAHALLY MYSORE","college_code":"E314","branch":"ELECTRONICS AND COMMUNICATIO N ENGG","category":"GM"}},"INFORMATION SCIENCE AND ENGINEERING|GMH|ROK":{"similarCollege":{"college":"A J Institute Of Engineering And Technology.Kottar chowki Boloor Village Mangalore KOTTARA CHOWKI BOLOOR VILLAGE,DAKSHINA KANNADA","college_code":"E254","branch":"INFORMATION SCIENCE AND ENGINEERING","category":"GMH"},"similarBranch":{"college":"CAUVERY COLLEGE OF ENGINEERING KBL LAYOUT, ALANAHALLY MYSORE","college_code":"E314","branch":"COMPUTER SCIENCE AND ENGINEERING","category":"GMH"}}}}