{"cutoffs":[{"college_code":"E031","college_name":"B V V Sangha`s Basaveshwara Engineering College , Bagalkote (AUTONOMOUS) NIJALINGAPPA ROAD,BAGALKOT 587102","course_name":"CIVIL ENGINEERING","category":"2AG","seat_type":"ROK","rounds":{"2024_R1":112681,"2024_R2":144067,"2024_R3":223912,"2025_R1":126300,"2025_R2":190697,"2025_R3":185519},"min_rank":112681,"max_rank":223912},{"college_code":"E031","college_name":"B V V Sangha`s Basaveshwara Engineering College , Bagalkote (AUTONOMOUS) NIJALINGAPPA ROAD,BAGALKOT 587102","course_name":"CIVIL ENGINEERING","category":"2AH","seat_type":"ROK","rounds":{"2025_R1":163458},"min_rank":163458,"max_rank":163458},{"college_code":"E031","college_name":"B V V Sangha`s Basaveshwara Engineering College , Bagalkote (AUTONOMOUS) NIJALINGAPPA ROAD,BAGALKOT 587102","course_name":"CIVIL ENGINEERING","category":"3BG","seat_type":"ROK","rounds":{"2024_R1":112854,"2024_R2":135993,"2024_R3":202304,"2025_R1":110997,"2025_R2":181986,"2025_R3":181986},"min_rank":110997,"max_rank":202304},{"college_code":"E031","college_name":"B V V Sangha`s Basaveshwara Engineering College , Bagalkote (AUTONOMOUS) NIJALINGAPPA ROAD,BAGALKOT 587102","course_name":"CIVIL ENGINEERING","category":"GM","seat_type":"ROK","rounds":{"2024_R1":90632,"2024_R2":100950,"2024_R3":106577,"2025_R1":102352,"2025_R2":134257,"2025_R3":152936},"min_rank":90632,"max_rank":152936},{"college_code":"E031","college_name":"B V V Sangha`s Basaveshwara Engineering College , Bagalkote (AUTONOMOUS) NIJALINGAPPA ROAD,BAGALKOT 587102","course_name":"CIVIL ENGINEERING","category":"GMH","seat_type":"HK","rounds":{"2025_R1":115486,"2025_R2":145027,"2025_R3":173870},"min_rank":115486,"max_rank":173870},{"college_code":"E031","college_name":"B V V Sangha`s Basaveshwara Engineering College , Bagalkote (AUTONOMOUS) NIJALINGAPPA ROAD,BAGALKOT 587102","course_name":"CIVIL ENGINEERING","category":"GMH","seat_type":"ROK","rounds":{"2025_R1":115486},"min_rank":115486,"max_rank":115486},{"college_code":"E031","college_name":"B V V Sangha`s Basaveshwara Engineering College , Bagalkote (AUTONOMOUS) NIJALINGAPPA ROAD,BAGALKOT 587102","course_name":"CIVIL ENGINEERING","category":"GMK","seat_type":"ROK","rounds":{"2024_R1":96178,"2024_R2":109126,"2024_R3":115487,"2025_R1":112182,"2025_R2":149700,"2025_R3":156008},"min_rank":96178,"max_rank":156008},{"college_code":"E031","college_name":"B V V Sangha`s Basaveshwara Engineering College , Bagalkote (AUTONOMOUS) NIJALINGAPPA ROAD,BAGALKOT 587102","course_name":"CIVIL ENGINEERING","category":"GMR","seat_type":"ROK","rounds":{"2024_R1":109126,"2024_R2":120771,"2024_R3":132217,"2025_R1":126468,"2025_R2":163485,"2025_R3":176405},"min_rank":109126,"max_rank":176405},{"college_code":"E031","college_name":"B V V Sangha`s Basaveshwara Engineering College , Bagalkote (AUTONOMOUS) NIJALINGAPPA ROAD,BAGALKOT 587102","course_name":"CIVIL ENGINEERING","category":"SCG","seat_type":"ROK","rounds":{"2024_R1":143301,"2024_R2":165776,"2024_R3":240526,"2025_R1":156628,"2025_R2":168194,"2025_R3":240136},"min_rank":143301,"max_rank":240526},{"college_code":"E031","college_name":"B V V Sangha`s Basaveshwara Engineering College , Bagalkote (AUTONOMOUS) NIJALINGAPPA ROAD,BAGALKOT 587102","course_name":"CIVIL ENGINEERING","category":"SCH","seat_type":"ROK","rounds":{"2025_R1":165220},"min_rank":165220,"max_rank":165220},{"college_code":"E031","college_name":"B V V Sangha`s Basaveshwara Engineering College , Bagalkote (AUTONOMOUS) NIJALINGAPPA ROAD,BAGALKOT 587102","course_name":"CIVIL ENGINEERING","category":"SCK","seat_type":"ROK","rounds":{"2024_R1":143324,"2024_R2":167094,"2024_R3":269834,"2025_R1":172388,"2025_R2":220794,"2025_R3":245422},"min_rank":143324,"max_rank":269834},{"college_code":"E031","college_name":"B V V Sangha`s Basaveshwara Engineering College , Bagalkote (AUTONOMOUS) NIJALINGAPPA ROAD,BAGALKOT 587102","course_name":"CIVIL ENGINEERING","category":"SCR","seat_type":"ROK","rounds":{"2024_R1":165203,"2024_R2":220447,"2024_R3":null,"2025_R1":176405,"2025_R2":247196,"2025_R3":248247},"min_rank":165203,"max_rank":248247},{"college_code":"E031","college_name":"B V V Sangha`s Basaveshwara Engineering College , Bagalkote (AUTONOMOUS) NIJALINGAPPA ROAD,BAGALKOT 587102","course_name":"CIVIL ENGINEERING","category":"SCRH","seat_type":"ROK","rounds":{"2025_R1":204901},"min_rank":204901,"max_rank":204901},{"college_code":"E031","college_name":"B V V Sangha`s Basaveshwara Engineering College , Bagalkote (AUTONOMOUS) NIJALINGAPPA ROAD,BAGALKOT 587102","course_name":"CIVIL ENGINEERING","category":"STG","seat_type":"ROK","rounds":{"2024_R1":149350,"2024_R2":246573,"2024_R3":246573,"2025_R1":178069,"2025_R2":217740,"2025_R3":232343},"min_rank":149350,"max_rank":246573},{"college_code":"E031","college_name":"B V V Sangha`s Basaveshwara Engineering College , Bagalkote (AUTONOMOUS) NIJALINGAPPA ROAD,BAGALKOT 587102","course_name":"CIVIL ENGINEERING","category":"STH","seat_type":"ROK","rounds":{"2025_R1":179515},"min_rank":179515,"max_rank":179515},{"college_code":"E031","college_name":"B V V Sangha`s Basaveshwara Engineering College , Bagalkote (AUTONOMOUS) NIJALINGAPPA ROAD,BAGALKOT 587102","course_name":"COMPUTER SCIENCE AND ENGINEERING","category":"1G","seat_type":"ROK","rounds":{"2024_R1":21606,"2024_R2":35352,"2024_R3":35352,"2025_R1":25042,"2025_R2":28473,"2025_R3":31649},"min_rank":21606,"max_rank":35352},{"college_code":"E031","college_name":"B V V Sangha`s Basaveshwara Engineering College , Bagalkote (AUTONOMOUS) NIJALINGAPPA ROAD,BAGALKOT 587102","course_name":"COMPUTER SCIENCE AND ENGINEERING","category":"1R","seat_type":"ROK","rounds":{"2024_R1":null,"2024_R2":null,"2024_R3":null,"2025_R1":28473,"2025_R2":30113,"2025_R3":75767},"min_rank":28473,"max_rank":75767},{"college_code":"E031","college_name":"B V V Sangha`s Basaveshwara Engineering College , Bagalkote (AUTONOMOUS) NIJALINGAPPA ROAD,BAGALKOT 587102","course_name":"COMPUTER SCIENCE AND ENGINEERING","category":"2AG","seat_type":"ROK","rounds":{"2024_R1":24636,"2024_R2":24762,"2024_R3":26722,"2025_R1":21942,"2025_R2":27843,"2025_R3":28188},"min_rank":21942,"max_rank":28188},{"college_code":"E031","college_name":"B V V Sangha`s Basaveshwara Engineering College , Bagalkote (AUTONOMOUS) NIJALINGAPPA ROAD,BAGALKOT 587102","course_name":"COMPUTER SCIENCE AND ENGINEERING","category":"2AH","seat_type":"HK","rounds":{"2025_R1":25382,"2025_R2":30772,"2025_R3":30772},"min_rank":25382,"max_rank":30772},{"college_code":"E031","college_name":"B V V Sangha`s Basaveshwara Engineering College , Bagalkote (AUTONOMOUS) NIJALINGAPPA ROAD,BAGALKOT 587102","course_name":"COMPUTER SCIENCE AND ENGINEERING","category":"2AH","seat_type":"ROK","rounds":{"2025_R1":25382},"min_rank":25382,"max_rank":25382},{"college_code":"E031","college_name":"B V V Sangha`s Basaveshwara Engineering College , Bagalkote (AUTONOMOUS) NIJALINGAPPA ROAD,BAGALKOT 587102","course_name":"COMPUTER SCIENCE AND ENGINEERING","category":"2AR","seat_type":"ROK","rounds":{"2024_R1":25072,"2024_R2":25072,"2024_R3":29236,"2025_R1":22246,"2025_R2":28188,"2025_R3":28290},"min_rank":22246,"max_rank":29236},{"college_code":"E031","college_name":"B V V Sangha`s Basaveshwara Engineering College , Bagalkote (AUTONOMOUS) NIJALINGAPPA ROAD,BAGALKOT 587102","course_name":"COMPUTER SCIENCE AND ENGINEERING","category":"2BG","seat_type":"ROK","rounds":{"2024_R1":27750,"2024_R2":27750,"2024_R3":27750,"2025_R1":28261,"2025_R2":36342,"2025_R3":36342},"min_rank":27750,"max_rank":36342},{"college_code":"E031","college_name":"B V V Sangha`s Basaveshwara Engineering College , Bagalkote (AUTONOMOUS) NIJALINGAPPA ROAD,BAGALKOT 587102","course_name":"COMPUTER SCIENCE AND ENGINEERING","category":"3AG","seat_type":"ROK","rounds":{"2024_R1":22500,"2024_R2":24398,"2024_R3":25876,"2025_R1":21059,"2025_R2":27473,"2025_R3":27473},"min_rank":21059,"max_rank":27473},{"college_code":"E031","college_name":"B V V Sangha`s Basaveshwara Engineering College , Bagalkote (AUTONOMOUS) NIJALINGAPPA ROAD,BAGALKOT 587102","course_name":"COMPUTER SCIENCE AND ENGINEERING","category":"3AH","seat_type":"HK","rounds":{"2025_R1":27473,"2025_R2":30704,"2025_R3":30704},"min_rank":27473,"max_rank":30704},{"college_code":"E031","college_name":"B V V Sangha`s Basaveshwara Engineering College , Bagalkote (AUTONOMOUS) NIJALINGAPPA ROAD,BAGALKOT 587102","course_name":"COMPUTER SCIENCE AND ENGINEERING","category":"3AH","seat_type":"ROK","rounds":{"2025_R1":27473},"min_rank":27473,"max_rank":27473},{"college_code":"E031","college_name":"B V V Sangha`s Basaveshwara Engineering College , Bagalkote (AUTONOMOUS) NIJALINGAPPA ROAD,BAGALKOT 587102","course_name":"COMPUTER SCIENCE AND ENGINEERING","category":"3BG","seat_type":"ROK","rounds":{"2024_R1":19532,"2024_R2":23608,"2024_R3":25020,"2025_R1":20603,"2025_R2":24315,"2025_R3":26013},"min_rank":19532,"max_rank":26013},{"college_code":"E031","college_name":"B V V Sangha`s Basaveshwara Engineering College , Bagalkote (AUTONOMOUS) NIJALINGAPPA ROAD,BAGALKOT 587102","course_name":"COMPUTER SCIENCE AND ENGINEERING","category":"3BK","seat_type":"ROK","rounds":{"2024_R1":null,"2024_R2":null,"2024_R3":null,"2025_R1":22107,"2025_R2":25064,"2025_R3":27432},"min_rank":22107,"max_rank":27432},{"college_code":"E031","college_name":"B V V Sangha`s Basaveshwara Engineering College , Bagalkote (AUTONOMOUS) NIJALINGAPPA ROAD,BAGALKOT 587102","course_name":"COMPUTER SCIENCE AND ENGINEERING","category":"GM","seat_type":"ROK","rounds":{"2024_R1":17684,"2024_R2":21640,"2024_R3":21776,"2025_R1":19827.5,"2025_R2":22902,"2025_R3":24315},"min_rank":17684,"max_rank":24315},{"college_code":"E031","college_name":"B V V Sangha`s Basaveshwara Engineering College , Bagalkote (AUTONOMOUS) NIJALINGAPPA ROAD,BAGALKOT 587102","course_name":"COMPUTER SCIENCE AND ENGINEERING","category":"GMH","seat_type":"HK","rounds":{"2025_R1":20144,"2025_R2":23265,"2025_R3":25382},"min_rank":20144,"max_rank":25382},{"college_code":"E031","college_name":"B V V Sangha`s Basaveshwara Engineering College , Bagalkote (AUTONOMOUS) NIJALINGAPPA ROAD,BAGALKOT 587102","course_name":"COMPUTER SCIENCE AND ENGINEERING","category":"GMH","seat_type":"ROK","rounds":{"2025_R1":20144},"min_rank":20144,"max_rank":20144},{"college_code":"E031","college_name":"B V V Sangha`s Basaveshwara Engineering College , Bagalkote (AUTONOMOUS) NIJALINGAPPA ROAD,BAGALKOT 587102","course_name":"COMPUTER SCIENCE AND ENGINEERING","category":"GMK","seat_type":"ROK","rounds":{"2024_R1":21640,"2024_R2":21776,"2024_R3":24762,"2025_R1":20304,"2025_R2":24626,"2025_R3":24626},"min_rank":20304,"max_rank":24762},{"college_code":"E031","college_name":"B V V Sangha`s Basaveshwara Engineering College , Bagalkote (AUTONOMOUS) NIJALINGAPPA ROAD,BAGALKOT 587102","course_name":"COMPUTER SCIENCE AND ENGINEERING","category":"GMR","seat_type":"ROK","rounds":{"2024_R1":22539,"2024_R2":24175,"2024_R3":25234,"2025_R1":20563,"2025_R2":24391,"2025_R3":25064},"min_rank":20563,"max_rank":25234},{"college_code":"E031","college_name":"B V V Sangha`s Basaveshwara Engineering College , Bagalkote (AUTONOMOUS) NIJALINGAPPA ROAD,BAGALKOT 587102","course_name":"COMPUTER SCIENCE AND ENGINEERING","category":"GMRH","seat_type":"HK","rounds":{"2025_R1":27154,"2025_R2":27154,"2025_R3":27154},"min_rank":27154,"max_rank":27154},{"college_code":"E031","college_name":"B V V Sangha`s Basaveshwara Engineering College , Bagalkote (AUTONOMOUS) NIJALINGAPPA ROAD,BAGALKOT 587102","course_name":"COMPUTER SCIENCE AND ENGINEERING","category":"GMRH","seat_type":"ROK","rounds":{"2025_R1":27154},"min_rank":27154,"max_rank":27154},{"college_code":"E031","college_name":"B V V Sangha`s Basaveshwara Engineering College , Bagalkote (AUTONOMOUS) NIJALINGAPPA ROAD,BAGALKOT 587102","course_name":"COMPUTER SCIENCE AND ENGINEERING","category":"SCG","seat_type":"ROK","rounds":{"2024_R1":53515,"2024_R2":53735,"2024_R3":53735,"2025_R1":55301,"2025_R2":61734,"2025_R3":61734},"min_rank":53515,"max_rank":61734},{"college_code":"E031","college_name":"B V V Sangha`s Basaveshwara Engineering College , Bagalkote (AUTONOMOUS) NIJALINGAPPA ROAD,BAGALKOT 587102","course_name":"COMPUTER SCIENCE AND ENGINEERING","category":"SCK","seat_type":"ROK","rounds":{"2024_R1":null,"2024_R2":null,"2024_R3":null,"2025_R1":56799,"2025_R2":64865,"2025_R3":64865},"min_rank":56799,"max_rank":64865},{"college_code":"E031","college_name":"B V V Sangha`s Basaveshwara Engineering College , Bagalkote (AUTONOMOUS) NIJALINGAPPA ROAD,BAGALKOT 587102","course_name":"COMPUTER SCIENCE AND ENGINEERING","category":"SCR","seat_type":"ROK","rounds":{"2024_R1":53735,"2024_R2":61868,"2024_R3":61868,"2025_R1":59490,"2025_R2":72381,"2025_R3":72381},"min_rank":53735,"max_rank":72381},{"college_code":"E031","college_name":"B V V Sangha`s Basaveshwara Engineering College , Bagalkote (AUTONOMOUS) NIJALINGAPPA ROAD,BAGALKOT 587102","course_name":"COMPUTER SCIENCE AND ENGINEERING","category":"STG","seat_type":"ROK","rounds":{"2024_R1":60265,"2024_R2":61545,"2024_R3":63841,"2025_R1":58357,"2025_R2":73239,"2025_R3":73239},"min_rank":58357,"max_rank":73239},{"college_code":"E031","college_name":"B V V Sangha`s Basaveshwara Engineering College , Bagalkote (AUTONOMOUS) NIJALINGAPPA ROAD,BAGALKOT 587102","course_name":"COMPUTER SCIENCE AND ENGINEERING","category":"STR","seat_type":"ROK","rounds":{"2024_R1":63841,"2024_R2":63841,"2024_R3":84373,"2025_R1":60172,"2025_R2":85708,"2025_R3":85708},"min_rank":60172,"max_rank":85708},{"college_code":"E031","college_name":"B V V Sangha`s Basaveshwara Engineering College , Bagalkote (AUTONOMOUS) NIJALINGAPPA ROAD,BAGALKOT 587102","course_name":"ELECTRICAL & ELECTRONICS ENGINEERING","category":"1G","seat_type":"ROK","rounds":{"2024_R1":61202,"2024_R2":91373,"2024_R3":212336,"2025_R1":77431,"2025_R2":84839.5,"2025_R3":168346},"min_rank":61202,"max_rank":212336},{"college_code":"E031","college_name":"B V V Sangha`s Basaveshwara Engineering College , Bagalkote (AUTONOMOUS) NIJALINGAPPA ROAD,BAGALKOT 587102","course_name":"ELECTRICAL & ELECTRONICS ENGINEERING","category":"2AG","seat_type":"ROK","rounds":{"2024_R1":64855,"2024_R2":70732,"2024_R3":89734,"2025_R1":51317.5,"2025_R2":84378,"2025_R3":84378},"min_rank":51317.5,"max_rank":89734},{"college_code":"E031","college_name":"B V V Sangha`s Basaveshwara Engineering College , Bagalkote (AUTONOMOUS) NIJALINGAPPA ROAD,BAGALKOT 587102","course_name":"ELECTRICAL & ELECTRONICS ENGINEERING","category":"2AH","seat_type":"HK","rounds":{"2025_R1":58730,"2025_R2":84758,"2025_R3":84758},"min_rank":58730,"max_rank":84758},{"college_code":"E031","college_name":"B V V Sangha`s Basaveshwara Engineering College , Bagalkote (AUTONOMOUS) NIJALINGAPPA ROAD,BAGALKOT 587102","course_name":"ELECTRICAL & ELECTRONICS ENGINEERING","category":"2AH","seat_type":"ROK","rounds":{"2025_R1":58730},"min_rank":58730,"max_rank":58730},{"college_code":"E031","college_name":"B V V Sangha`s Basaveshwara Engineering College , Bagalkote (AUTONOMOUS) NIJALINGAPPA ROAD,BAGALKOT 587102","course_name":"ELECTRICAL & ELECTRONICS ENGINEERING","category":"2AR","seat_type":"ROK","rounds":{"2024_R1":66416,"2024_R2":71493,"2024_R3":90400,"2025_R1":57115,"2025_R2":86802,"2025_R3":93236},"min_rank":57115,"max_rank":93236},{"college_code":"E031","college_name":"B V V Sangha`s Basaveshwara Engineering College , Bagalkote (AUTONOMOUS) NIJALINGAPPA ROAD,BAGALKOT 587102","course_name":"ELECTRICAL & ELECTRONICS ENGINEERING","category":"2BG","seat_type":"ROK","rounds":{"2024_R1":87688,"2024_R2":87688,"2024_R3":87688,"2025_R1":67904,"2025_R2":67904,"2025_R3":67904},"min_rank":67904,"max_rank":87688},{"college_code":"E031","college_name":"B V V Sangha`s Basaveshwara Engineering College , Bagalkote (AUTONOMOUS) NIJALINGAPPA ROAD,BAGALKOT 587102","course_name":"ELECTRICAL & ELECTRONICS ENGINEERING","category":"2BK","seat_type":"ROK","rounds":{"2024_R1":null,"2024_R2":null,"2024_R3":null,"2025_R1":137659,"2025_R2":137659,"2025_R3":137659},"min_rank":137659,"max_rank":137659},{"college_code":"E031","college_name":"B V V Sangha`s Basaveshwara Engineering College , Bagalkote (AUTONOMOUS) NIJALINGAPPA ROAD,BAGALKOT 587102","course_name":"ELECTRICAL & ELECTRONICS ENGINEERING","category":"2BR","seat_type":"ROK","rounds":{"2024_R1":174661,"2024_R2":174661,"2024_R3":73806,"2025_R1":140210,"2025_R2":140210,"2025_R3":140210},"min_rank":73806,"max_rank":174661},{"college_code":"E031","college_name":"B V V Sangha`s Basaveshwara Engineering College , Bagalkote (AUTONOMOUS) NIJALINGAPPA ROAD,BAGALKOT 587102","course_name":"ELECTRICAL & ELECTRONICS ENGINEERING","category":"3AG","seat_type":"ROK","rounds":{"2024_R1":61113,"2024_R2":61113,"2024_R3":70090,"2025_R1":49991,"2025_R2":81272,"2025_R3":140401},"min_rank":49991,"max_rank":140401},{"college_code":"E031","college_name":"B V V Sangha`s Basaveshwara Engineering College , Bagalkote (AUTONOMOUS) NIJALINGAPPA ROAD,BAGALKOT 587102","course_name":"ELECTRICAL & ELECTRONICS ENGINEERING","category":"3BG","seat_type":"ROK","rounds":{"2024_R1":55806,"2024_R2":65198,"2024_R3":81496,"2025_R1":47602,"2025_R2":71890,"2025_R3":71890},"min_rank":47602,"max_rank":81496},{"college_code":"E031","college_name":"B V V Sangha`s Basaveshwara Engineering College , Bagalkote (AUTONOMOUS) NIJALINGAPPA ROAD,BAGALKOT 587102","course_name":"ELECTRICAL & ELECTRONICS ENGINEERING","category":"GM","seat_type":"ROK","rounds":{"2024_R1":54031,"2024_R2":57666,"2024_R3":61202,"2025_R1":45831,"2025_R2":57261.5,"2025_R3":57277},"min_rank":45831,"max_rank":61202},{"college_code":"E031","college_name":"B V V Sangha`s Basaveshwara Engineering College , Bagalkote (AUTONOMOUS) NIJALINGAPPA ROAD,BAGALKOT 587102","course_name":"ELECTRICAL & ELECTRONICS ENGINEERING","category":"GMH","seat_type":"HK","rounds":{"2025_R1":46860,"2025_R2":64260,"2025_R3":64260},"min_rank":46860,"max_rank":64260},{"college_code":"E031","college_name":"B V V Sangha`s Basaveshwara Engineering College , Bagalkote (AUTONOMOUS) NIJALINGAPPA ROAD,BAGALKOT 587102","course_name":"ELECTRICAL & ELECTRONICS ENGINEERING","category":"GMH","seat_type":"ROK","rounds":{"2025_R1":46860},"min_rank":46860,"max_rank":46860},{"college_code":"E031","college_name":"B V V Sangha`s Basaveshwara Engineering College , Bagalkote (AUTONOMOUS) NIJALINGAPPA ROAD,BAGALKOT 587102","course_name":"ELECTRICAL & ELECTRONICS ENGINEERING","category":"GMK","seat_type":"ROK","rounds":{"2024_R1":55026,"2024_R2":60926,"2024_R3":62514,"2025_R1":47987,"2025_R2":61254,"2025_R3":61254},"min_rank":47987,"max_rank":62514},{"college_code":"E031","college_name":"B V V Sangha`s Basaveshwara Engineering College , Bagalkote (AUTONOMOUS) NIJALINGAPPA ROAD,BAGALKOT 587102","course_name":"ELECTRICAL & ELECTRONICS ENGINEERING","category":"GMR","seat_type":"ROK","rounds":{"2024_R1":57666,"2024_R2":63098,"2024_R3":68782,"2025_R1":55019,"2025_R2":69935,"2025_R3":69935},"min_rank":55019,"max_rank":69935},{"college_code":"E031","college_name":"B V V Sangha`s Basaveshwara Engineering College , Bagalkote (AUTONOMOUS) NIJALINGAPPA ROAD,BAGALKOT 587102","course_name":"ELECTRICAL & ELECTRONICS ENGINEERING","category":"GMRH","seat_type":"HK","rounds":{"2025_R1":64260,"2025_R2":71992,"2025_R3":71992},"min_rank":64260,"max_rank":71992},{"college_code":"E031","college_name":"B V V Sangha`s Basaveshwara Engineering College , Bagalkote (AUTONOMOUS) NIJALINGAPPA ROAD,BAGALKOT 587102","course_name":"ELECTRICAL & ELECTRONICS ENGINEERING","category":"GMRH","seat_type":"ROK","rounds":{"2025_R1":64260},"min_rank":64260,"max_rank":64260},{"college_code":"E031","college_name":"B V V Sangha`s Basaveshwara Engineering College , Bagalkote (AUTONOMOUS) NIJALINGAPPA ROAD,BAGALKOT 587102","course_name":"ELECTRICAL & ELECTRONICS ENGINEERING","category":"SCG","seat_type":"ROK","rounds":{"2024_R1":113673,"2024_R2":130400,"2024_R3":133759,"2025_R1":140095,"2025_R2":140095,"2025_R3":141185},"min_rank":113673,"max_rank":141185},{"college_code":"E031","college_name":"B V V Sangha`s Basaveshwara Engineering College , Bagalkote (AUTONOMOUS) NIJALINGAPPA ROAD,BAGALKOT 587102","course_name":"ELECTRICAL & ELECTRONICS ENGINEERING","category":"SCH","seat_type":"HK","rounds":{"2025_R1":165649,"2025_R2":165649,"2025_R3":165649},"min_rank":165649,"max_rank":165649},{"college_code":"E031","college_name":"B V V Sangha`s Basaveshwara Engineering College , Bagalkote (AUTONOMOUS) NIJALINGAPPA ROAD,BAGALKOT 587102","course_name":"ELECTRICAL & ELECTRONICS ENGINEERING","category":"SCH","seat_type":"ROK","rounds":{"2025_R1":165649},"min_rank":165649,"max_rank":165649},{"college_code":"E031","college_name":"B V V Sangha`s Basaveshwara Engineering College , Bagalkote (AUTONOMOUS) NIJALINGAPPA ROAD,BAGALKOT 587102","course_name":"ELECTRICAL & ELECTRONICS ENGINEERING","category":"SCR","seat_type":"ROK","rounds":{"2024_R1":151326,"2024_R2":151326,"2024_R3":151326,"2025_R1":155169,"2025_R2":155169,"2025_R3":155169},"min_rank":151326,"max_rank":155169},{"college_code":"E031","college_name":"B V V Sangha`s Basaveshwara Engineering College , Bagalkote (AUTONOMOUS) NIJALINGAPPA ROAD,BAGALKOT 587102","course_name":"ELECTRICAL & ELECTRONICS ENGINEERING","category":"STG","seat_type":"ROK","rounds":{"2024_R1":139392,"2024_R2":139392,"2024_R3":214430,"2025_R1":129486,"2025_R2":162747,"2025_R3":162747},"min_rank":129486,"max_rank":214430},{"college_code":"E031","college_name":"B V V Sangha`s Basaveshwara Engineering College , Bagalkote (AUTONOMOUS) NIJALINGAPPA ROAD,BAGALKOT 587102","course_name":"ELECTRONICS AND COMMUNICATIO N ENGG","category":"1G","seat_type":"ROK","rounds":{"2025_R2":35320.5,"2025_R3":35320.5},"min_rank":35320.5,"max_rank":35320.5},{"college_code":"E031","college_name":"B V V Sangha`s Basaveshwara Engineering College , Bagalkote (AUTONOMOUS) NIJALINGAPPA ROAD,BAGALKOT 587102","course_name":"ELECTRONICS AND COMMUNICATIO N ENGG","category":"2AG","seat_type":"ROK","rounds":{"2025_R2":35126,"2025_R3":37064},"min_rank":35126,"max_rank":37064},{"college_code":"E031","college_name":"B V V Sangha`s Basaveshwara Engineering College , Bagalkote (AUTONOMOUS) NIJALINGAPPA ROAD,BAGALKOT 587102","course_name":"ELECTRONICS AND COMMUNICATIO N ENGG","category":"2AR","seat_type":"ROK","rounds":{"2025_R2":36087,"2025_R3":40388},"min_rank":36087,"max_rank":40388},{"college_code":"E031","college_name":"B V V Sangha`s Basaveshwara Engineering College , Bagalkote (AUTONOMOUS) NIJALINGAPPA ROAD,BAGALKOT 587102","course_name":"ELECTRONICS AND COMMUNICATIO N ENGG","category":"2BG","seat_type":"ROK","rounds":{"2025_R2":38522,"2025_R3":38522},"min_rank":38522,"max_rank":38522},{"college_code":"E031","college_name":"B V V Sangha`s Basaveshwara Engineering College , Bagalkote (AUTONOMOUS) NIJALINGAPPA ROAD,BAGALKOT 587102","course_name":"ELECTRONICS AND COMMUNICATIO N ENGG","category":"3AG","seat_type":"ROK","rounds":{"2025_R2":39309,"2025_R3":39309},"min_rank":39309,"max_rank":39309},{"college_code":"E031","college_name":"B V V Sangha`s Basaveshwara Engineering College , Bagalkote (AUTONOMOUS) NIJALINGAPPA ROAD,BAGALKOT 587102","course_name":"ELECTRONICS AND COMMUNICATIO N ENGG","category":"3AK","seat_type":"ROK","rounds":{"2025_R2":53331,"2025_R3":53331},"min_rank":53331,"max_rank":53331},{"college_code":"E031","college_name":"B V V Sangha`s Basaveshwara Engineering College , Bagalkote (AUTONOMOUS) NIJALINGAPPA ROAD,BAGALKOT 587102","course_name":"ELECTRONICS AND COMMUNICATIO N ENGG","category":"3BG","seat_type":"ROK","rounds":{"2025_R2":34143,"2025_R3":34143},"min_rank":34143,"max_rank":34143},{"college_code":"E031","college_name":"B V V Sangha`s Basaveshwara Engineering College , Bagalkote (AUTONOMOUS) NIJALINGAPPA ROAD,BAGALKOT 587102","course_name":"ELECTRONICS AND COMMUNICATIO N ENGG","category":"GM","seat_type":"ROK","rounds":{"2025_R2":32381,"2025_R3":32785},"min_rank":32381,"max_rank":32785},{"college_code":"E031","college_name":"B V V Sangha`s Basaveshwara Engineering College , Bagalkote (AUTONOMOUS) NIJALINGAPPA ROAD,BAGALKOT 587102","course_name":"ELECTRONICS AND COMMUNICATIO N ENGG","category":"GMK","seat_type":"ROK","rounds":{"2025_R2":32420,"2025_R3":34480},"min_rank":32420,"max_rank":34480},{"college_code":"E031","college_name":"B V V Sangha`s Basaveshwara Engineering College , Bagalkote (AUTONOMOUS) NIJALINGAPPA ROAD,BAGALKOT 587102","course_name":"ELECTRONICS AND COMMUNICATIO N ENGG","category":"GMR","seat_type":"ROK","rounds":{"2025_R2":35945,"2025_R3":36087},"min_rank":35945,"max_rank":36087},{"college_code":"E031","college_name":"B V V Sangha`s Basaveshwara Engineering College , Bagalkote (AUTONOMOUS) NIJALINGAPPA ROAD,BAGALKOT 587102","course_name":"ELECTRONICS AND COMMUNICATIO N ENGG","category":"SCG","seat_type":"ROK","rounds":{"2025_R2":82397,"2025_R3":82397},"min_rank":82397,"max_rank":82397},{"college_code":"E031","college_name":"B V V Sangha`s Basaveshwara Engineering College , Bagalkote (AUTONOMOUS) NIJALINGAPPA ROAD,BAGALKOT 587102","course_name":"ELECTRONICS AND COMMUNICATIO N ENGG","category":"SCR","seat_type":"ROK","rounds":{"2025_R2":114131,"2025_R3":114131},"min_rank":114131,"max_rank":114131},{"college_code":"E031","college_name":"B V V Sangha`s Basaveshwara Engineering College , Bagalkote (AUTONOMOUS) NIJALINGAPPA ROAD,BAGALKOT 587102","course_name":"ELECTRONICS AND COMMUNICATIO N ENGG","category":"STG","seat_type":"ROK","rounds":{"2025_R2":77199,"2025_R3":77199},"min_rank":77199,"max_rank":77199},{"college_code":"E031","college_name":"B V V Sangha`s Basaveshwara Engineering College , Bagalkote (AUTONOMOUS) NIJALINGAPPA ROAD,BAGALKOT 587102","course_name":"ELECTRONICS AND COMMUNICATIO N ENGG","category":"STR","seat_type":"ROK","rounds":{"2025_R2":104380,"2025_R3":104380},"min_rank":104380,"max_rank":104380},{"college_code":"E031","college_name":"B V V Sangha`s Basaveshwara Engineering College , Bagalkote (AUTONOMOUS) NIJALINGAPPA ROAD,BAGALKOT 587102","course_name":"ELECTRONICS AND COMMUNICATION ENGG","category":"1G","seat_type":"ROK","rounds":{"2024_R1":38801,"2024_R2":38801,"2024_R3":40309,"2025_R1":29976},"min_rank":29976,"max_rank":40309},{"college_code":"E031","college_name":"B V V Sangha`s Basaveshwara Engineering College , Bagalkote (AUTONOMOUS) NIJALINGAPPA ROAD,BAGALKOT 587102","course_name":"ELECTRONICS AND COMMUNICATION ENGG","category":"2AG","seat_type":"ROK","rounds":{"2024_R1":33239,"2024_R2":36564,"2024_R3":37296,"2025_R1":28320.5},"min_rank":28320.5,"max_rank":37296},{"college_code":"E031","college_name":"B V V Sangha`s Basaveshwara Engineering College , Bagalkote (AUTONOMOUS) NIJALINGAPPA ROAD,BAGALKOT 587102","course_name":"ELECTRONICS AND COMMUNICATION ENGG","category":"2AR","seat_type":"ROK","rounds":{"2024_R1":33337,"2024_R2":39534,"2024_R3":39534,"2025_R1":30068},"min_rank":30068,"max_rank":39534},{"college_code":"E031","college_name":"B V V Sangha`s Basaveshwara Engineering College , Bagalkote (AUTONOMOUS) NIJALINGAPPA ROAD,BAGALKOT 587102","course_name":"ELECTRONICS AND COMMUNICATION ENGG","category":"2BG","seat_type":"ROK","rounds":{"2024_R1":34013,"2024_R2":34013,"2024_R3":34013,"2025_R1":38522},"min_rank":34013,"max_rank":38522},{"college_code":"E031","college_name":"B V V Sangha`s Basaveshwara Engineering College , Bagalkote (AUTONOMOUS) NIJALINGAPPA ROAD,BAGALKOT 587102","course_name":"ELECTRONICS AND COMMUNICATION ENGG","category":"2BH","seat_type":"HK","rounds":{"2025_R1":67614,"2025_R2":67614,"2025_R3":67614},"min_rank":67614,"max_rank":67614},{"college_code":"E031","college_name":"B V V Sangha`s Basaveshwara Engineering College , Bagalkote (AUTONOMOUS) NIJALINGAPPA ROAD,BAGALKOT 587102","course_name":"ELECTRONICS AND COMMUNICATION ENGG","category":"2BH","seat_type":"ROK","rounds":{"2025_R1":67614},"min_rank":67614,"max_rank":67614},{"college_code":"E031","college_name":"B V V Sangha`s Basaveshwara Engineering College , Bagalkote (AUTONOMOUS) NIJALINGAPPA ROAD,BAGALKOT 587102","course_name":"ELECTRONICS AND COMMUNICATION ENGG","category":"3AG","seat_type":"ROK","rounds":{"2024_R1":33483,"2024_R2":39775,"2024_R3":39775,"2025_R1":30209},"min_rank":30209,"max_rank":39775},{"college_code":"E031","college_name":"B V V Sangha`s Basaveshwara Engineering College , Bagalkote (AUTONOMOUS) NIJALINGAPPA ROAD,BAGALKOT 587102","course_name":"ELECTRONICS AND COMMUNICATION ENGG","category":"3AK","seat_type":"ROK","rounds":{"2024_R1":null,"2024_R2":null,"2024_R3":null,"2025_R1":51898},"min_rank":51898,"max_rank":51898},{"college_code":"E031","college_name":"B V V Sangha`s Basaveshwara Engineering College , Bagalkote (AUTONOMOUS) NIJALINGAPPA ROAD,BAGALKOT 587102","course_name":"ELECTRONICS AND COMMUNICATION ENGG","category":"3BG","seat_type":"ROK","rounds":{"2024_R1":30450,"2024_R2":34640,"2024_R3":34640,"2025_R1":26392},"min_rank":26392,"max_rank":34640},{"college_code":"E031","college_name":"B V V Sangha`s Basaveshwara Engineering College , Bagalkote (AUTONOMOUS) NIJALINGAPPA ROAD,BAGALKOT 587102","course_name":"ELECTRONICS AND COMMUNICATION ENGG","category":"GM","seat_type":"ROK","rounds":{"2024_R1":28782,"2024_R2":31325,"2024_R3":31954,"2025_R1":25225},"min_rank":25225,"max_rank":31954},{"college_code":"E031","college_name":"B V V Sangha`s Basaveshwara Engineering College , Bagalkote (AUTONOMOUS) NIJALINGAPPA ROAD,BAGALKOT 587102","course_name":"ELECTRONICS AND COMMUNICATION ENGG","category":"GMH","seat_type":"HK","rounds":{"2025_R1":28048,"2025_R2":33757,"2025_R3":33757},"min_rank":28048,"max_rank":33757},{"college_code":"E031","college_name":"B V V Sangha`s Basaveshwara Engineering College , Bagalkote (AUTONOMOUS) NIJALINGAPPA ROAD,BAGALKOT 587102","course_name":"ELECTRONICS AND COMMUNICATION ENGG","category":"GMH","seat_type":"ROK","rounds":{"2025_R1":28048},"min_rank":28048,"max_rank":28048},{"college_code":"E031","college_name":"B V V Sangha`s Basaveshwara Engineering College , Bagalkote (AUTONOMOUS) NIJALINGAPPA ROAD,BAGALKOT 587102","course_name":"ELECTRONICS AND COMMUNICATION ENGG","category":"GMK","seat_type":"ROK","rounds":{"2024_R1":29236,"2024_R2":32363,"2024_R3":32363,"2025_R1":26868},"min_rank":26868,"max_rank":32363},{"college_code":"E031","college_name":"B V V Sangha`s Basaveshwara Engineering College , Bagalkote (AUTONOMOUS) NIJALINGAPPA ROAD,BAGALKOT 587102","course_name":"ELECTRONICS AND COMMUNICATION ENGG","category":"GMR","seat_type":"ROK","rounds":{"2024_R1":31229,"2024_R2":38027,"2024_R3":38027,"2025_R1":26230},"min_rank":26230,"max_rank":38027},{"college_code":"E031","college_name":"B V V Sangha`s Basaveshwara Engineering College , Bagalkote (AUTONOMOUS) NIJALINGAPPA ROAD,BAGALKOT 587102","course_name":"ELECTRONICS AND COMMUNICATION ENGG","category":"SCG","seat_type":"ROK","rounds":{"2024_R1":75012,"2024_R2":75012,"2024_R3":95941,"2025_R1":81163},"min_rank":75012,"max_rank":95941},{"college_code":"E031","college_name":"B V V Sangha`s Basaveshwara Engineering College , Bagalkote (AUTONOMOUS) NIJALINGAPPA ROAD,BAGALKOT 587102","course_name":"ELECTRONICS AND COMMUNICATION ENGG","category":"SCH","seat_type":"HK","rounds":{"2025_R1":83022,"2025_R2":107592,"2025_R3":107592},"min_rank":83022,"max_rank":107592},{"college_code":"E031","college_name":"B V V Sangha`s Basaveshwara Engineering College , Bagalkote (AUTONOMOUS) NIJALINGAPPA ROAD,BAGALKOT 587102","course_name":"ELECTRONICS AND COMMUNICATION ENGG","category":"SCH","seat_type":"ROK","rounds":{"2025_R1":83022},"min_rank":83022,"max_rank":83022},{"college_code":"E031","college_name":"B V V Sangha`s Basaveshwara Engineering College , Bagalkote (AUTONOMOUS) NIJALINGAPPA ROAD,BAGALKOT 587102","course_name":"ELECTRONICS AND COMMUNICATION ENGG","category":"SCR","seat_type":"ROK","rounds":{"2024_R1":103223,"2024_R2":103223,"2024_R3":103223,"2025_R1":107592},"min_rank":103223,"max_rank":107592},{"college_code":"E031","college_name":"B V V Sangha`s Basaveshwara Engineering College , Bagalkote (AUTONOMOUS) NIJALINGAPPA ROAD,BAGALKOT 587102","course_name":"ELECTRONICS AND COMMUNICATION ENGG","category":"STG","seat_type":"ROK","rounds":{"2024_R1":96902,"2024_R2":96902,"2024_R3":96902,"2025_R1":70406},"min_rank":70406,"max_rank":96902},{"college_code":"E031","college_name":"B V V Sangha`s Basaveshwara Engineering College , Bagalkote (AUTONOMOUS) NIJALINGAPPA ROAD,BAGALKOT 587102","course_name":"ELECTRONICS AND COMMUNICATION ENGG","category":"STR","seat_type":"ROK","rounds":{"2024_R1":102241,"2024_R2":102241,"2024_R3":102241,"2025_R1":80355},"min_rank":80355,"max_rank":102241},{"college_code":"E031","college_name":"B V V Sangha`s Basaveshwara Engineering College , Bagalkote (AUTONOMOUS) NIJALINGAPPA ROAD,BAGALKOT 587102","course_name":"ELECTRONICS AND COMMUNICATION ENGG","category":"STRH","seat_type":"ROK","rounds":{"2025_R1":168715},"min_rank":168715,"max_rank":168715},{"college_code":"E031","college_name":"B V V Sangha`s Basaveshwara Engineering College , Bagalkote (AUTONOMOUS) NIJALINGAPPA ROAD,BAGALKOT 587102","course_name":"INDUSTRIAL & PRODUCTION ENGINEERING","category":"GMH","seat_type":"ROK","rounds":{"2025_R1":200672},"min_rank":200672,"max_rank":200672},{"college_code":"E031","college_name":"B V V Sangha`s Basaveshwara Engineering College , Bagalkote (AUTONOMOUS) NIJALINGAPPA ROAD,BAGALKOT 587102","course_name":"IP Ind.Prodn.","category":"GM","seat_type":"ROK","rounds":{"2024_R1":135383,"2024_R2":220089,"2024_R3":272296},"min_rank":135383,"max_rank":272296},{"college_code":"E031","college_name":"B V V Sangha`s Basaveshwara Engineering College , Bagalkote (AUTONOMOUS) NIJALINGAPPA ROAD,BAGALKOT 587102","course_name":"MECHANICAL ENGINEERING","category":"2AH","seat_type":"ROK","rounds":{"2025_R1":168470.5},"min_rank":168470.5,"max_rank":168470.5},{"college_code":"E031","college_name":"B V V Sangha`s Basaveshwara Engineering College , Bagalkote (AUTONOMOUS) NIJALINGAPPA ROAD,BAGALKOT 587102","course_name":"MECHANICAL ENGINEERING","category":"3BH","seat_type":"ROK","rounds":{"2025_R1":145218},"min_rank":145218,"max_rank":145218},{"college_code":"E031","college_name":"B V V Sangha`s Basaveshwara Engineering College , Bagalkote (AUTONOMOUS) NIJALINGAPPA ROAD,BAGALKOT 587102","course_name":"MECHANICAL ENGINEERING","category":"GM","seat_type":"ROK","rounds":{"2024_R1":135993,"2024_R2":173848,"2024_R3":268834,"2025_R1":125851.5,"2025_R2":261347,"2025_R3":261347},"min_rank":125851.5,"max_rank":268834},{"college_code":"E031","college_name":"B V V Sangha`s Basaveshwara Engineering College , Bagalkote (AUTONOMOUS) NIJALINGAPPA ROAD,BAGALKOT 587102","course_name":"MECHANICAL ENGINEERING","category":"GMH","seat_type":"ROK","rounds":{"2025_R1":135916},"min_rank":135916,"max_rank":135916},{"college_code":"E031","college_name":"B V V Sangha`s Basaveshwara Engineering College , Bagalkote (AUTONOMOUS) NIJALINGAPPA ROAD,BAGALKOT 587102","course_name":"MECHANICAL ENGINEERING","category":"SCH","seat_type":"ROK","rounds":{"2025_R1":242405},"min_rank":242405,"max_rank":242405},{"college_code":"E031","college_name":"B V V Sangha`s Basaveshwara Engineering College , Bagalkote (AUTONOMOUS) NIJALINGAPPA ROAD,BAGALKOT 587102","course_name":"MECHANICAL ENGINEERING","category":"STH","seat_type":"ROK","rounds":{"2025_R1":229717},"min_rank":229717,"max_rank":229717}],"suggestions":{"CIVIL ENGINEERING|2AG|ROK":{"similarCollege":{"college":"B M S Institute of Technology & Management, Yelahanka, Bangalore(AUTONOMOUS) POST BOX NO.6443, AVALAHALLI,DODDABALLAPURA MAIN ROAD,YELAHANKA, BANGALORE - 560064.","branch":"CIVIL ENGINEERING","category":"2AG"},"similarBranch":{"college":"B V V Sangha`s Basaveshwara Engineering College , Bagalkote (AUTONOMOUS) NIJALINGAPPA ROAD,BAGALKOT 587102","branch":"COMPUTER SCIENCE AND ENGINEERING","category":"2AG"}},"CIVIL ENGINEERING|2AH|ROK":{"similarCollege":{"college":"Vidya Vikas Institute of Engineering & Technology, Mysore #127,ALANAHALLY,ALANAHALLY POST,MYSORE-BANNUR ROAD,MYSORE","branch":"CIVIL ENGINEERING","category":"2AH"},"similarBranch":{"college":"B V V Sangha`s Basaveshwara Engineering College , Bagalkote (AUTONOMOUS) NIJALINGAPPA ROAD,BAGALKOT 587102","branch":"MECHANICAL ENGINEERING","category":"2AH"}},"CIVIL ENGINEERING|3BG|ROK":{"similarCollege":{"college":"Dr. Ambedkar Institute of Technology, Bangalore(AUTONOMOUS) OUTER RING ROAD,NEAR JNANA BHARATHI CAMPUS,MALLATHAHALLI,BANGALORE-560056","branch":"CIVIL ENGINEERING","category":"3BG"},"similarBranch":{"college":"B V V Sangha`s Basaveshwara Engineering College , Bagalkote (AUTONOMOUS) NIJALINGAPPA ROAD,BAGALKOT 587102","branch":"COMPUTER SCIENCE AND ENGINEERING","category":"3BG"}},"CIVIL ENGINEERING|GM|ROK":{"similarCollege":{"college":"Mysuru Royal Institute Of Technology,Lakshmipura road,Mysuru LAKSHMIPURA ROAD, OFF MYSURU -BENGALURU HIGHWAY,MANDYA","branch":"CIVIL ENGINEERING","category":"GM"},"similarBranch":{"college":"B V V Sangha`s Basaveshwara Engineering College , Bagalkote (AUTONOMOUS) NIJALINGAPPA ROAD,BAGALKOT 587102","branch":"MECHANICAL ENGINEERING","category":"GM"}},"CIVIL ENGINEERING|GMH|HK":{"similarCollege":{"college":"The National Institute of Engineering(SOUTH CAMPUS), Mysore(AUTONOMOUS) MANANDAVADI ROAD,MYSORE 570008","branch":"CIVIL ENGINEERING","category":"GMH"},"similarBranch":{"college":"B V V Sangha`s Basaveshwara Engineering College , Bagalkote (AUTONOMOUS) NIJALINGAPPA ROAD,BAGALKOT 587102","branch":"COMPUTER SCIENCE AND ENGINEERING","category":"GMH"}},"CIVIL ENGINEERING|GMH|ROK":{"similarCollege":{"college":"Malnad College of Engineering, Hassan(AUTONOMOUS) P.B. NO. 21, SALAGAME ROAD,HASSSAN","branch":"CIVIL ENGINEERING","category":"GMH"},"similarBranch":{"college":"B V V Sangha`s Basaveshwara Engineering College , Bagalkote (AUTONOMOUS) NIJALINGAPPA ROAD,BAGALKOT 587102","branch":"MECHANICAL ENGINEERING","category":"GMH"}},"CIVIL ENGINEERING|GMK|ROK":{"similarCollege":{"college":"Dayananda Sagar College of Engineering, Bangalore(AUTONOMOUS) SHAVIGE MALLESHWARA HILLS, KUMARASWAMY LAYOUT, BANGALORE-560078","branch":"CIVIL ENGINEERING","category":"GMK"},"similarBranch":{"college":"B V V Sangha`s Basaveshwara Engineering College , Bagalkote (AUTONOMOUS) NIJALINGAPPA ROAD,BAGALKOT 587102","branch":"COMPUTER SCIENCE AND ENGINEERING","category":"GMK"}},"CIVIL ENGINEERING|GMR|ROK":{"similarCollege":{"college":"SDM College of Engineering, Dharwad (AUTONOMOUS) DHAVALAGIRI,KALGHATGI ROAD,DHARWAD","branch":"CIVIL ENGINEERING","category":"GMR"},"similarBranch":{"college":"B V V Sangha`s Basaveshwara Engineering College , Bagalkote (AUTONOMOUS) NIJALINGAPPA ROAD,BAGALKOT 587102","branch":"COMPUTER SCIENCE AND ENGINEERING","category":"GMR"}},"CIVIL ENGINEERING|SCG|ROK":{"similarCollege":{"college":"Bangalore Institute of Technology, K.R.Road, Bangalore (AUTONOMOUS) K.R.ROAD, V.V.PURA, BANGALORE-560004","branch":"CIVIL ENGINEERING","category":"SCG"},"similarBranch":{"college":"B V V Sangha`s Basaveshwara Engineering College , Bagalkote (AUTONOMOUS) NIJALINGAPPA ROAD,BAGALKOT 587102","branch":"COMPUTER SCIENCE AND ENGINEERING","category":"SCG"}},"CIVIL ENGINEERING|SCH|ROK":{"similarCollege":{"college":"P E S College of Engineering, Mandya(AUTONOMOUS) MANDYA: 571 401","branch":"CIVIL ENGINEERING","category":"SCH"},"similarBranch":{"college":"B V V Sangha`s Basaveshwara Engineering College , Bagalkote (AUTONOMOUS) NIJALINGAPPA ROAD,BAGALKOT 587102","branch":"ELECTRICAL & ELECTRONICS ENGINEERING","category":"SCH"}},"CIVIL ENGINEERING|SCK|ROK":{"similarCollege":{"college":"Govt.S K S J T Institute of Engineering, Bangalore AMBEDKAR VEEDHI, K.R. CIRCLE, BANGALORE-01","branch":"CIVIL ENGINEERING","category":"SCK"},"similarBranch":{"college":"B V V Sangha`s Basaveshwara Engineering College , Bagalkote (AUTONOMOUS) NIJALINGAPPA ROAD,BAGALKOT 587102","branch":"COMPUTER SCIENCE AND ENGINEERING","category":"SCK"}},"CIVIL ENGINEERING|SCR|ROK":{"similarCollege":{"college":"Govt.S K S J T Institute of Engineering, Bangalore AMBEDKAR VEEDHI, K.R. CIRCLE, BANGALORE-01","branch":"CIVIL ENGINEERING","category":"SCR"},"similarBranch":{"college":"B V V Sangha`s Basaveshwara Engineering College , Bagalkote (AUTONOMOUS) NIJALINGAPPA ROAD,BAGALKOT 587102","branch":"COMPUTER SCIENCE AND ENGINEERING","category":"SCR"}},"CIVIL ENGINEERING|SCRH|ROK":{"similarCollege":{"college":"Government Engineering College,Mailur,Bidar","branch":"CIVIL ENGINEERING","category":"SCRH"},"similarBranch":null},"CIVIL ENGINEERING|STG|ROK":{"similarCollege":{"college":"SDM College of Engineering, Dharwad (AUTONOMOUS) DHAVALAGIRI,KALGHATGI ROAD,DHARWAD","branch":"CIVIL ENGINEERING","category":"STG"},"similarBranch":{"college":"B V V Sangha`s Basaveshwara Engineering College , Bagalkote (AUTONOMOUS) NIJALINGAPPA ROAD,BAGALKOT 587102","branch":"ELECTRONICS AND COMMUNICATION ENGG","category":"STG"}},"CIVIL ENGINEERING|STH|ROK":{"similarCollege":{"college":"Rao Bahadur Y.Mahabaleswarappa Engineering College, Bellary CONTONMENT, BELLARY-583104","branch":"CIVIL ENGINEERING","category":"STH"},"similarBranch":{"college":"B V V Sangha`s Basaveshwara Engineering College , Bagalkote (AUTONOMOUS) NIJALINGAPPA ROAD,BAGALKOT 587102","branch":"MECHANICAL ENGINEERING","category":"STH"}},"COMPUTER SCIENCE AND ENGINEERING|1G|ROK":{"similarCollege":{"college":"Vidya Vardhaka College of Engineering, Mysore(AUTONOMOUS) P.B.NO.206,GOKULAM 3RD STAGE,MYSORE","branch":"COMPUTER SCIENCE AND ENGINEERING","category":"1G"},"similarBranch":{"college":"B V V Sangha`s Basaveshwara Engineering College , Bagalkote (AUTONOMOUS) NIJALINGAPPA ROAD,BAGALKOT 587102","branch":"ELECTRONICS AND COMMUNICATIO N ENGG","category":"1G"}},"COMPUTER SCIENCE AND ENGINEERING|1R|ROK":{"similarCollege":{"college":"Visvesvaraya Technological University,VTU,CPGS,Mysuru.","branch":"COMPUTER SCIENCE AND ENGINEERING","category":"1R"},"similarBranch":null},"COMPUTER SCIENCE AND ENGINEERING|2AG|ROK":{"similarCollege":{"college":"Dr. Ambedkar Institute of Technology, Bangalore(AUTONOMOUS) OUTER RING ROAD,NEAR JNANA BHARATHI CAMPUS,MALLATHAHALLI,BANGALORE-560056","branch":"COMPUTER SCIENCE AND ENGINEERING","category":"2AG"},"similarBranch":{"college":"B V V Sangha`s Basaveshwara Engineering College , Bagalkote (AUTONOMOUS) NIJALINGAPPA ROAD,BAGALKOT 587102","branch":"ELECTRONICS AND COMMUNICATION ENGG","category":"2AG"}},"COMPUTER SCIENCE AND ENGINEERING|2AH|HK":{"similarCollege":{"college":"Dayananda Sagar Academy of Technology & Management Technical Campus, Bangalore(AUTONOMOUS) UDAYAPURA,KANAKAPURA ROAD,BANGALORE URBAN","branch":"COMPUTER SCIENCE AND ENGINEERING","category":"2AH"},"similarBranch":{"college":"B V V Sangha`s Basaveshwara Engineering College , Bagalkote (AUTONOMOUS) NIJALINGAPPA ROAD,BAGALKOT 587102","branch":"ELECTRICAL & ELECTRONICS ENGINEERING","category":"2AH"}},"COMPUTER SCIENCE AND ENGINEERING|2AH|ROK":{"similarCollege":{"college":"Vidya Vardhaka College of Engineering, Mysore(AUTONOMOUS) P.B.NO.206,GOKULAM 3RD STAGE,MYSORE","branch":"COMPUTER SCIENCE AND ENGINEERING","category":"2AH"},"similarBranch":{"college":"B V V Sangha`s Basaveshwara Engineering College , Bagalkote (AUTONOMOUS) NIJALINGAPPA ROAD,BAGALKOT 587102","branch":"ELECTRICAL & ELECTRONICS ENGINEERING","category":"2AH"}},"COMPUTER SCIENCE AND ENGINEERING|2AR|ROK":{"similarCollege":{"college":"C M R Institute of Technology, Kundala Halli village, Bangalore # 132, KUNDALAHALLI VILLAGE,IT PARK ROAD,BANGALORE - 560 037","branch":"COMPUTER SCIENCE AND ENGINEERING","category":"2AR"},"similarBranch":{"college":"B V V Sangha`s Basaveshwara Engineering College , Bagalkote (AUTONOMOUS) NIJALINGAPPA ROAD,BAGALKOT 587102","branch":"ELECTRONICS AND COMMUNICATION ENGG","category":"2AR"}},"COMPUTER SCIENCE AND ENGINEERING|2BG|ROK":{"similarCollege":{"college":"Cambridge Institutute of Technology, K.R.Puram, Bangalore(AUTONOMOUS) K R PURAM,BANGALORE","branch":"COMPUTER SCIENCE AND ENGINEERING","category":"2BG"},"similarBranch":{"college":"B V V Sangha`s Basaveshwara Engineering College , Bagalkote (AUTONOMOUS) NIJALINGAPPA ROAD,BAGALKOT 587102","branch":"ELECTRONICS AND COMMUNICATIO N ENGG","category":"2BG"}},"COMPUTER SCIENCE AND ENGINEERING|3AG|ROK":{"similarCollege":{"college":"University B.D.T College of Engineering, Davanagere P J EXTENSION,HADADI ROAD,DAVENGERE","branch":"COMPUTER SCIENCE AND ENGINEERING","category":"3AG"},"similarBranch":{"college":"B V V Sangha`s Basaveshwara Engineering College , Bagalkote (AUTONOMOUS) NIJALINGAPPA ROAD,BAGALKOT 587102","branch":"ELECTRONICS AND COMMUNICATION ENGG","category":"3AG"}},"COMPUTER SCIENCE AND ENGINEERING|3AH|HK":{"similarCollege":{"college":"Vidya Vardhaka College of Engineering, Mysore(AUTONOMOUS) P.B.NO.206,GOKULAM 3RD STAGE,MYSORE","branch":"COMPUTER SCIENCE AND ENGINEERING","category":"3AH"},"similarBranch":null},"COMPUTER SCIENCE AND ENGINEERING|3AH|ROK":{"similarCollege":{"college":"Bapuji Institute of Engineering & Technology, Davangere (AUTONOMOUS) BAPUJI INSTITUTE OF ENGINEERING & TECHNOLOGY,P.B. NO.325,SHAMANUR ROAD,DAVANGERE-577 004","branch":"COMPUTER SCIENCE AND ENGINEERING","category":"3AH"},"similarBranch":null},"COMPUTER SCIENCE AND ENGINEERING|3BG|ROK":{"similarCollege":{"college":"S.J B. Institute of Technology, Bangalore (AUTONOMOUS) BGS HEALTH & EDUCATION CITY,NO 67, UTTARAHALLI ROAD.KENGERI, BANGALORE -60","branch":"COMPUTER SCIENCE AND ENGINEERING","category":"3BG"},"similarBranch":{"college":"B V V Sangha`s Basaveshwara Engineering College , Bagalkote (AUTONOMOUS) NIJALINGAPPA ROAD,BAGALKOT 587102","branch":"ELECTRONICS AND COMMUNICATION ENGG","category":"3BG"}},"COMPUTER SCIENCE AND ENGINEERING|3BK|ROK":{"similarCollege":{"college":"RNS Institute of Technology, Bangalore (AUTONOMOUS) CHANNASANDRA,UTTARAHALLI -KENGERI MAIN ROAD,SUBRAMANYAPURA POST,BANGALORE","branch":"COMPUTER SCIENCE AND ENGINEERING","category":"3BK"},"similarBranch":null},"COMPUTER SCIENCE AND ENGINEERING|GM|ROK":{"similarCollege":{"college":"University B.D.T College of Engineering, Davanagere P J EXTENSION,HADADI ROAD,DAVENGERE","branch":"COMPUTER SCIENCE AND ENGINEERING","category":"GM"},"similarBranch":{"college":"B V V Sangha`s Basaveshwara Engineering College , Bagalkote (AUTONOMOUS) NIJALINGAPPA ROAD,BAGALKOT 587102","branch":"ELECTRONICS AND COMMUNICATION ENGG","category":"GM"}},"COMPUTER SCIENCE AND ENGINEERING|GMH|HK":{"similarCollege":{"college":"S.J B. Institute of Technology, Bangalore (AUTONOMOUS) BGS HEALTH & EDUCATION CITY,NO 67, UTTARAHALLI ROAD.KENGERI, BANGALORE -60","branch":"COMPUTER SCIENCE AND ENGINEERING","category":"GMH"},"similarBranch":{"college":"B V V Sangha`s Basaveshwara Engineering College , Bagalkote (AUTONOMOUS) NIJALINGAPPA ROAD,BAGALKOT 587102","branch":"ELECTRONICS AND COMMUNICATION ENGG","category":"GMH"}},"COMPUTER SCIENCE AND ENGINEERING|GMH|ROK":{"similarCollege":{"college":"Acharya Institute of Technology, Soldevanahalli,Chikkabanavara post, Bangalore SOLDEVANAHALLI, HESARAGHATTA MAIN ROAD, CHIKKABANAVARA POST,BANGALORE URBAN","branch":"COMPUTER SCIENCE AND ENGINEERING","category":"GMH"},"similarBranch":{"college":"B V V Sangha`s Basaveshwara Engineering College , Bagalkote (AUTONOMOUS) NIJALINGAPPA ROAD,BAGALKOT 587102","branch":"ELECTRONICS AND COMMUNICATION ENGG","category":"GMH"}},"COMPUTER SCIENCE AND ENGINEERING|GMK|ROK":{"similarCollege":{"college":"Dr. Ambedkar Institute of Technology, Bangalore(AUTONOMOUS) OUTER RING ROAD,NEAR JNANA BHARATHI CAMPUS,MALLATHAHALLI,BANGALORE-560056","branch":"COMPUTER SCIENCE AND ENGINEERING","category":"GMK"},"similarBranch":{"college":"B V V Sangha`s Basaveshwara Engineering College , Bagalkote (AUTONOMOUS) NIJALINGAPPA ROAD,BAGALKOT 587102","branch":"ELECTRONICS AND COMMUNICATION ENGG","category":"GMK"}},"COMPUTER SCIENCE AND ENGINEERING|GMR|ROK":{"similarCollege":{"college":"Sahyadri College Of Engineering & Management, Adyar, Mangalore(AUTONOMOUS) 'SAHYADRI CAMPUS'N.H-48, ADYAR,MANGALORE","branch":"COMPUTER SCIENCE AND ENGINEERING","category":"GMR"},"similarBranch":{"college":"B V V Sangha`s Basaveshwara Engineering College , Bagalkote (AUTONOMOUS) NIJALINGAPPA ROAD,BAGALKOT 587102","branch":"ELECTRONICS AND COMMUNICATION ENGG","category":"GMR"}},"COMPUTER SCIENCE AND ENGINEERING|GMRH|HK":{"similarCollege":{"college":"SDM College of Engineering, Dharwad (AUTONOMOUS) DHAVALAGIRI,KALGHATGI ROAD,DHARWAD","branch":"COMPUTER SCIENCE AND ENGINEERING","category":"GMRH"},"similarBranch":{"college":"B V V Sangha`s Basaveshwara Engineering College , Bagalkote (AUTONOMOUS) NIJALINGAPPA ROAD,BAGALKOT 587102","branch":"ELECTRICAL & ELECTRONICS ENGINEERING","category":"GMRH"}},"COMPUTER SCIENCE AND ENGINEERING|GMRH|ROK":{"similarCollege":{"college":"Cambridge Institutute of Technology, K.R.Puram, Bangalore(AUTONOMOUS) K R PURAM,BANGALORE","branch":"COMPUTER SCIENCE AND ENGINEERING","category":"GMRH"},"similarBranch":{"college":"B V V Sangha`s Basaveshwara Engineering College , Bagalkote (AUTONOMOUS) NIJALINGAPPA ROAD,BAGALKOT 587102","branch":"ELECTRICAL & ELECTRONICS ENGINEERING","category":"GMRH"}},"COMPUTER SCIENCE AND ENGINEERING|SCG|ROK":{"similarCollege":{"college":"RNS Institute of Technology, Bangalore (AUTONOMOUS) CHANNASANDRA,UTTARAHALLI -KENGERI MAIN ROAD,SUBRAMANYAPURA POST,BANGALORE","branch":"COMPUTER SCIENCE AND ENGINEERING","category":"SCG"},"similarBranch":{"college":"B V V Sangha`s Basaveshwara Engineering College , Bagalkote (AUTONOMOUS) NIJALINGAPPA ROAD,BAGALKOT 587102","branch":"ELECTRONICS AND COMMUNICATION ENGG","category":"SCG"}},"COMPUTER SCIENCE AND ENGINEERING|SCK|ROK":{"similarCollege":{"college":"Sir M.Visvesvaraya Institute of Technology, Bangalore KRISHNADEVARAYANAGAR, HUNASAMARANAHALLI, VIA YELAHANKA,BANGALORE - 562 157","branch":"COMPUTER SCIENCE AND ENGINEERING","category":"SCK"},"similarBranch":{"college":"B V V Sangha`s Basaveshwara Engineering College , Bagalkote (AUTONOMOUS) NIJALINGAPPA ROAD,BAGALKOT 587102","branch":"CIVIL ENGINEERING","category":"SCK"}},"COMPUTER SCIENCE AND ENGINEERING|SCR|ROK":{"similarCollege":{"college":"RNS Institute of Technology, Bangalore (AUTONOMOUS) CHANNASANDRA,UTTARAHALLI -KENGERI MAIN ROAD,SUBRAMANYAPURA POST,BANGALORE","branch":"COMPUTER SCIENCE AND ENGINEERING","category":"SCR"},"similarBranch":{"college":"B V V Sangha`s Basaveshwara Engineering College , Bagalkote (AUTONOMOUS) NIJALINGAPPA ROAD,BAGALKOT 587102","branch":"ELECTRONICS AND COMMUNICATION ENGG","category":"SCR"}},"COMPUTER SCIENCE AND ENGINEERING|STG|ROK":{"similarCollege":{"college":"G S S S Institute of Engineering & Technology for Women, Mysore K.R.S. ROAD, METAGALLI INDUSTRIAL AREA, MYSORE-16","branch":"COMPUTER SCIENCE AND ENGINEERING","category":"STG"},"similarBranch":{"college":"B V V Sangha`s Basaveshwara Engineering College , Bagalkote (AUTONOMOUS) NIJALINGAPPA ROAD,BAGALKOT 587102","branch":"ELECTRONICS AND COMMUNICATIO N ENGG","category":"STG"}},"COMPUTER SCIENCE AND ENGINEERING|STR|ROK":{"similarCollege":{"college":"M V J College of Engineering, Bangalore(AUTONOMOUS) NEAR ITPB,CHANNASANDRA,KADUGODI POST,BANGALORE","branch":"COMPUTER SCIENCE AND ENGINEERING","category":"STR"},"similarBranch":{"college":"B V V Sangha`s Basaveshwara Engineering College , Bagalkote (AUTONOMOUS) NIJALINGAPPA ROAD,BAGALKOT 587102","branch":"ELECTRONICS AND COMMUNICATIO N ENGG","category":"STR"}},"ELECTRICAL & ELECTRONICS ENGINEERING|1G|ROK":{"similarCollege":{"college":"University B.D.T. college of Engineering, (H.GOV),Davangere","branch":"ELECTRICAL & ELECTRONICS ENGINEERING","category":"1G"},"similarBranch":{"college":"B V V Sangha`s Basaveshwara Engineering College , Bagalkote (AUTONOMOUS) NIJALINGAPPA ROAD,BAGALKOT 587102","branch":"ELECTRONICS AND COMMUNICATION ENGG","category":"1G"}},"ELECTRICAL & ELECTRONICS ENGINEERING|2AG|ROK":{"similarCollege":{"college":"G S S S Institute of Engineering & Technology for Women, Mysore K.R.S. ROAD, METAGALLI INDUSTRIAL AREA, MYSORE-16","branch":"ELECTRICAL & ELECTRONICS ENGINEERING","category":"2AG"},"similarBranch":{"college":"B V V Sangha`s Basaveshwara Engineering College , Bagalkote (AUTONOMOUS) NIJALINGAPPA ROAD,BAGALKOT 587102","branch":"CIVIL ENGINEERING","category":"2AG"}},"ELECTRICAL & ELECTRONICS ENGINEERING|2AH|HK":{"similarCollege":{"college":"Sir M.Visvesvaraya Institute of Technology, Bangalore KRISHNADEVARAYANAGAR, HUNASAMARANAHALLI, VIA YELAHANKA,BANGALORE - 562 157","branch":"ELECTRICAL & ELECTRONICS ENGINEERING","category":"2AH"},"similarBranch":{"college":"B V V Sangha`s Basaveshwara Engineering College , Bagalkote (AUTONOMOUS) NIJALINGAPPA ROAD,BAGALKOT 587102","branch":"COMPUTER SCIENCE AND ENGINEERING","category":"2AH"}},"ELECTRICAL & ELECTRONICS ENGINEERING|2AH|ROK":{"similarCollege":{"college":"P D A College of Engineering, Gulbarga(AUTONOMOUS) AIWAN-E-SHAHI AREA,STATION ROAD,GULBARGA-585102","branch":"ELECTRICAL & ELECTRONICS ENGINEERING","category":"2AH"},"similarBranch":{"college":"B V V Sangha`s Basaveshwara Engineering College , Bagalkote (AUTONOMOUS) NIJALINGAPPA ROAD,BAGALKOT 587102","branch":"CIVIL ENGINEERING","category":"2AH"}},"ELECTRICAL & ELECTRONICS ENGINEERING|2AR|ROK":{"similarCollege":{"college":"G S S S Institute of Engineering & Technology for Women, Mysore K.R.S. ROAD, METAGALLI INDUSTRIAL AREA, MYSORE-16","branch":"ELECTRICAL & ELECTRONICS ENGINEERING","category":"2AR"},"similarBranch":{"college":"B V V Sangha`s Basaveshwara Engineering College , Bagalkote (AUTONOMOUS) NIJALINGAPPA ROAD,BAGALKOT 587102","branch":"COMPUTER SCIENCE AND ENGINEERING","category":"2AR"}},"ELECTRICAL & ELECTRONICS ENGINEERING|2BG|ROK":{"similarCollege":{"college":"University B.D.T College of Engineering, Davanagere P J EXTENSION,HADADI ROAD,DAVENGERE","branch":"ELECTRICAL & ELECTRONICS ENGINEERING","category":"2BG"},"similarBranch":{"college":"B V V Sangha`s Basaveshwara Engineering College , Bagalkote (AUTONOMOUS) NIJALINGAPPA ROAD,BAGALKOT 587102","branch":"COMPUTER SCIENCE AND ENGINEERING","category":"2BG"}},"ELECTRICAL & ELECTRONICS ENGINEERING|2BK|ROK":{"similarCollege":{"college":"Nitte Meenakshi Institutute of Technology Bangalore","branch":"ELECTRICAL & ELECTRONICS ENGINEERING","category":"2BK"},"similarBranch":null},"ELECTRICAL & ELECTRONICS ENGINEERING|2BR|ROK":{"similarCollege":{"college":"SDM College of Engineering, Dharwad (AUTONOMOUS) DHAVALAGIRI,KALGHATGI ROAD,DHARWAD","branch":"ELECTRICAL & ELECTRONICS ENGINEERING","category":"2BR"},"similarBranch":null},"ELECTRICAL & ELECTRONICS ENGINEERING|3AG|ROK":{"similarCollege":{"college":"P D A College of Engineering, Gulbarga(AUTONOMOUS) AIWAN-E-SHAHI AREA,STATION ROAD,GULBARGA-585102","branch":"ELECTRICAL & ELECTRONICS ENGINEERING","category":"3AG"},"similarBranch":{"college":"B V V Sangha`s Basaveshwara Engineering College , Bagalkote (AUTONOMOUS) NIJALINGAPPA ROAD,BAGALKOT 587102","branch":"COMPUTER SCIENCE AND ENGINEERING","category":"3AG"}},"ELECTRICAL & ELECTRONICS ENGINEERING|3BG|ROK":{"similarCollege":{"college":"P E S College of Engineering, Mandya(AUTONOMOUS) MANDYA: 571 401","branch":"ELECTRICAL & ELECTRONICS ENGINEERING","category":"3BG"},"similarBranch":{"college":"B V V Sangha`s Basaveshwara Engineering College , Bagalkote (AUTONOMOUS) NIJALINGAPPA ROAD,BAGALKOT 587102","branch":"CIVIL ENGINEERING","category":"3BG"}},"ELECTRICAL & ELECTRONICS ENGINEERING|GM|ROK":{"similarCollege":{"college":"P E S College of Engineering, Mandya(AUTONOMOUS) MANDYA: 571 401","branch":"ELECTRICAL & ELECTRONICS ENGINEERING","category":"GM"},"similarBranch":{"college":"B V V Sangha`s Basaveshwara Engineering College , Bagalkote (AUTONOMOUS) NIJALINGAPPA ROAD,BAGALKOT 587102","branch":"CIVIL ENGINEERING","category":"GM"}},"ELECTRICAL & ELECTRONICS ENGINEERING|GMH|HK":{"similarCollege":{"college":"Acharya Institute of Technology, Soldevanahalli,Chikkabanavara post, Bangalore SOLDEVANAHALLI, HESARAGHATTA MAIN ROAD, CHIKKABANAVARA POST,BANGALORE URBAN","branch":"ELECTRICAL & ELECTRONICS ENGINEERING","category":"GMH"},"similarBranch":{"college":"B V V Sangha`s Basaveshwara Engineering College , Bagalkote (AUTONOMOUS) NIJALINGAPPA ROAD,BAGALKOT 587102","branch":"CIVIL ENGINEERING","category":"GMH"}},"ELECTRICAL & ELECTRONICS ENGINEERING|GMH|ROK":{"similarCollege":{"college":"Global Academy of Technology, Bangalore(AUTONOMOUS) IDEAL HOMES TOWNSHIP,RAJARAJESHWARINAGAR,BANGALORE-560098","branch":"ELECTRICAL & ELECTRONICS ENGINEERING","category":"GMH"},"similarBranch":{"college":"B V V Sangha`s Basaveshwara Engineering College , Bagalkote (AUTONOMOUS) NIJALINGAPPA ROAD,BAGALKOT 587102","branch":"CIVIL ENGINEERING","category":"GMH"}},"ELECTRICAL & ELECTRONICS ENGINEERING|GMK|ROK":{"similarCollege":{"college":"P E S College of Engineering, Mandya(AUTONOMOUS) MANDYA: 571 401","branch":"ELECTRICAL & ELECTRONICS ENGINEERING","category":"GMK"},"similarBranch":{"college":"B V V Sangha`s Basaveshwara Engineering College , Bagalkote (AUTONOMOUS) NIJALINGAPPA ROAD,BAGALKOT 587102","branch":"CIVIL ENGINEERING","category":"GMK"}},"ELECTRICAL & ELECTRONICS ENGINEERING|GMR|ROK":{"similarCollege":{"college":"P E S College of Engineering, Mandya(AUTONOMOUS) MANDYA: 571 401","branch":"ELECTRICAL & ELECTRONICS ENGINEERING","category":"GMR"},"similarBranch":{"college":"B V V Sangha`s Basaveshwara Engineering College , Bagalkote (AUTONOMOUS) NIJALINGAPPA ROAD,BAGALKOT 587102","branch":"CIVIL ENGINEERING","category":"GMR"}},"ELECTRICAL & ELECTRONICS ENGINEERING|GMRH|HK":{"similarCollege":{"college":"KLE Technological University(Formerly (BVBCET) BVBHOOMARADDI COLLEGE CAMPUS, VIDYANAGAR, HUBBALLI","branch":"ELECTRICAL & ELECTRONICS ENGINEERING","category":"GMRH"},"similarBranch":{"college":"B V V Sangha`s Basaveshwara Engineering College , Bagalkote (AUTONOMOUS) NIJALINGAPPA ROAD,BAGALKOT 587102","branch":"COMPUTER SCIENCE AND ENGINEERING","category":"GMRH"}},"ELECTRICAL & ELECTRONICS ENGINEERING|GMRH|ROK":{"similarCollege":{"college":"Bapuji Institute of Engineering & Technology, Davangere (AUTONOMOUS) BAPUJI INSTITUTE OF ENGINEERING & TECHNOLOGY,P.B. NO.325,SHAMANUR ROAD,DAVANGERE-577 004","branch":"ELECTRICAL & ELECTRONICS ENGINEERING","category":"GMRH"},"similarBranch":{"college":"B V V Sangha`s Basaveshwara Engineering College , Bagalkote (AUTONOMOUS) NIJALINGAPPA ROAD,BAGALKOT 587102","branch":"COMPUTER SCIENCE AND ENGINEERING","category":"GMRH"}},"ELECTRICAL & ELECTRONICS ENGINEERING|SCG|ROK":{"similarCollege":{"college":"G S S S Institute of Engineering & Technology for Women, Mysore K.R.S. ROAD, METAGALLI INDUSTRIAL AREA, MYSORE-16","branch":"ELECTRICAL & ELECTRONICS ENGINEERING","category":"SCG"},"similarBranch":{"college":"B V V Sangha`s Basaveshwara Engineering College , Bagalkote (AUTONOMOUS) NIJALINGAPPA ROAD,BAGALKOT 587102","branch":"CIVIL ENGINEERING","category":"SCG"}},"ELECTRICAL & ELECTRONICS ENGINEERING|SCH|HK":{"similarCollege":{"college":"KLE Technological University(Formerly (BVBCET) BVBHOOMARADDI COLLEGE CAMPUS, VIDYANAGAR, HUBBALLI","branch":"ELECTRICAL & ELECTRONICS ENGINEERING","category":"SCH"},"similarBranch":{"college":"B V V Sangha`s Basaveshwara Engineering College , Bagalkote (AUTONOMOUS) NIJALINGAPPA ROAD,BAGALKOT 587102","branch":"ELECTRONICS AND COMMUNICATION ENGG","category":"SCH"}},"ELECTRICAL & ELECTRONICS ENGINEERING|SCH|ROK":{"similarCollege":{"college":"CONSTITUENT COLLEGE OF VTU, CHINTAMANI CHIKABALLAPURA DIST CHIKBALLAPURA","branch":"ELECTRICAL & ELECTRONICS ENGINEERING","category":"SCH"},"similarBranch":{"college":"B V V Sangha`s Basaveshwara Engineering College , Bagalkote (AUTONOMOUS) NIJALINGAPPA ROAD,BAGALKOT 587102","branch":"MECHANICAL ENGINEERING","category":"SCH"}},"ELECTRICAL & ELECTRONICS ENGINEERING|SCR|ROK":{"similarCollege":{"college":"Bapuji Institute of Engineering & Technology, Davangere (AUTONOMOUS) BAPUJI INSTITUTE OF ENGINEERING & TECHNOLOGY,P.B. NO.325,SHAMANUR ROAD,DAVANGERE-577 004","branch":"ELECTRICAL & ELECTRONICS ENGINEERING","category":"SCR"},"similarBranch":{"college":"B V V Sangha`s Basaveshwara Engineering College , Bagalkote (AUTONOMOUS) NIJALINGAPPA ROAD,BAGALKOT 587102","branch":"CIVIL ENGINEERING","category":"SCR"}},"ELECTRICAL & ELECTRONICS ENGINEERING|STG|ROK":{"similarCollege":{"college":"M V J College of Engineering, Bangalore(AUTONOMOUS) NEAR ITPB,CHANNASANDRA,KADUGODI POST,BANGALORE","branch":"ELECTRICAL & ELECTRONICS ENGINEERING","category":"STG"},"similarBranch":{"college":"B V V Sangha`s Basaveshwara Engineering College , Bagalkote (AUTONOMOUS) NIJALINGAPPA ROAD,BAGALKOT 587102","branch":"CIVIL ENGINEERING","category":"STG"}},"ELECTRONICS AND COMMUNICATIO N ENGG|1G|ROK":{"similarCollege":{"college":"C M R Institute of Technology, Kundala Halli village, Bangalore # 132, KUNDALAHALLI VILLAGE,IT PARK ROAD,BANGALORE - 560 037","branch":"ELECTRONICS AND COMMUNICATIO N ENGG","category":"1G"},"similarBranch":{"college":"B V V Sangha`s Basaveshwara Engineering College , Bagalkote (AUTONOMOUS) NIJALINGAPPA ROAD,BAGALKOT 587102","branch":"ELECTRICAL & ELECTRONICS ENGINEERING","category":"1G"}},"ELECTRONICS AND COMMUNICATIO N ENGG|2AG|ROK":{"similarCollege":{"college":"J S S Academy of Technical Education, Bangalore JSSATE CAMPUS,UTTARAHALLI-KENGERI ROAD ,BANGALORE 560060","branch":"ELECTRONICS AND COMMUNICATIO N ENGG","category":"2AG"},"similarBranch":{"college":"B V V Sangha`s Basaveshwara Engineering College , Bagalkote (AUTONOMOUS) NIJALINGAPPA ROAD,BAGALKOT 587102","branch":"ELECTRICAL & ELECTRONICS ENGINEERING","category":"2AG"}},"ELECTRONICS AND COMMUNICATIO N ENGG|2AR|ROK":{"similarCollege":{"college":"Sir M.Visvesvaraya Institute of Technology, Bangalore KRISHNADEVARAYANAGAR, HUNASAMARANAHALLI, VIA YELAHANKA,BANGALORE - 562 157","branch":"ELECTRONICS AND COMMUNICATIO N ENGG","category":"2AR"},"similarBranch":{"college":"B V V Sangha`s Basaveshwara Engineering College , Bagalkote (AUTONOMOUS) NIJALINGAPPA ROAD,BAGALKOT 587102","branch":"ELECTRICAL & ELECTRONICS ENGINEERING","category":"2AR"}},"ELECTRONICS AND COMMUNICATIO N ENGG|2BG|ROK":{"similarCollege":{"college":"University B.D.T College of Engineering, Davanagere P J EXTENSION,HADADI ROAD,DAVENGERE","branch":"ELECTRONICS AND COMMUNICATIO N ENGG","category":"2BG"},"similarBranch":{"college":"B V V Sangha`s Basaveshwara Engineering College , Bagalkote (AUTONOMOUS) NIJALINGAPPA ROAD,BAGALKOT 587102","branch":"ELECTRONICS AND COMMUNICATION ENGG","category":"2BG"}},"ELECTRONICS AND COMMUNICATIO N ENGG|3AG|ROK":{"similarCollege":{"college":"Govt.S K S J T Institute of Engineering, Bangalore AMBEDKAR VEEDHI, K.R. CIRCLE, BANGALORE-01","branch":"ELECTRONICS AND COMMUNICATIO N ENGG","category":"3AG"},"similarBranch":{"college":"B V V Sangha`s Basaveshwara Engineering College , Bagalkote (AUTONOMOUS) NIJALINGAPPA ROAD,BAGALKOT 587102","branch":"ELECTRICAL & ELECTRONICS ENGINEERING","category":"3AG"}},"ELECTRONICS AND COMMUNICATIO N ENGG|3AK|ROK":{"similarCollege":{"college":"Sahyadri College Of Engineering & Management, Adyar, Mangalore(AUTONOMOUS) 'SAHYADRI CAMPUS'N.H-48, ADYAR,MANGALORE","branch":"ELECTRONICS AND COMMUNICATIO N ENGG","category":"3AK"},"similarBranch":{"college":"B V V Sangha`s Basaveshwara Engineering College , Bagalkote (AUTONOMOUS) NIJALINGAPPA ROAD,BAGALKOT 587102","branch":"ELECTRONICS AND COMMUNICATION ENGG","category":"3AK"}},"ELECTRONICS AND COMMUNICATIO N ENGG|3BG|ROK":{"similarCollege":{"college":"Dayananda Sagar Academy of Technology & Management Technical Campus, Bangalore(AUTONOMOUS) UDAYAPURA,KANAKAPURA ROAD,BANGALORE URBAN","branch":"ELECTRONICS AND COMMUNICATIO N ENGG","category":"3BG"},"similarBranch":{"college":"B V V Sangha`s Basaveshwara Engineering College , Bagalkote (AUTONOMOUS) NIJALINGAPPA ROAD,BAGALKOT 587102","branch":"ELECTRICAL & ELECTRONICS ENGINEERING","category":"3BG"}},"ELECTRONICS AND COMMUNICATIO N ENGG|GM|ROK":{"similarCollege":{"college":"Malnad College of Engineering, Hassan(AUTONOMOUS) P.B. NO. 21, SALAGAME ROAD,HASSSAN","branch":"ELECTRONICS AND COMMUNICATIO N ENGG","category":"GM"},"similarBranch":{"college":"B V V Sangha`s Basaveshwara Engineering College , Bagalkote (AUTONOMOUS) NIJALINGAPPA ROAD,BAGALKOT 587102","branch":"ELECTRICAL & ELECTRONICS ENGINEERING","category":"GM"}},"ELECTRONICS AND COMMUNICATIO N ENGG|GMK|ROK":{"similarCollege":{"college":"B N M Institute of Technology, Bangalore (AUTONOMOUS) 12TH MAIN, 27TH CROSS, BSK SECOND STAGE","branch":"ELECTRONICS AND COMMUNICATIO N ENGG","category":"GMK"},"similarBranch":{"college":"B V V Sangha`s Basaveshwara Engineering College , Bagalkote (AUTONOMOUS) NIJALINGAPPA ROAD,BAGALKOT 587102","branch":"ELECTRICAL & ELECTRONICS ENGINEERING","category":"GMK"}},"ELECTRONICS AND COMMUNICATIO N ENGG|GMR|ROK":{"similarCollege":{"college":"J S S Academy of Technical Education, Bangalore JSSATE CAMPUS,UTTARAHALLI-KENGERI ROAD ,BANGALORE 560060","branch":"ELECTRONICS AND COMMUNICATIO N ENGG","category":"GMR"},"similarBranch":{"college":"B V V Sangha`s Basaveshwara Engineering College , Bagalkote (AUTONOMOUS) NIJALINGAPPA ROAD,BAGALKOT 587102","branch":"ELECTRICAL & ELECTRONICS ENGINEERING","category":"GMR"}},"ELECTRONICS AND COMMUNICATIO N ENGG|SCG|ROK":{"similarCollege":{"college":"P D A College of Engineering, Gulbarga(AUTONOMOUS) AIWAN-E-SHAHI AREA,STATION ROAD,GULBARGA-585102","branch":"ELECTRONICS AND COMMUNICATIO N ENGG","category":"SCG"},"similarBranch":{"college":"B V V Sangha`s Basaveshwara Engineering College , Bagalkote (AUTONOMOUS) NIJALINGAPPA ROAD,BAGALKOT 587102","branch":"ELECTRICAL & ELECTRONICS ENGINEERING","category":"SCG"}},"ELECTRONICS AND COMMUNICATIO N ENGG|SCR|ROK":{"similarCollege":{"college":"Dayananda Sagar Academy of Technology & Management Technical Campus, Bangalore(AUTONOMOUS) UDAYAPURA,KANAKAPURA ROAD,BANGALORE URBAN","branch":"ELECTRONICS AND COMMUNICATIO N ENGG","category":"SCR"},"similarBranch":{"college":"B V V Sangha`s Basaveshwara Engineering College , Bagalkote (AUTONOMOUS) NIJALINGAPPA ROAD,BAGALKOT 587102","branch":"ELECTRICAL & ELECTRONICS ENGINEERING","category":"SCR"}},"ELECTRONICS AND COMMUNICATIO N ENGG|STG|ROK":{"similarCollege":{"college":"University B.D.T College of Engineering, Davanagere P J EXTENSION,HADADI ROAD,DAVENGERE","branch":"ELECTRONICS AND COMMUNICATIO N ENGG","category":"STG"},"similarBranch":{"college":"B V V Sangha`s Basaveshwara Engineering College , Bagalkote (AUTONOMOUS) NIJALINGAPPA ROAD,BAGALKOT 587102","branch":"ELECTRICAL & ELECTRONICS ENGINEERING","category":"STG"}},"ELECTRONICS AND COMMUNICATIO N ENGG|STR|ROK":{"similarCollege":{"college":"KLE Technological University(Formerly (BVBCET) BVBHOOMARADDI COLLEGE CAMPUS, VIDYANAGAR, HUBBALLI","branch":"ELECTRONICS AND COMMUNICATIO N ENGG","category":"STR"},"similarBranch":{"college":"B V V Sangha`s Basaveshwara Engineering College , Bagalkote (AUTONOMOUS) NIJALINGAPPA ROAD,BAGALKOT 587102","branch":"ELECTRONICS AND COMMUNICATION ENGG","category":"STR"}},"ELECTRONICS AND COMMUNICATION ENGG|1G|ROK":{"similarCollege":{"college":"S.J B. Institute of Technology, Bangalore (AUTONOMOUS) BGS HEALTH & EDUCATION CITY,NO 67, UTTARAHALLI ROAD.KENGERI, BANGALORE -60","branch":"ELECTRONICS AND COMMUNICATION ENGG","category":"1G"},"similarBranch":{"college":"B V V Sangha`s Basaveshwara Engineering College , Bagalkote (AUTONOMOUS) NIJALINGAPPA ROAD,BAGALKOT 587102","branch":"COMPUTER SCIENCE AND ENGINEERING","category":"1G"}},"ELECTRONICS AND COMMUNICATION ENGG|2AG|ROK":{"similarCollege":{"college":"Nitte Meenakshi Institutute of Technology Bangalore","branch":"ELECTRONICS AND COMMUNICATION ENGG","category":"2AG"},"similarBranch":{"college":"B V V Sangha`s Basaveshwara Engineering College , Bagalkote (AUTONOMOUS) NIJALINGAPPA ROAD,BAGALKOT 587102","branch":"ELECTRONICS AND COMMUNICATIO N ENGG","category":"2AG"}},"ELECTRONICS AND COMMUNICATION ENGG|2AR|ROK":{"similarCollege":{"college":"Dayananda Sagar Academy of Technology & Management Technical Campus, Bangalore(AUTONOMOUS) UDAYAPURA,KANAKAPURA ROAD,BANGALORE URBAN","branch":"ELECTRONICS AND COMMUNICATION ENGG","category":"2AR"},"similarBranch":{"college":"B V V Sangha`s Basaveshwara Engineering College , Bagalkote (AUTONOMOUS) NIJALINGAPPA ROAD,BAGALKOT 587102","branch":"ELECTRONICS AND COMMUNICATIO N ENGG","category":"2AR"}},"ELECTRONICS AND COMMUNICATION ENGG|2BG|ROK":{"similarCollege":{"college":"Nitte Meenakshi Institutute of Technology Bangalore","branch":"ELECTRONICS AND COMMUNICATION ENGG","category":"2BG"},"similarBranch":{"college":"B V V Sangha`s Basaveshwara Engineering College , Bagalkote (AUTONOMOUS) NIJALINGAPPA ROAD,BAGALKOT 587102","branch":"ELECTRICAL & ELECTRONICS ENGINEERING","category":"2BG"}},"ELECTRONICS AND COMMUNICATION ENGG|2BH|HK":{"similarCollege":{"college":"P D A College of Engineering, Gulbarga(AUTONOMOUS) AIWAN-E-SHAHI AREA,STATION ROAD,GULBARGA-585102","branch":"ELECTRONICS AND COMMUNICATION ENGG","category":"2BH"},"similarBranch":null},"ELECTRONICS AND COMMUNICATION ENGG|2BH|ROK":{"similarCollege":{"college":"P D A College of Engineering, Gulbarga(AUTONOMOUS) AIWAN-E-SHAHI AREA,STATION ROAD,GULBARGA-585102","branch":"ELECTRONICS AND COMMUNICATION ENGG","category":"2BH"},"similarBranch":null},"ELECTRONICS AND COMMUNICATION ENGG|3AG|ROK":{"similarCollege":{"college":"P E S College of Engineering, Mandya(AUTONOMOUS) MANDYA: 571 401","branch":"ELECTRONICS AND COMMUNICATION ENGG","category":"3AG"},"similarBranch":{"college":"B V V Sangha`s Basaveshwara Engineering College , Bagalkote (AUTONOMOUS) NIJALINGAPPA ROAD,BAGALKOT 587102","branch":"ELECTRONICS AND COMMUNICATIO N ENGG","category":"3AG"}},"ELECTRONICS AND COMMUNICATION ENGG|3AK|ROK":{"similarCollege":{"college":"Sahyadri College Of Engineering & Management, Adyar, Mangalore(AUTONOMOUS) 'SAHYADRI CAMPUS'N.H-48, ADYAR,MANGALORE","branch":"ELECTRONICS AND COMMUNICATION ENGG","category":"3AK"},"similarBranch":{"college":"B V V Sangha`s Basaveshwara Engineering College , Bagalkote (AUTONOMOUS) NIJALINGAPPA ROAD,BAGALKOT 587102","branch":"ELECTRONICS AND COMMUNICATIO N ENGG","category":"3AK"}},"ELECTRONICS AND COMMUNICATION ENGG|3BG|ROK":{"similarCollege":{"college":"Govt.S K S J T Institute of Engineering, Bangalore AMBEDKAR VEEDHI, K.R. CIRCLE, BANGALORE-01","branch":"ELECTRONICS AND COMMUNICATION ENGG","category":"3BG"},"similarBranch":{"college":"B V V Sangha`s Basaveshwara Engineering College , Bagalkote (AUTONOMOUS) NIJALINGAPPA ROAD,BAGALKOT 587102","branch":"ELECTRONICS AND COMMUNICATIO N ENGG","category":"3BG"}},"ELECTRONICS AND COMMUNICATION ENGG|GM|ROK":{"similarCollege":{"college":"S.J B. Institute of Technology, Bangalore (AUTONOMOUS) BGS HEALTH & EDUCATION CITY,NO 67, UTTARAHALLI ROAD.KENGERI, BANGALORE -60","branch":"ELECTRONICS AND COMMUNICATION ENGG","category":"GM"},"similarBranch":{"college":"B V V Sangha`s Basaveshwara Engineering College , Bagalkote (AUTONOMOUS) NIJALINGAPPA ROAD,BAGALKOT 587102","branch":"ELECTRONICS AND COMMUNICATIO N ENGG","category":"GM"}},"ELECTRONICS AND COMMUNICATION ENGG|GMH|HK":{"similarCollege":{"college":"S.J B. Institute of Technology, Bangalore (AUTONOMOUS) BGS HEALTH & EDUCATION CITY,NO 67, UTTARAHALLI ROAD.KENGERI, BANGALORE -60","branch":"ELECTRONICS AND COMMUNICATION ENGG","category":"GMH"},"similarBranch":{"college":"B V V Sangha`s Basaveshwara Engineering College , Bagalkote (AUTONOMOUS) NIJALINGAPPA ROAD,BAGALKOT 587102","branch":"ELECTRICAL & ELECTRONICS ENGINEERING","category":"GMH"}},"ELECTRONICS AND COMMUNICATION ENGG|GMH|ROK":{"similarCollege":{"college":"Vidya Vardhaka College of Engineering, Mysore(AUTONOMOUS) P.B.NO.206,GOKULAM 3RD STAGE,MYSORE","branch":"ELECTRONICS AND COMMUNICATION ENGG","category":"GMH"},"similarBranch":{"college":"B V V Sangha`s Basaveshwara Engineering College , Bagalkote (AUTONOMOUS) NIJALINGAPPA ROAD,BAGALKOT 587102","branch":"ELECTRICAL & ELECTRONICS ENGINEERING","category":"GMH"}},"ELECTRONICS AND COMMUNICATION ENGG|GMK|ROK":{"similarCollege":{"college":"Govt.S K S J T Institute of Engineering, Bangalore AMBEDKAR VEEDHI, K.R. CIRCLE, BANGALORE-01","branch":"ELECTRONICS AND COMMUNICATION ENGG","category":"GMK"},"similarBranch":{"college":"B V V Sangha`s Basaveshwara Engineering College , Bagalkote (AUTONOMOUS) NIJALINGAPPA ROAD,BAGALKOT 587102","branch":"ELECTRONICS AND COMMUNICATIO N ENGG","category":"GMK"}},"ELECTRONICS AND COMMUNICATION ENGG|GMR|ROK":{"similarCollege":{"college":"Govt.S K S J T Institute of Engineering, Bangalore AMBEDKAR VEEDHI, K.R. CIRCLE, BANGALORE-01","branch":"ELECTRONICS AND COMMUNICATION ENGG","category":"GMR"},"similarBranch":{"college":"B V V Sangha`s Basaveshwara Engineering College , Bagalkote (AUTONOMOUS) NIJALINGAPPA ROAD,BAGALKOT 587102","branch":"ELECTRONICS AND COMMUNICATIO N ENGG","category":"GMR"}},"ELECTRONICS AND COMMUNICATION ENGG|SCG|ROK":{"similarCollege":{"college":"K L E Technological Univeristy, Belgaum Campus (Formerly KLE Dr M.S.Sheshagiri College of Engineering and Technology) UDYAMBAGH,BELGAUM","branch":"ELECTRONICS AND COMMUNICATION ENGG","category":"SCG"},"similarBranch":{"college":"B V V Sangha`s Basaveshwara Engineering College , Bagalkote (AUTONOMOUS) NIJALINGAPPA ROAD,BAGALKOT 587102","branch":"ELECTRONICS AND COMMUNICATIO N ENGG","category":"SCG"}},"ELECTRONICS AND COMMUNICATION ENGG|SCH|HK":{"similarCollege":{"college":"Govt.S K S J T Institute of Engineering, Bangalore AMBEDKAR VEEDHI, K.R. CIRCLE, BANGALORE-01","branch":"ELECTRONICS AND COMMUNICATION ENGG","category":"SCH"},"similarBranch":{"college":"B V V Sangha`s Basaveshwara Engineering College , Bagalkote (AUTONOMOUS) NIJALINGAPPA ROAD,BAGALKOT 587102","branch":"ELECTRICAL & ELECTRONICS ENGINEERING","category":"SCH"}},"ELECTRONICS AND COMMUNICATION ENGG|SCH|ROK":{"similarCollege":{"college":"Vidya Vardhaka College of Engineering, Mysore(AUTONOMOUS) P.B.NO.206,GOKULAM 3RD STAGE,MYSORE","branch":"ELECTRONICS AND COMMUNICATION ENGG","category":"SCH"},"similarBranch":{"college":"B V V Sangha`s Basaveshwara Engineering College , Bagalkote (AUTONOMOUS) NIJALINGAPPA ROAD,BAGALKOT 587102","branch":"CIVIL ENGINEERING","category":"SCH"}},"ELECTRONICS AND COMMUNICATION ENGG|SCR|ROK":{"similarCollege":{"college":"P E S College of Engineering, Mandya(AUTONOMOUS) MANDYA: 571 401","branch":"ELECTRONICS AND COMMUNICATION ENGG","category":"SCR"},"similarBranch":{"college":"B V V Sangha`s Basaveshwara Engineering College , Bagalkote (AUTONOMOUS) NIJALINGAPPA ROAD,BAGALKOT 587102","branch":"ELECTRONICS AND COMMUNICATIO N ENGG","category":"SCR"}},"ELECTRONICS AND COMMUNICATION ENGG|STG|ROK":{"similarCollege":{"college":"University B.D.T College of Engineering, Davanagere P J EXTENSION,HADADI ROAD,DAVENGERE","branch":"ELECTRONICS AND COMMUNICATION ENGG","category":"STG"},"similarBranch":{"college":"B V V Sangha`s Basaveshwara Engineering College , Bagalkote (AUTONOMOUS) NIJALINGAPPA ROAD,BAGALKOT 587102","branch":"COMPUTER SCIENCE AND ENGINEERING","category":"STG"}},"ELECTRONICS AND COMMUNICATION ENGG|STR|ROK":{"similarCollege":{"college":"Vidya Vardhaka College of Engineering, Mysore(AUTONOMOUS) P.B.NO.206,GOKULAM 3RD STAGE,MYSORE","branch":"ELECTRONICS AND COMMUNICATION ENGG","category":"STR"},"similarBranch":{"college":"B V V Sangha`s Basaveshwara Engineering College , Bagalkote (AUTONOMOUS) NIJALINGAPPA ROAD,BAGALKOT 587102","branch":"COMPUTER SCIENCE AND ENGINEERING","category":"STR"}},"ELECTRONICS AND COMMUNICATION ENGG|STRH|ROK":{"similarCollege":{"college":"Bheemanna Khandre Institute of Technology, Bhalki BHALKI-HUMNABAD ROAD,BHALKI- 585328,DIST. BIDAR","branch":"ELECTRONICS AND COMMUNICATION ENGG","category":"STRH"},"similarBranch":null},"INDUSTRIAL & PRODUCTION ENGINEERING|GMH|ROK":{"similarCollege":{"college":"P D A College of Engineering, Gulbarga(AUTONOMOUS) AIWAN-E-SHAHI AREA,STATION ROAD,GULBARGA-585102","branch":"INDUSTRIAL & PRODUCTION ENGINEERING","category":"GMH"},"similarBranch":{"college":"B V V Sangha`s Basaveshwara Engineering College , Bagalkote (AUTONOMOUS) NIJALINGAPPA ROAD,BAGALKOT 587102","branch":"COMPUTER SCIENCE AND ENGINEERING","category":"GMH"}},"IP Ind.Prodn.|GM|ROK":{"similarCollege":{"college":"Sri Jayachamarajendra College of Engineering(Constituent College of JSS Science & Technology University), Mysore JSS TECHNICAL INSTITUTIONS CAMPUS,MANASAGANGOTHRI PO,MYSORE","branch":"IP Ind.Prodn.","category":"GM"},"similarBranch":{"college":"B V V Sangha`s Basaveshwara Engineering College , Bagalkote (AUTONOMOUS) NIJALINGAPPA ROAD,BAGALKOT 587102","branch":"COMPUTER SCIENCE AND ENGINEERING","category":"GM"}},"MECHANICAL ENGINEERING|2AH|ROK":{"similarCollege":{"college":"St.Joseph Engineering College, Mangalore(AUTONOMOUS) MANGALORE","branch":"MECHANICAL ENGINEERING","category":"2AH"},"similarBranch":{"college":"B V V Sangha`s Basaveshwara Engineering College , Bagalkote (AUTONOMOUS) NIJALINGAPPA ROAD,BAGALKOT 587102","branch":"COMPUTER SCIENCE AND ENGINEERING","category":"2AH"}},"MECHANICAL ENGINEERING|3BH|ROK":{"similarCollege":{"college":"P D A College of Engineering, Gulbarga(AUTONOMOUS) AIWAN-E-SHAHI AREA,STATION ROAD,GULBARGA-585102","branch":"MECHANICAL ENGINEERING","category":"3BH"},"similarBranch":null},"MECHANICAL ENGINEERING|GM|ROK":{"similarCollege":{"college":"P D A College of Engineering, Gulbarga(AUTONOMOUS) AIWAN-E-SHAHI AREA,STATION ROAD,GULBARGA-585102","branch":"MECHANICAL ENGINEERING","category":"GM"},"similarBranch":{"college":"B V V Sangha`s Basaveshwara Engineering College , Bagalkote (AUTONOMOUS) NIJALINGAPPA ROAD,BAGALKOT 587102","branch":"IP Ind.Prodn.","category":"GM"}},"MECHANICAL ENGINEERING|GMH|ROK":{"similarCollege":{"college":"East West College Of Engineering, Yelahanka,Bangalore NO.13 SECTOR \"A\", YELAHANKA NEW TOWN,YELAHANKA, BANGALORE-560064","branch":"MECHANICAL ENGINEERING","category":"GMH"},"similarBranch":{"college":"B V V Sangha`s Basaveshwara Engineering College , Bagalkote (AUTONOMOUS) NIJALINGAPPA ROAD,BAGALKOT 587102","branch":"INDUSTRIAL & PRODUCTION ENGINEERING","category":"GMH"}},"MECHANICAL ENGINEERING|SCH|ROK":{"similarCollege":{"college":"Government Engineering College, Hassan DAIRY CIRCLE, B M ROAD, HASSAN","branch":"MECHANICAL ENGINEERING","category":"SCH"},"similarBranch":{"college":"B V V Sangha`s Basaveshwara Engineering College , Bagalkote (AUTONOMOUS) NIJALINGAPPA ROAD,BAGALKOT 587102","branch":"ELECTRONICS AND COMMUNICATION ENGG","category":"SCH"}},"MECHANICAL ENGINEERING|STH|ROK":{"similarCollege":{"college":"The Oxford College of Engineering, Bangalore HOSUR ROAD,BOMMANAHALLI,BANGALORE","branch":"MECHANICAL ENGINEERING","category":"STH"},"similarBranch":{"college":"B V V Sangha`s Basaveshwara Engineering College , Bagalkote (AUTONOMOUS) NIJALINGAPPA ROAD,BAGALKOT 587102","branch":"CIVIL ENGINEERING","category":"STH"}}}}