{"cutoffs":[{"college_code":"E209","college_name":"Jyothi Institute of Technology, Kanakapura Road,Bangalore ,BANGALORE","course_name":"ARTIFICIAL INTELLIGENCE AND DATA SCIENCE","category":"1G","seat_type":"ROK","rounds":{"2024_R1":78134,"2024_R2":118493,"2024_R3":118493},"min_rank":78134,"max_rank":118493},{"college_code":"E209","college_name":"Jyothi Institute of Technology, Kanakapura Road,Bangalore ,BANGALORE","course_name":"ARTIFICIAL INTELLIGENCE AND DATA SCIENCE","category":"2AG","seat_type":"ROK","rounds":{"2024_R1":57469,"2024_R2":67307,"2024_R3":162734},"min_rank":57469,"max_rank":162734},{"college_code":"E209","college_name":"Jyothi Institute of Technology, Kanakapura Road,Bangalore ,BANGALORE","course_name":"ARTIFICIAL INTELLIGENCE AND DATA SCIENCE","category":"2BG","seat_type":"ROK","rounds":{"2024_R1":67636,"2024_R2":67636,"2024_R3":67636},"min_rank":67636,"max_rank":67636},{"college_code":"E209","college_name":"Jyothi Institute of Technology, Kanakapura Road,Bangalore ,BANGALORE","course_name":"ARTIFICIAL INTELLIGENCE AND DATA SCIENCE","category":"3AG","seat_type":"ROK","rounds":{"2024_R1":49038,"2024_R2":63876,"2024_R3":71816},"min_rank":49038,"max_rank":71816},{"college_code":"E209","college_name":"Jyothi Institute of Technology, Kanakapura Road,Bangalore ,BANGALORE","course_name":"ARTIFICIAL INTELLIGENCE AND DATA SCIENCE","category":"3BG","seat_type":"ROK","rounds":{"2024_R1":52187,"2024_R2":69083,"2024_R3":170172},"min_rank":52187,"max_rank":170172},{"college_code":"E209","college_name":"Jyothi Institute of Technology, Kanakapura Road,Bangalore ,BANGALORE","course_name":"ARTIFICIAL INTELLIGENCE AND DATA SCIENCE","category":"GM","seat_type":"ROK","rounds":{"2024_R1":48847,"2024_R2":55793,"2024_R3":66234},"min_rank":48847,"max_rank":66234},{"college_code":"E209","college_name":"Jyothi Institute of Technology, Kanakapura Road,Bangalore ,BANGALORE","course_name":"ARTIFICIAL INTELLIGENCE AND DATA SCIENCE","category":"GMR","seat_type":"ROK","rounds":{"2024_R1":64455,"2024_R2":72736,"2024_R3":162359},"min_rank":64455,"max_rank":162359},{"college_code":"E209","college_name":"Jyothi Institute of Technology, Kanakapura Road,Bangalore ,BANGALORE","course_name":"ARTIFICIAL INTELLIGENCE AND DATA SCIENCE","category":"SCG","seat_type":"ROK","rounds":{"2024_R1":147964,"2024_R2":147964,"2024_R3":147964},"min_rank":147964,"max_rank":147964},{"college_code":"E209","college_name":"Jyothi Institute of Technology, Kanakapura Road,Bangalore ,BANGALORE","course_name":"ARTIFICIAL INTELLIGENCE AND MACHINE LEARNING","category":"1G","seat_type":"ROK","rounds":{"2025_R1":44762,"2025_R2":68482,"2025_R3":68482},"min_rank":44762,"max_rank":68482},{"college_code":"E209","college_name":"Jyothi Institute of Technology, Kanakapura Road,Bangalore ,BANGALORE","course_name":"ARTIFICIAL INTELLIGENCE AND MACHINE LEARNING","category":"2AG","seat_type":"ROK","rounds":{"2025_R1":49571,"2025_R2":67752,"2025_R3":67752},"min_rank":49571,"max_rank":67752},{"college_code":"E209","college_name":"Jyothi Institute of Technology, Kanakapura Road,Bangalore ,BANGALORE","course_name":"ARTIFICIAL INTELLIGENCE AND MACHINE LEARNING","category":"2BG","seat_type":"ROK","rounds":{"2025_R1":55055,"2025_R2":62145,"2025_R3":80257},"min_rank":55055,"max_rank":80257},{"college_code":"E209","college_name":"Jyothi Institute of Technology, Kanakapura Road,Bangalore ,BANGALORE","course_name":"ARTIFICIAL INTELLIGENCE AND MACHINE LEARNING","category":"3AG","seat_type":"ROK","rounds":{"2025_R1":42707.5,"2025_R2":49880,"2025_R3":68471},"min_rank":42707.5,"max_rank":68471},{"college_code":"E209","college_name":"Jyothi Institute of Technology, Kanakapura Road,Bangalore ,BANGALORE","course_name":"ARTIFICIAL INTELLIGENCE AND MACHINE LEARNING","category":"3BG","seat_type":"ROK","rounds":{"2025_R1":43585,"2025_R2":49019,"2025_R3":49019},"min_rank":43585,"max_rank":49019},{"college_code":"E209","college_name":"Jyothi Institute of Technology, Kanakapura Road,Bangalore ,BANGALORE","course_name":"ARTIFICIAL INTELLIGENCE AND MACHINE LEARNING","category":"3BH","seat_type":"HK","rounds":{"2025_R1":49131,"2025_R2":92869,"2025_R3":92869},"min_rank":49131,"max_rank":92869},{"college_code":"E209","college_name":"Jyothi Institute of Technology, Kanakapura Road,Bangalore ,BANGALORE","course_name":"ARTIFICIAL INTELLIGENCE AND MACHINE LEARNING","category":"3BH","seat_type":"ROK","rounds":{"2025_R1":49131},"min_rank":49131,"max_rank":49131},{"college_code":"E209","college_name":"Jyothi Institute of Technology, Kanakapura Road,Bangalore ,BANGALORE","course_name":"ARTIFICIAL INTELLIGENCE AND MACHINE LEARNING","category":"GM","seat_type":"ROK","rounds":{"2025_R1":42351,"2025_R2":48937,"2025_R3":48937},"min_rank":42351,"max_rank":48937},{"college_code":"E209","college_name":"Jyothi Institute of Technology, Kanakapura Road,Bangalore ,BANGALORE","course_name":"ARTIFICIAL INTELLIGENCE AND MACHINE LEARNING","category":"GMH","seat_type":"HK","rounds":{"2025_R1":45132,"2025_R2":68296,"2025_R3":68296},"min_rank":45132,"max_rank":68296},{"college_code":"E209","college_name":"Jyothi Institute of Technology, Kanakapura Road,Bangalore ,BANGALORE","course_name":"ARTIFICIAL INTELLIGENCE AND MACHINE LEARNING","category":"GMH","seat_type":"ROK","rounds":{"2025_R1":45132},"min_rank":45132,"max_rank":45132},{"college_code":"E209","college_name":"Jyothi Institute of Technology, Kanakapura Road,Bangalore ,BANGALORE","course_name":"ARTIFICIAL INTELLIGENCE AND MACHINE LEARNING","category":"GMR","seat_type":"ROK","rounds":{"2025_R1":48441,"2025_R2":67329,"2025_R3":72261},"min_rank":48441,"max_rank":72261},{"college_code":"E209","college_name":"Jyothi Institute of Technology, Kanakapura Road,Bangalore ,BANGALORE","course_name":"ARTIFICIAL INTELLIGENCE AND MACHINE LEARNING","category":"SCG","seat_type":"ROK","rounds":{"2025_R1":107520,"2025_R2":111005,"2025_R3":111005},"min_rank":107520,"max_rank":111005},{"college_code":"E209","college_name":"Jyothi Institute of Technology, Kanakapura Road,Bangalore ,BANGALORE","course_name":"ARTIFICIAL INTELLIGENCE AND MACHINE LEARNING","category":"STG","seat_type":"ROK","rounds":{"2025_R1":94538,"2025_R2":135028,"2025_R3":135028},"min_rank":94538,"max_rank":135028},{"college_code":"E209","college_name":"Jyothi Institute of Technology, Kanakapura Road,Bangalore ,BANGALORE","course_name":"CIVIL ENGINEERING","category":"GM","seat_type":"ROK","rounds":{"2024_R1":114399,"2024_R2":262028,"2024_R3":null,"2025_R1":148565,"2025_R2":261588,"2025_R3":246755},"min_rank":114399,"max_rank":262028},{"college_code":"E209","college_name":"Jyothi Institute of Technology, Kanakapura Road,Bangalore ,BANGALORE","course_name":"CIVIL ENGINEERING","category":"GMH","seat_type":"ROK","rounds":{"2025_R1":194013},"min_rank":194013,"max_rank":194013},{"college_code":"E209","college_name":"Jyothi Institute of Technology, Kanakapura Road,Bangalore ,BANGALORE","course_name":"COMPUTER SCIENCE AND ENGINEERING","category":"1G","seat_type":"ROK","rounds":{"2024_R1":56832,"2024_R2":85479,"2024_R3":121912,"2025_R1":51978,"2025_R2":68827,"2025_R3":108237},"min_rank":51978,"max_rank":121912},{"college_code":"E209","college_name":"Jyothi Institute of Technology, Kanakapura Road,Bangalore ,BANGALORE","course_name":"COMPUTER SCIENCE AND ENGINEERING","category":"2AG","seat_type":"ROK","rounds":{"2024_R1":50133,"2024_R2":58841,"2024_R3":109905,"2025_R1":50662,"2025_R2":68135,"2025_R3":121379},"min_rank":50133,"max_rank":121379},{"college_code":"E209","college_name":"Jyothi Institute of Technology, Kanakapura Road,Bangalore ,BANGALORE","course_name":"COMPUTER SCIENCE AND ENGINEERING","category":"2AH","seat_type":"ROK","rounds":{"2025_R1":59542},"min_rank":59542,"max_rank":59542},{"college_code":"E209","college_name":"Jyothi Institute of Technology, Kanakapura Road,Bangalore ,BANGALORE","course_name":"COMPUTER SCIENCE AND ENGINEERING","category":"2AK","seat_type":"ROK","rounds":{"2024_R1":88775,"2024_R2":117928,"2024_R3":112466,"2025_R1":61704,"2025_R2":91157,"2025_R3":130525.5},"min_rank":61704,"max_rank":130525.5},{"college_code":"E209","college_name":"Jyothi Institute of Technology, Kanakapura Road,Bangalore ,BANGALORE","course_name":"COMPUTER SCIENCE AND ENGINEERING","category":"2AR","seat_type":"ROK","rounds":{"2024_R1":70989,"2024_R2":83837,"2024_R3":null,"2025_R1":65866,"2025_R2":87016,"2025_R3":200514},"min_rank":65866,"max_rank":200514},{"college_code":"E209","college_name":"Jyothi Institute of Technology, Kanakapura Road,Bangalore ,BANGALORE","course_name":"COMPUTER SCIENCE AND ENGINEERING","category":"2BG","seat_type":"ROK","rounds":{"2024_R1":69816,"2024_R2":76708,"2024_R3":null,"2025_R1":67356,"2025_R2":80458,"2025_R3":112900},"min_rank":67356,"max_rank":112900},{"college_code":"E209","college_name":"Jyothi Institute of Technology, Kanakapura Road,Bangalore ,BANGALORE","course_name":"COMPUTER SCIENCE AND ENGINEERING","category":"3AG","seat_type":"ROK","rounds":{"2024_R1":39458,"2024_R2":57679,"2024_R3":68139,"2025_R1":43916,"2025_R2":61559,"2025_R3":83375},"min_rank":39458,"max_rank":83375},{"college_code":"E209","college_name":"Jyothi Institute of Technology, Kanakapura Road,Bangalore ,BANGALORE","course_name":"COMPUTER SCIENCE AND ENGINEERING","category":"3BG","seat_type":"ROK","rounds":{"2024_R1":43798,"2024_R2":56416,"2024_R3":112183,"2025_R1":44652,"2025_R2":64583,"2025_R3":81088},"min_rank":43798,"max_rank":112183},{"college_code":"E209","college_name":"Jyothi Institute of Technology, Kanakapura Road,Bangalore ,BANGALORE","course_name":"COMPUTER SCIENCE AND ENGINEERING","category":"3BR","seat_type":"ROK","rounds":{"2024_R1":56431,"2024_R2":90249,"2024_R3":null,"2025_R1":52085,"2025_R2":93721,"2025_R3":93721},"min_rank":52085,"max_rank":93721},{"college_code":"E209","college_name":"Jyothi Institute of Technology, Kanakapura Road,Bangalore ,BANGALORE","course_name":"COMPUTER SCIENCE AND ENGINEERING","category":"GM","seat_type":"ROK","rounds":{"2024_R1":38224,"2024_R2":49038,"2024_R3":66245,"2025_R1":42519.5,"2025_R2":55893,"2025_R3":68827},"min_rank":38224,"max_rank":68827},{"college_code":"E209","college_name":"Jyothi Institute of Technology, Kanakapura Road,Bangalore ,BANGALORE","course_name":"COMPUTER SCIENCE AND ENGINEERING","category":"GMH","seat_type":"HK","rounds":{"2025_R1":48882,"2025_R2":60826,"2025_R3":89954},"min_rank":48882,"max_rank":89954},{"college_code":"E209","college_name":"Jyothi Institute of Technology, Kanakapura Road,Bangalore ,BANGALORE","course_name":"COMPUTER SCIENCE AND ENGINEERING","category":"GMH","seat_type":"ROK","rounds":{"2025_R1":48882},"min_rank":48882,"max_rank":48882},{"college_code":"E209","college_name":"Jyothi Institute of Technology, Kanakapura Road,Bangalore ,BANGALORE","course_name":"COMPUTER SCIENCE AND ENGINEERING","category":"GMK","seat_type":"ROK","rounds":{"2024_R1":60079,"2024_R2":90866,"2024_R3":90866,"2025_R1":55926,"2025_R2":76595,"2025_R3":120295},"min_rank":55926,"max_rank":120295},{"college_code":"E209","college_name":"Jyothi Institute of Technology, Kanakapura Road,Bangalore ,BANGALORE","course_name":"COMPUTER SCIENCE AND ENGINEERING","category":"GMR","seat_type":"ROK","rounds":{"2024_R1":41909,"2024_R2":66963,"2024_R3":146693,"2025_R1":52072,"2025_R2":68222,"2025_R3":89742},"min_rank":41909,"max_rank":146693},{"college_code":"E209","college_name":"Jyothi Institute of Technology, Kanakapura Road,Bangalore ,BANGALORE","course_name":"COMPUTER SCIENCE AND ENGINEERING","category":"GMRH","seat_type":"HK","rounds":{"2025_R1":55278,"2025_R2":82485,"2025_R3":95001},"min_rank":55278,"max_rank":95001},{"college_code":"E209","college_name":"Jyothi Institute of Technology, Kanakapura Road,Bangalore ,BANGALORE","course_name":"COMPUTER SCIENCE AND ENGINEERING","category":"GMRH","seat_type":"ROK","rounds":{"2025_R1":55278},"min_rank":55278,"max_rank":55278},{"college_code":"E209","college_name":"Jyothi Institute of Technology, Kanakapura Road,Bangalore ,BANGALORE","course_name":"COMPUTER SCIENCE AND ENGINEERING","category":"SCG","seat_type":"ROK","rounds":{"2024_R1":138697,"2024_R2":157395,"2024_R3":268767,"2025_R1":145010,"2025_R2":180001,"2025_R3":180001},"min_rank":138697,"max_rank":268767},{"college_code":"E209","college_name":"Jyothi Institute of Technology, Kanakapura Road,Bangalore ,BANGALORE","course_name":"COMPUTER SCIENCE AND ENGINEERING","category":"SCH","seat_type":"HK","rounds":{"2025_R1":161758,"2025_R2":185774,"2025_R3":185774},"min_rank":161758,"max_rank":185774},{"college_code":"E209","college_name":"Jyothi Institute of Technology, Kanakapura Road,Bangalore ,BANGALORE","course_name":"COMPUTER SCIENCE AND ENGINEERING","category":"SCH","seat_type":"ROK","rounds":{"2025_R1":161758},"min_rank":161758,"max_rank":161758},{"college_code":"E209","college_name":"Jyothi Institute of Technology, Kanakapura Road,Bangalore ,BANGALORE","course_name":"COMPUTER SCIENCE AND ENGINEERING","category":"STG","seat_type":"ROK","rounds":{"2024_R1":150342,"2024_R2":272287,"2024_R3":202628,"2025_R1":157362,"2025_R2":257875,"2025_R3":257875},"min_rank":150342,"max_rank":272287},{"college_code":"E209","college_name":"Jyothi Institute of Technology, Kanakapura Road,Bangalore ,BANGALORE","course_name":"COMPUTER SCIENCE AND ENGINEERING","category":"STH","seat_type":"ROK","rounds":{"2025_R1":240052},"min_rank":240052,"max_rank":240052},{"college_code":"E209","college_name":"Jyothi Institute of Technology, Kanakapura Road,Bangalore ,BANGALORE","course_name":"ELECTRONICS AND COMMUNICATIO N ENGG","category":"GM","seat_type":"ROK","rounds":{"2025_R2":78592,"2025_R3":250723},"min_rank":78592,"max_rank":250723},{"college_code":"E209","college_name":"Jyothi Institute of Technology, Kanakapura Road,Bangalore ,BANGALORE","course_name":"ELECTRONICS AND COMMUNICATION ENGG","category":"1G","seat_type":"ROK","rounds":{"2024_R1":69783,"2024_R2":113313,"2024_R3":null,"2025_R1":65745},"min_rank":65745,"max_rank":113313},{"college_code":"E209","college_name":"Jyothi Institute of Technology, Kanakapura Road,Bangalore ,BANGALORE","course_name":"ELECTRONICS AND COMMUNICATION ENGG","category":"1RH","seat_type":"ROK","rounds":{"2025_R1":152615},"min_rank":152615,"max_rank":152615},{"college_code":"E209","college_name":"Jyothi Institute of Technology, Kanakapura Road,Bangalore ,BANGALORE","course_name":"ELECTRONICS AND COMMUNICATION ENGG","category":"2AG","seat_type":"ROK","rounds":{"2024_R1":70236,"2024_R2":104978,"2024_R3":null,"2025_R1":66465},"min_rank":66465,"max_rank":104978},{"college_code":"E209","college_name":"Jyothi Institute of Technology, Kanakapura Road,Bangalore ,BANGALORE","course_name":"ELECTRONICS AND COMMUNICATION ENGG","category":"2AH","seat_type":"ROK","rounds":{"2025_R1":88707},"min_rank":88707,"max_rank":88707},{"college_code":"E209","college_name":"Jyothi Institute of Technology, Kanakapura Road,Bangalore ,BANGALORE","course_name":"ELECTRONICS AND COMMUNICATION ENGG","category":"2AR","seat_type":"ROK","rounds":{"2024_R1":97880,"2024_R2":156311,"2024_R3":null,"2025_R1":87299},"min_rank":87299,"max_rank":156311},{"college_code":"E209","college_name":"Jyothi Institute of Technology, Kanakapura Road,Bangalore ,BANGALORE","course_name":"ELECTRONICS AND COMMUNICATION ENGG","category":"2BG","seat_type":"ROK","rounds":{"2024_R1":115086,"2024_R2":154959,"2024_R3":null,"2025_R1":106965},"min_rank":106965,"max_rank":154959},{"college_code":"E209","college_name":"Jyothi Institute of Technology, Kanakapura Road,Bangalore ,BANGALORE","course_name":"ELECTRONICS AND COMMUNICATION ENGG","category":"3AG","seat_type":"ROK","rounds":{"2024_R1":59859,"2024_R2":75398,"2024_R3":null,"2025_R1":57885},"min_rank":57885,"max_rank":75398},{"college_code":"E209","college_name":"Jyothi Institute of Technology, Kanakapura Road,Bangalore ,BANGALORE","course_name":"ELECTRONICS AND COMMUNICATION ENGG","category":"3BG","seat_type":"ROK","rounds":{"2024_R1":62230,"2024_R2":76133,"2024_R3":null,"2025_R1":60251},"min_rank":60251,"max_rank":76133},{"college_code":"E209","college_name":"Jyothi Institute of Technology, Kanakapura Road,Bangalore ,BANGALORE","course_name":"ELECTRONICS AND COMMUNICATION ENGG","category":"3BR","seat_type":"ROK","rounds":{"2024_R1":null,"2024_R2":null,"2024_R3":null,"2025_R1":68732},"min_rank":68732,"max_rank":68732},{"college_code":"E209","college_name":"Jyothi Institute of Technology, Kanakapura Road,Bangalore ,BANGALORE","course_name":"ELECTRONICS AND COMMUNICATION ENGG","category":"GM","seat_type":"ROK","rounds":{"2024_R1":54239,"2024_R2":72150,"2024_R3":263223,"2025_R1":48594},"min_rank":48594,"max_rank":263223},{"college_code":"E209","college_name":"Jyothi Institute of Technology, Kanakapura Road,Bangalore ,BANGALORE","course_name":"ELECTRONICS AND COMMUNICATION ENGG","category":"GMH","seat_type":"ROK","rounds":{"2025_R1":58542},"min_rank":58542,"max_rank":58542},{"college_code":"E209","college_name":"Jyothi Institute of Technology, Kanakapura Road,Bangalore ,BANGALORE","course_name":"ELECTRONICS AND COMMUNICATION ENGG","category":"GMK","seat_type":"ROK","rounds":{"2024_R1":75220,"2024_R2":75220,"2024_R3":null,"2025_R1":56646},"min_rank":56646,"max_rank":75220},{"college_code":"E209","college_name":"Jyothi Institute of Technology, Kanakapura Road,Bangalore ,BANGALORE","course_name":"ELECTRONICS AND COMMUNICATION ENGG","category":"GMR","seat_type":"ROK","rounds":{"2024_R1":80862,"2024_R2":106358,"2024_R3":null,"2025_R1":62993},"min_rank":62993,"max_rank":106358},{"college_code":"E209","college_name":"Jyothi Institute of Technology, Kanakapura Road,Bangalore ,BANGALORE","course_name":"ELECTRONICS AND COMMUNICATION ENGG","category":"SCG","seat_type":"ROK","rounds":{"2024_R1":182027,"2024_R2":263223,"2024_R3":null,"2025_R1":169816},"min_rank":169816,"max_rank":263223},{"college_code":"E209","college_name":"Jyothi Institute of Technology, Kanakapura Road,Bangalore ,BANGALORE","course_name":"ELECTRONICS AND COMMUNICATION ENGG","category":"SCH","seat_type":"ROK","rounds":{"2025_R1":236337},"min_rank":236337,"max_rank":236337},{"college_code":"E209","college_name":"Jyothi Institute of Technology, Kanakapura Road,Bangalore ,BANGALORE","course_name":"ELECTRONICS AND COMMUNICATION ENGG","category":"SCK","seat_type":"ROK","rounds":{"2024_R1":225292,"2024_R2":null,"2024_R3":null,"2025_R1":252386},"min_rank":225292,"max_rank":252386},{"college_code":"E209","college_name":"Jyothi Institute of Technology, Kanakapura Road,Bangalore ,BANGALORE","course_name":"ELECTRONICS AND COMMUNICATION ENGG","category":"SCR","seat_type":"ROK","rounds":{"2024_R1":248748,"2024_R2":null,"2024_R3":null,"2025_R1":201386},"min_rank":201386,"max_rank":248748},{"college_code":"E209","college_name":"Jyothi Institute of Technology, Kanakapura Road,Bangalore ,BANGALORE","course_name":"ELECTRONICS AND COMMUNICATION ENGG","category":"STG","seat_type":"ROK","rounds":{"2024_R1":203498,"2024_R2":201496,"2024_R3":null,"2025_R1":193054},"min_rank":193054,"max_rank":203498},{"college_code":"E209","college_name":"Jyothi Institute of Technology, Kanakapura Road,Bangalore ,BANGALORE","course_name":"ELECTRONICS AND COMMUNICATION ENGG","category":"STR","seat_type":"ROK","rounds":{"2024_R1":231830,"2024_R2":null,"2024_R3":null,"2025_R1":242925},"min_rank":231830,"max_rank":242925},{"college_code":"E209","college_name":"Jyothi Institute of Technology, Kanakapura Road,Bangalore ,BANGALORE","course_name":"INFORMATION SCIENCE AND ENGINEERING","category":"1G","seat_type":"ROK","rounds":{"2024_R1":82572,"2024_R2":95469,"2024_R3":181981,"2025_R1":77299,"2025_R2":77299,"2025_R3":140585},"min_rank":77299,"max_rank":181981},{"college_code":"E209","college_name":"Jyothi Institute of Technology, Kanakapura Road,Bangalore ,BANGALORE","course_name":"INFORMATION SCIENCE AND ENGINEERING","category":"2AG","seat_type":"ROK","rounds":{"2024_R1":56478,"2024_R2":70983,"2024_R3":159558,"2025_R1":55193,"2025_R2":84830,"2025_R3":128151},"min_rank":55193,"max_rank":159558},{"college_code":"E209","college_name":"Jyothi Institute of Technology, Kanakapura Road,Bangalore ,BANGALORE","course_name":"INFORMATION SCIENCE AND ENGINEERING","category":"2BG","seat_type":"ROK","rounds":{"2024_R1":97209,"2024_R2":129460,"2024_R3":null,"2025_R1":80257,"2025_R2":95888,"2025_R3":91752},"min_rank":80257,"max_rank":129460},{"college_code":"E209","college_name":"Jyothi Institute of Technology, Kanakapura Road,Bangalore ,BANGALORE","course_name":"INFORMATION SCIENCE AND ENGINEERING","category":"3AG","seat_type":"ROK","rounds":{"2024_R1":49592,"2024_R2":67528,"2024_R3":115840,"2025_R1":52255,"2025_R2":65032,"2025_R3":85797},"min_rank":49592,"max_rank":115840},{"college_code":"E209","college_name":"Jyothi Institute of Technology, Kanakapura Road,Bangalore ,BANGALORE","course_name":"INFORMATION SCIENCE AND ENGINEERING","category":"3BG","seat_type":"ROK","rounds":{"2024_R1":53110,"2024_R2":79802,"2024_R3":null,"2025_R1":49019,"2025_R2":69656,"2025_R3":94542},"min_rank":49019,"max_rank":94542},{"college_code":"E209","college_name":"Jyothi Institute of Technology, Kanakapura Road,Bangalore ,BANGALORE","course_name":"INFORMATION SCIENCE AND ENGINEERING","category":"3BKH","seat_type":"ROK","rounds":{"2025_R1":108849},"min_rank":108849,"max_rank":108849},{"college_code":"E209","college_name":"Jyothi Institute of Technology, Kanakapura Road,Bangalore ,BANGALORE","course_name":"INFORMATION SCIENCE AND ENGINEERING","category":"GM","seat_type":"ROK","rounds":{"2024_R1":49398,"2024_R2":62732,"2024_R3":103337,"2025_R1":45378,"2025_R2":64862,"2025_R3":83809},"min_rank":45378,"max_rank":103337},{"college_code":"E209","college_name":"Jyothi Institute of Technology, Kanakapura Road,Bangalore ,BANGALORE","course_name":"INFORMATION SCIENCE AND ENGINEERING","category":"GMH","seat_type":"HK","rounds":{"2025_R1":52431.5,"2025_R2":76741,"2025_R3":102563.5},"min_rank":52431.5,"max_rank":102563.5},{"college_code":"E209","college_name":"Jyothi Institute of Technology, Kanakapura Road,Bangalore ,BANGALORE","course_name":"INFORMATION SCIENCE AND ENGINEERING","category":"GMH","seat_type":"ROK","rounds":{"2025_R1":52431.5},"min_rank":52431.5,"max_rank":52431.5},{"college_code":"E209","college_name":"Jyothi Institute of Technology, Kanakapura Road,Bangalore ,BANGALORE","course_name":"INFORMATION SCIENCE AND ENGINEERING","category":"GMR","seat_type":"ROK","rounds":{"2024_R1":52026,"2024_R2":92066,"2024_R3":149169,"2025_R1":58837,"2025_R2":82015,"2025_R3":96585},"min_rank":52026,"max_rank":149169},{"college_code":"E209","college_name":"Jyothi Institute of Technology, Kanakapura Road,Bangalore ,BANGALORE","course_name":"INFORMATION SCIENCE AND ENGINEERING","category":"SCG","seat_type":"ROK","rounds":{"2024_R1":156982,"2024_R2":189617,"2024_R3":189617,"2025_R1":164552,"2025_R2":218821,"2025_R3":238343},"min_rank":156982,"max_rank":238343},{"college_code":"E209","college_name":"Jyothi Institute of Technology, Kanakapura Road,Bangalore ,BANGALORE","course_name":"MECHANICAL ENGINEERING","category":"GM","seat_type":"ROK","rounds":{"2024_R1":112202,"2024_R2":239731,"2024_R3":null,"2025_R1":84007,"2025_R2":203448,"2025_R3":203448},"min_rank":84007,"max_rank":239731}],"suggestions":{"ARTIFICIAL INTELLIGENCE AND DATA SCIENCE|1G|ROK":{"similarCollege":{"college":"S.S.E.T.S.S.G.Balekundri Institute of Technology, Shivabasavanagar, Belgaum SHIVABASAVA NAGAR, BELGAUM - 590010","branch":"ARTIFICIAL INTELLIGENCE AND DATA SCIENCE","category":"1G"},"similarBranch":{"college":"Jyothi Institute of Technology, Kanakapura Road,Bangalore ,BANGALORE","branch":"INFORMATION SCIENCE AND ENGINEERING","category":"1G"}},"ARTIFICIAL INTELLIGENCE AND DATA SCIENCE|2AG|ROK":{"similarCollege":{"college":"Vivekananada Institute of Technology, Kengeri, Bangalore GUDIMAVU VILLAGE ,KENGERI(HOBLI)NEAR KUMBALAGODU,BANGALORE","branch":"ARTIFICIAL INTELLIGENCE AND DATA SCIENCE","category":"2AG"},"similarBranch":{"college":"Jyothi Institute of Technology, Kanakapura Road,Bangalore ,BANGALORE","branch":"ELECTRONICS AND COMMUNICATION ENGG","category":"2AG"}},"ARTIFICIAL INTELLIGENCE AND DATA SCIENCE|2BG|ROK":{"similarCollege":{"college":"S.S.E.T.S.S.G.Balekundri Institute of Technology, Shivabasavanagar, Belgaum SHIVABASAVA NAGAR, BELGAUM - 590010","branch":"ARTIFICIAL INTELLIGENCE AND DATA SCIENCE","category":"2BG"},"similarBranch":{"college":"Jyothi Institute of Technology, Kanakapura Road,Bangalore ,BANGALORE","branch":"ARTIFICIAL INTELLIGENCE AND MACHINE LEARNING","category":"2BG"}},"ARTIFICIAL INTELLIGENCE AND DATA SCIENCE|3AG|ROK":{"similarCollege":{"college":"K S School of Engineering & Management, Mallasandra, Bangalore #15/1, MALLASANDRA, OFF KANAKAPURA ROAD, BANGALORE - 560062","branch":"ARTIFICIAL INTELLIGENCE AND DATA SCIENCE","category":"3AG"},"similarBranch":{"college":"Jyothi Institute of Technology, Kanakapura Road,Bangalore ,BANGALORE","branch":"COMPUTER SCIENCE AND ENGINEERING","category":"3AG"}},"ARTIFICIAL INTELLIGENCE AND DATA SCIENCE|3BG|ROK":{"similarCollege":{"college":"Jain Institute of Technology, Davanagere 323, BADA CROSS NEAR BLIND SCHOOL AVARAGERE DAVANGERE","branch":"ARTIFICIAL INTELLIGENCE AND DATA SCIENCE","category":"3BG"},"similarBranch":{"college":"Jyothi Institute of Technology, Kanakapura Road,Bangalore ,BANGALORE","branch":"ARTIFICIAL INTELLIGENCE AND MACHINE LEARNING","category":"3BG"}},"ARTIFICIAL INTELLIGENCE AND DATA SCIENCE|GM|ROK":{"similarCollege":{"college":"Adhichunchanagiri Institute of Technology, Chickamagalur ADICHUNCHANAGIRI EXTENTION,JYOTHINAGAR,CHIKMAGALUR - 577102","branch":"ARTIFICIAL INTELLIGENCE AND DATA SCIENCE","category":"GM"},"similarBranch":{"college":"Jyothi Institute of Technology, Kanakapura Road,Bangalore ,BANGALORE","branch":"COMPUTER SCIENCE AND ENGINEERING","category":"GM"}},"ARTIFICIAL INTELLIGENCE AND DATA SCIENCE|GMR|ROK":{"similarCollege":{"college":"T.John Institute of technology, Bangalore #86/1, KAMMANAHALLI,GOTTIGERE,BANNERUGATTA ROAD,BANGALORE","branch":"ARTIFICIAL INTELLIGENCE AND DATA SCIENCE","category":"GMR"},"similarBranch":{"college":"Jyothi Institute of Technology, Kanakapura Road,Bangalore ,BANGALORE","branch":"ELECTRONICS AND COMMUNICATION ENGG","category":"GMR"}},"ARTIFICIAL INTELLIGENCE AND DATA SCIENCE|SCG|ROK":{"similarCollege":{"college":"Rajeev Institute of Technology, Hassan PLOT 1-D(P-1), GROWTH CENTRE, INDUSTRIAL AREA, BANGALORE MANGALORE BYPASS ROAD","branch":"ARTIFICIAL INTELLIGENCE AND DATA SCIENCE","category":"SCG"},"similarBranch":{"college":"Jyothi Institute of Technology, Kanakapura Road,Bangalore ,BANGALORE","branch":"ELECTRONICS AND COMMUNICATION ENGG","category":"SCG"}},"ARTIFICIAL INTELLIGENCE AND MACHINE LEARNING|1G|ROK":{"similarCollege":{"college":"P E S Institute of Technology & Management, Shimoga GUDDADAARAKERE, KOTEGANGOORSAGAR ROAD,SHIMOGA","branch":"ARTIFICIAL INTELLIGENCE AND MACHINE LEARNING","category":"1G"},"similarBranch":{"college":"Jyothi Institute of Technology, Kanakapura Road,Bangalore ,BANGALORE","branch":"COMPUTER SCIENCE AND ENGINEERING","category":"1G"}},"ARTIFICIAL INTELLIGENCE AND MACHINE LEARNING|2AG|ROK":{"similarCollege":{"college":"Jain College of Engineering and Technology,Hubballi 404/4, 404/5, SAI NAGAR, UNKAL, HUBLI","branch":"ARTIFICIAL INTELLIGENCE AND MACHINE LEARNING","category":"2AG"},"similarBranch":{"college":"Jyothi Institute of Technology, Kanakapura Road,Bangalore ,BANGALORE","branch":"COMPUTER SCIENCE AND ENGINEERING","category":"2AG"}},"ARTIFICIAL INTELLIGENCE AND MACHINE LEARNING|2BG|ROK":{"similarCollege":{"college":"Adhichunchanagiri University (Formerly B G S Institute of Technology) B.G.NAGARA ,NAGAMANGALA TALUK,MANDYA DISTRICT -571448","branch":"ARTIFICIAL INTELLIGENCE AND MACHINE LEARNING","category":"2BG"},"similarBranch":{"college":"Jyothi Institute of Technology, Kanakapura Road,Bangalore ,BANGALORE","branch":"INFORMATION SCIENCE AND ENGINEERING","category":"2BG"}},"ARTIFICIAL INTELLIGENCE AND MACHINE LEARNING|3AG|ROK":{"similarCollege":{"college":"R.R. Institute of Technology, Chikkabanavara, Bangalore(AUTONOMOUS) NO. 67, RAJA REDDY LAYOUT,NEAR CHIKKABANAVARA RAILWAY STATION,CHIKKABANAVARA,BANGALORE - 560090","branch":"ARTIFICIAL INTELLIGENCE AND MACHINE LEARNING","category":"3AG"},"similarBranch":{"college":"Jyothi Institute of Technology, Kanakapura Road,Bangalore ,BANGALORE","branch":"ARTIFICIAL INTELLIGENCE AND DATA SCIENCE","category":"3AG"}},"ARTIFICIAL INTELLIGENCE AND MACHINE LEARNING|3BG|ROK":{"similarCollege":{"college":"AMC Engineering College, Bannerghatta Road, Bangalore(AUTONOMOUS) 18KM,BANNERAGHATTA ROAD,KALKERE,BANGALORE-560083,BANGALORE URBAN","branch":"ARTIFICIAL INTELLIGENCE AND MACHINE LEARNING","category":"3BG"},"similarBranch":{"college":"Jyothi Institute of Technology, Kanakapura Road,Bangalore ,BANGALORE","branch":"ELECTRONICS AND COMMUNICATION ENGG","category":"3BG"}},"ARTIFICIAL INTELLIGENCE AND MACHINE LEARNING|3BH|HK":{"similarCollege":{"college":"GOVERNMENT ENGINEERING COLLEGE, ARASIKERE ARASIKERE, HASSAN DISTRICT","branch":"ARTIFICIAL INTELLIGENCE AND MACHINE LEARNING","category":"3BH"},"similarBranch":null},"ARTIFICIAL INTELLIGENCE AND MACHINE LEARNING|3BH|ROK":{"similarCollege":{"college":"Ballari Institute of Technology & Management, Bellary(AUTONOMOUS) \"JNANA GANGOTRI\" CAMPUS, #873/2 OF KOLAGAL VILLAGE,BELLARY-HOSPET ROAD, ALLIPUR","branch":"ARTIFICIAL INTELLIGENCE AND MACHINE LEARNING","category":"3BH"},"similarBranch":null},"ARTIFICIAL INTELLIGENCE AND MACHINE LEARNING|GM|ROK":{"similarCollege":{"college":"Ballari Institute of Technology & Management, Bellary(AUTONOMOUS) \"JNANA GANGOTRI\" CAMPUS, #873/2 OF KOLAGAL VILLAGE,BELLARY-HOSPET ROAD, ALLIPUR","branch":"ARTIFICIAL INTELLIGENCE AND MACHINE LEARNING","category":"GM"},"similarBranch":{"college":"Jyothi Institute of Technology, Kanakapura Road,Bangalore ,BANGALORE","branch":"ARTIFICIAL INTELLIGENCE AND DATA SCIENCE","category":"GM"}},"ARTIFICIAL INTELLIGENCE AND MACHINE LEARNING|GMH|HK":{"similarCollege":{"college":"Government Engineering College, Challakere, Chitradurga BALLARI ROAD CHALLAKERE,CHITRADURGA","branch":"ARTIFICIAL INTELLIGENCE AND MACHINE LEARNING","category":"GMH"},"similarBranch":{"college":"Jyothi Institute of Technology, Kanakapura Road,Bangalore ,BANGALORE","branch":"COMPUTER SCIENCE AND ENGINEERING","category":"GMH"}},"ARTIFICIAL INTELLIGENCE AND MACHINE LEARNING|GMH|ROK":{"similarCollege":{"college":"H.K.B.K.College of Engineering, Bangalore # 22/1, NAGAWARA, BANGALORE-560045","branch":"ARTIFICIAL INTELLIGENCE AND MACHINE LEARNING","category":"GMH"},"similarBranch":{"college":"Jyothi Institute of Technology, Kanakapura Road,Bangalore ,BANGALORE","branch":"COMPUTER SCIENCE AND ENGINEERING","category":"GMH"}},"ARTIFICIAL INTELLIGENCE AND MACHINE LEARNING|GMR|ROK":{"similarCollege":{"college":"Adhichunchanagiri Institute of Technology, Chickamagalur ADICHUNCHANAGIRI EXTENTION,JYOTHINAGAR,CHIKMAGALUR - 577102","branch":"ARTIFICIAL INTELLIGENCE AND MACHINE LEARNING","category":"GMR"},"similarBranch":{"college":"Jyothi Institute of Technology, Kanakapura Road,Bangalore ,BANGALORE","branch":"COMPUTER SCIENCE AND ENGINEERING","category":"GMR"}},"ARTIFICIAL INTELLIGENCE AND MACHINE LEARNING|SCG|ROK":{"similarCollege":{"college":"Ballari Institute of Technology & Management, Bellary(AUTONOMOUS) \"JNANA GANGOTRI\" CAMPUS, #873/2 OF KOLAGAL VILLAGE,BELLARY-HOSPET ROAD, ALLIPUR","branch":"ARTIFICIAL INTELLIGENCE AND MACHINE LEARNING","category":"SCG"},"similarBranch":{"college":"Jyothi Institute of Technology, Kanakapura Road,Bangalore ,BANGALORE","branch":"ARTIFICIAL INTELLIGENCE AND DATA SCIENCE","category":"SCG"}},"ARTIFICIAL INTELLIGENCE AND MACHINE LEARNING|STG|ROK":{"similarCollege":{"college":"ANUVARTIK MIRJI BHARATESH INSTITUTE OF TECHNOLOGY BELAGAVI","branch":"ARTIFICIAL INTELLIGENCE AND MACHINE LEARNING","category":"STG"},"similarBranch":{"college":"Jyothi Institute of Technology, Kanakapura Road,Bangalore ,BANGALORE","branch":"ELECTRONICS AND COMMUNICATION ENGG","category":"STG"}},"CIVIL ENGINEERING|GM|ROK":{"similarCollege":{"college":"Brindavan College of Engineering, Yelahanaka, Bangalore DWARAKANAGARA, BAGALUR MAIN ROAD,YELAHANKA, BANGALORE - 560 063","branch":"CIVIL ENGINEERING","category":"GM"},"similarBranch":{"college":"Jyothi Institute of Technology, Kanakapura Road,Bangalore ,BANGALORE","branch":"ELECTRONICS AND COMMUNICATIO N ENGG","category":"GM"}},"CIVIL ENGINEERING|GMH|ROK":{"similarCollege":{"college":"Vijaya Vittala Institute of Technology, Doddagubbi, Hennur Bagalur Road, Bangalore #35/1, DODDA GUBBI POST, HENNUR-BAGALURU ROAD,BANGALORE","branch":"CIVIL ENGINEERING","category":"GMH"},"similarBranch":{"college":"Jyothi Institute of Technology, Kanakapura Road,Bangalore ,BANGALORE","branch":"ARTIFICIAL INTELLIGENCE AND MACHINE LEARNING","category":"GMH"}},"COMPUTER SCIENCE AND ENGINEERING|1G|ROK":{"similarCollege":{"college":"Gurunanak Dev Engineering College, Bidar MAILOOR ROAD,BIDAR 585403","branch":"COMPUTER SCIENCE AND ENGINEERING","category":"1G"},"similarBranch":{"college":"Jyothi Institute of Technology, Kanakapura Road,Bangalore ,BANGALORE","branch":"ARTIFICIAL INTELLIGENCE AND DATA SCIENCE","category":"1G"}},"COMPUTER SCIENCE AND ENGINEERING|2AG|ROK":{"similarCollege":{"college":"Alva's Institute of Engineering & Technology, Moodabidre, D.K (AUTONOMOUS) SHOBHAVANA CAMPUS,MIJAR,MOODBIDRI - 574225,MANGALORE TALUK,DHAKSHINA KANNADA","branch":"COMPUTER SCIENCE AND ENGINEERING","category":"2AG"},"similarBranch":{"college":"Jyothi Institute of Technology, Kanakapura Road,Bangalore ,BANGALORE","branch":"INFORMATION SCIENCE AND ENGINEERING","category":"2AG"}},"COMPUTER SCIENCE AND ENGINEERING|2AH|ROK":{"similarCollege":{"college":"Jain College of Engineering and Technology,Hubballi 404/4, 404/5, SAI NAGAR, UNKAL, HUBLI","branch":"COMPUTER SCIENCE AND ENGINEERING","category":"2AH"},"similarBranch":{"college":"Jyothi Institute of Technology, Kanakapura Road,Bangalore ,BANGALORE","branch":"ELECTRONICS AND COMMUNICATION ENGG","category":"2AH"}},"COMPUTER SCIENCE AND ENGINEERING|2AK|ROK":{"similarCollege":{"college":"Cambridge Institute Of Technology, North Campus, Devanahalli, Bangalore SURVEY NO. 73, LINGADHEERA GOLLAHALLI, KUNDANA POST, DEVANAHALLI TALUK","branch":"COMPUTER SCIENCE AND ENGINEERING","category":"2AK"},"similarBranch":null},"COMPUTER SCIENCE AND ENGINEERING|2AR|ROK":{"similarCollege":{"college":"Sri Sairam College Of Engineering, Anekal, Bangalore SAI LEO NAGAR","branch":"COMPUTER SCIENCE AND ENGINEERING","category":"2AR"},"similarBranch":{"college":"Jyothi Institute of Technology, Kanakapura Road,Bangalore ,BANGALORE","branch":"ELECTRONICS AND COMMUNICATION ENGG","category":"2AR"}},"COMPUTER SCIENCE AND ENGINEERING|2BG|ROK":{"similarCollege":{"college":"DR H N NATIONAL COLLEGE OF ENGINEERING BENGALURU","branch":"COMPUTER SCIENCE AND ENGINEERING","category":"2BG"},"similarBranch":{"college":"Jyothi Institute of Technology, Kanakapura Road,Bangalore ,BANGALORE","branch":"ARTIFICIAL INTELLIGENCE AND DATA SCIENCE","category":"2BG"}},"COMPUTER SCIENCE AND ENGINEERING|3AG|ROK":{"similarCollege":{"college":"H.K.B.K.College of Engineering, Bangalore # 22/1, NAGAWARA, BANGALORE-560045","branch":"COMPUTER SCIENCE AND ENGINEERING","category":"3AG"},"similarBranch":{"college":"Jyothi Institute of Technology, Kanakapura Road,Bangalore ,BANGALORE","branch":"INFORMATION SCIENCE AND ENGINEERING","category":"3AG"}},"COMPUTER SCIENCE AND ENGINEERING|3BG|ROK":{"similarCollege":{"college":"K L S Viswanathrao Deshpande Institute of Technology, Haliyal UDYOG VIDYA NAGAR,DANDELI ROAD, HALIYAL-581329","branch":"COMPUTER SCIENCE AND ENGINEERING","category":"3BG"},"similarBranch":{"college":"Jyothi Institute of Technology, Kanakapura Road,Bangalore ,BANGALORE","branch":"INFORMATION SCIENCE AND ENGINEERING","category":"3BG"}},"COMPUTER SCIENCE AND ENGINEERING|3BR|ROK":{"similarCollege":{"college":"K L E S's K L E College of Engineering & Technology, Chikkodi, Belgaum Dist. BANANTIKODI ROAD CHIKODI,BELGAUM -591 201,","branch":"COMPUTER SCIENCE AND ENGINEERING","category":"3BR"},"similarBranch":{"college":"Jyothi Institute of Technology, Kanakapura Road,Bangalore ,BANGALORE","branch":"ELECTRONICS AND COMMUNICATION ENGG","category":"3BR"}},"COMPUTER SCIENCE AND ENGINEERING|GM|ROK":{"similarCollege":{"college":"Maharaja Institute of Technology,Tandavapura,Mysore THANDAVAPURA VILLAGA,ON NATIONAL HIGHWWAYNANJANAGUD TALUK,MYSORE DISTRICT","branch":"COMPUTER SCIENCE AND ENGINEERING","category":"GM"},"similarBranch":{"college":"Jyothi Institute of Technology, Kanakapura Road,Bangalore ,BANGALORE","branch":"INFORMATION SCIENCE AND ENGINEERING","category":"GM"}},"COMPUTER SCIENCE AND ENGINEERING|GMH|HK":{"similarCollege":{"college":"R.R. Institute of Technology, Chikkabanavara, Bangalore(AUTONOMOUS) NO. 67, RAJA REDDY LAYOUT,NEAR CHIKKABANAVARA RAILWAY STATION,CHIKKABANAVARA,BANGALORE - 560090","branch":"COMPUTER SCIENCE AND ENGINEERING","category":"GMH"},"similarBranch":{"college":"Jyothi Institute of Technology, Kanakapura Road,Bangalore ,BANGALORE","branch":"INFORMATION SCIENCE AND ENGINEERING","category":"GMH"}},"COMPUTER SCIENCE AND ENGINEERING|GMH|ROK":{"similarCollege":{"college":"Maharaja Institute of Technology,Tandavapura,Mysore THANDAVAPURA VILLAGA,ON NATIONAL HIGHWWAYNANJANAGUD TALUK,MYSORE DISTRICT","branch":"COMPUTER SCIENCE AND ENGINEERING","category":"GMH"},"similarBranch":{"college":"Jyothi Institute of Technology, Kanakapura Road,Bangalore ,BANGALORE","branch":"INFORMATION SCIENCE AND ENGINEERING","category":"GMH"}},"COMPUTER SCIENCE AND ENGINEERING|GMK|ROK":{"similarCollege":{"college":"APS College of Engineering, Somanahalli, Bangalore 26 KM KANAKAPURA ROAD BANGALORE 82,BANGALORE URBAN","branch":"COMPUTER SCIENCE AND ENGINEERING","category":"GMK"},"similarBranch":{"college":"Jyothi Institute of Technology, Kanakapura Road,Bangalore ,BANGALORE","branch":"ELECTRONICS AND COMMUNICATION ENGG","category":"GMK"}},"COMPUTER SCIENCE AND ENGINEERING|GMR|ROK":{"similarCollege":{"college":"Bheemanna Khandre Institute of Technology, Bhalki BHALKI-HUMNABAD ROAD,BHALKI- 585328,DIST. BIDAR","branch":"COMPUTER SCIENCE AND ENGINEERING","category":"GMR"},"similarBranch":{"college":"Jyothi Institute of Technology, Kanakapura Road,Bangalore ,BANGALORE","branch":"INFORMATION SCIENCE AND ENGINEERING","category":"GMR"}},"COMPUTER SCIENCE AND ENGINEERING|GMRH|HK":{"similarCollege":{"college":"Malnad College of Engineering, Hassan(AUTONOMOUS) P.B. NO. 21, SALAGAME ROAD,HASSSAN","branch":"COMPUTER SCIENCE AND ENGINEERING","category":"GMRH"},"similarBranch":null},"COMPUTER SCIENCE AND ENGINEERING|GMRH|ROK":{"similarCollege":{"college":"P D A College of Engineering, Gulbarga(AUTONOMOUS) AIWAN-E-SHAHI AREA,STATION ROAD,GULBARGA-585102","branch":"COMPUTER SCIENCE AND ENGINEERING","category":"GMRH"},"similarBranch":null},"COMPUTER SCIENCE AND ENGINEERING|SCG|ROK":{"similarCollege":{"college":"Sai Vidya Institute of Technology, Rajanakunte, Bangalore RAJANUKUNTE,DODDBALLAPURA ROAD ,VIA: YELAHANKA,BANGALORE","branch":"COMPUTER SCIENCE AND ENGINEERING","category":"SCG"},"similarBranch":{"college":"Jyothi Institute of Technology, Kanakapura Road,Bangalore ,BANGALORE","branch":"INFORMATION SCIENCE AND ENGINEERING","category":"SCG"}},"COMPUTER SCIENCE AND ENGINEERING|SCH|HK":{"similarCollege":{"college":"Angadi Institute of Technology and Management , Savgoan Rd., Belgaum SAVAGAON ROAD BELGAUM","branch":"COMPUTER SCIENCE AND ENGINEERING","category":"SCH"},"similarBranch":null},"COMPUTER SCIENCE AND ENGINEERING|SCH|ROK":{"similarCollege":{"college":"T.John Institute of technology, Bangalore #86/1, KAMMANAHALLI,GOTTIGERE,BANNERUGATTA ROAD,BANGALORE","branch":"COMPUTER SCIENCE AND ENGINEERING","category":"SCH"},"similarBranch":{"college":"Jyothi Institute of Technology, Kanakapura Road,Bangalore ,BANGALORE","branch":"ELECTRONICS AND COMMUNICATION ENGG","category":"SCH"}},"COMPUTER SCIENCE AND ENGINEERING|STG|ROK":{"similarCollege":{"college":"R. V. College of Engineering, Bangalore(AUTONOMOUS) R.V. VIDYANIKETAN POST, MYSORE ROAD,BANGALORE","branch":"COMPUTER SCIENCE AND ENGINEERING","category":"STG"},"similarBranch":{"college":"Jyothi Institute of Technology, Kanakapura Road,Bangalore ,BANGALORE","branch":"ARTIFICIAL INTELLIGENCE AND MACHINE LEARNING","category":"STG"}},"COMPUTER SCIENCE AND ENGINEERING|STH|ROK":{"similarCollege":{"college":"ANUVARTIK MIRJI BHARATESH INSTITUTE OF TECHNOLOGY BELAGAVI","branch":"COMPUTER SCIENCE AND ENGINEERING","category":"STH"},"similarBranch":null},"ELECTRONICS AND COMMUNICATIO N ENGG|GM|ROK":{"similarCollege":{"college":"S E A College of Engineering & Technology, Virgonagar, Bangalore EKTA NAGAR, BASAVANAPURA, VIRGO NAGAR POST, BANGALORE - 560 049.","branch":"ELECTRONICS AND COMMUNICATIO N ENGG","category":"GM"},"similarBranch":{"college":"Jyothi Institute of Technology, Kanakapura Road,Bangalore ,BANGALORE","branch":"ELECTRONICS AND COMMUNICATION ENGG","category":"GM"}},"ELECTRONICS AND COMMUNICATION ENGG|1G|ROK":{"similarCollege":{"college":"G M Institute of Technology, Davanagere POST BOX. NO. 4, P.B.ROAD.DAVANGERE.","branch":"ELECTRONICS AND COMMUNICATION ENGG","category":"1G"},"similarBranch":{"college":"Jyothi Institute of Technology, Kanakapura Road,Bangalore ,BANGALORE","branch":"ARTIFICIAL INTELLIGENCE AND MACHINE LEARNING","category":"1G"}},"ELECTRONICS AND COMMUNICATION ENGG|1RH|ROK":{"similarCollege":{"college":"Government Engineering College, Viprasinagar, Gangavathi VIPRASAI NAGAR,GANGAVATHI,KOPPAL","branch":"ELECTRONICS AND COMMUNICATION ENGG","category":"1RH"},"similarBranch":null},"ELECTRONICS AND COMMUNICATION ENGG|2AG|ROK":{"similarCollege":{"college":"K L E Institute of Technology Hubli","branch":"ELECTRONICS AND COMMUNICATION ENGG","category":"2AG"},"similarBranch":{"college":"Jyothi Institute of Technology, Kanakapura Road,Bangalore ,BANGALORE","branch":"ARTIFICIAL INTELLIGENCE AND MACHINE LEARNING","category":"2AG"}},"ELECTRONICS AND COMMUNICATION ENGG|2AH|ROK":{"similarCollege":{"college":"H.K.B.K.College of Engineering, Bangalore # 22/1, NAGAWARA, BANGALORE-560045","branch":"ELECTRONICS AND COMMUNICATION ENGG","category":"2AH"},"similarBranch":{"college":"Jyothi Institute of Technology, Kanakapura Road,Bangalore ,BANGALORE","branch":"COMPUTER SCIENCE AND ENGINEERING","category":"2AH"}},"ELECTRONICS AND COMMUNICATION ENGG|2AR|ROK":{"similarCollege":{"college":"Sri Venkateshwara College of Engineering, Bangalore VIDYANAGAR, BENGALURU INTERNATIONAL AIRPORT ROAD,BETTAHALASUR POST,BENGALURU NORTH,BENGALURU - 562 157","branch":"ELECTRONICS AND COMMUNICATION ENGG","category":"2AR"},"similarBranch":{"college":"Jyothi Institute of Technology, Kanakapura Road,Bangalore ,BANGALORE","branch":"COMPUTER SCIENCE AND ENGINEERING","category":"2AR"}},"ELECTRONICS AND COMMUNICATION ENGG|2BG|ROK":{"similarCollege":{"college":"ANUVARTIK MIRJI BHARATESH INSTITUTE OF TECHNOLOGY BELAGAVI","branch":"ELECTRONICS AND COMMUNICATION ENGG","category":"2BG"},"similarBranch":{"college":"Jyothi Institute of Technology, Kanakapura Road,Bangalore ,BANGALORE","branch":"COMPUTER SCIENCE AND ENGINEERING","category":"2BG"}},"ELECTRONICS AND COMMUNICATION ENGG|3AG|ROK":{"similarCollege":{"college":"Cambridge Institute Of Technology, North Campus, Devanahalli, Bangalore SURVEY NO. 73, LINGADHEERA GOLLAHALLI, KUNDANA POST, DEVANAHALLI TALUK","branch":"ELECTRONICS AND COMMUNICATION ENGG","category":"3AG"},"similarBranch":{"college":"Jyothi Institute of Technology, Kanakapura Road,Bangalore ,BANGALORE","branch":"ARTIFICIAL INTELLIGENCE AND MACHINE LEARNING","category":"3AG"}},"ELECTRONICS AND COMMUNICATION ENGG|3BG|ROK":{"similarCollege":{"college":"East West Institute Of Technology,Bangalore(AUTONOMOUS) SY. NO.63, OFF MAGADI MAIN ROAD, VISHWANEEDAM POST,BANGALORE","branch":"ELECTRONICS AND COMMUNICATION ENGG","category":"3BG"},"similarBranch":{"college":"Jyothi Institute of Technology, Kanakapura Road,Bangalore ,BANGALORE","branch":"COMPUTER SCIENCE AND ENGINEERING","category":"3BG"}},"ELECTRONICS AND COMMUNICATION ENGG|3BR|ROK":{"similarCollege":{"college":"Ballari Institute of Technology & Management, Bellary(AUTONOMOUS) \"JNANA GANGOTRI\" CAMPUS, #873/2 OF KOLAGAL VILLAGE,BELLARY-HOSPET ROAD, ALLIPUR","branch":"ELECTRONICS AND COMMUNICATION ENGG","category":"3BR"},"similarBranch":{"college":"Jyothi Institute of Technology, Kanakapura Road,Bangalore ,BANGALORE","branch":"COMPUTER SCIENCE AND ENGINEERING","category":"3BR"}},"ELECTRONICS AND COMMUNICATION ENGG|GM|ROK":{"similarCollege":{"college":"BLDEA's VP. Dr.P.G. Hallakatti College of Engineering & Technology, Bijapur ASHRAM ROAD,BIJAPUR - 586103","branch":"ELECTRONICS AND COMMUNICATION ENGG","category":"GM"},"similarBranch":{"college":"Jyothi Institute of Technology, Kanakapura Road,Bangalore ,BANGALORE","branch":"ARTIFICIAL INTELLIGENCE AND MACHINE LEARNING","category":"GM"}},"ELECTRONICS AND COMMUNICATION ENGG|GMH|ROK":{"similarCollege":{"college":"G M Institute of Technology, Davanagere POST BOX. NO. 4, P.B.ROAD.DAVANGERE.","branch":"ELECTRONICS AND COMMUNICATION ENGG","category":"GMH"},"similarBranch":{"college":"Jyothi Institute of Technology, Kanakapura Road,Bangalore ,BANGALORE","branch":"CIVIL ENGINEERING","category":"GMH"}},"ELECTRONICS AND COMMUNICATION ENGG|GMK|ROK":{"similarCollege":{"college":"Cambridge Institute Of Technology, North Campus, Devanahalli, Bangalore SURVEY NO. 73, LINGADHEERA GOLLAHALLI, KUNDANA POST, DEVANAHALLI TALUK","branch":"ELECTRONICS AND COMMUNICATION ENGG","category":"GMK"},"similarBranch":{"college":"Jyothi Institute of Technology, Kanakapura Road,Bangalore ,BANGALORE","branch":"COMPUTER SCIENCE AND ENGINEERING","category":"GMK"}},"ELECTRONICS AND COMMUNICATION ENGG|GMR|ROK":{"similarCollege":{"college":"S J C Institute of Technology, Chickkaballapur(AUTONOMOUS) P B NO. 20, B B ROAD, CHICKBALLAPUR, CHICKBALLAPUR (DISTRICT)","branch":"ELECTRONICS AND COMMUNICATION ENGG","category":"GMR"},"similarBranch":{"college":"Jyothi Institute of Technology, Kanakapura Road,Bangalore ,BANGALORE","branch":"ARTIFICIAL INTELLIGENCE AND MACHINE LEARNING","category":"GMR"}},"ELECTRONICS AND COMMUNICATION ENGG|SCG|ROK":{"similarCollege":{"college":"S J M Institute of Technology, Chitradurga P B NO 73, NH -4 BYE PASS, CHITRADURGA","branch":"ELECTRONICS AND COMMUNICATION ENGG","category":"SCG"},"similarBranch":{"college":"Jyothi Institute of Technology, Kanakapura Road,Bangalore ,BANGALORE","branch":"COMPUTER SCIENCE AND ENGINEERING","category":"SCG"}},"ELECTRONICS AND COMMUNICATION ENGG|SCH|ROK":{"similarCollege":{"college":"S D M Institute of Tech., Ujire, Dakshina Kannada UJIRE-574240 DAKSHINA KANNADA KARNATAKA","branch":"ELECTRONICS AND COMMUNICATION ENGG","category":"SCH"},"similarBranch":{"college":"Jyothi Institute of Technology, Kanakapura Road,Bangalore ,BANGALORE","branch":"COMPUTER SCIENCE AND ENGINEERING","category":"SCH"}},"ELECTRONICS AND COMMUNICATION ENGG|SCK|ROK":{"similarCollege":{"college":"ADITYA COLLEGE OF ENGINEERING AND TECHNOLOGY SURVEY NO 2/8 2/9 AND 2/2, KAMAKSHIPURA, SONNENAHALLI PANCHAYATH, HESARAGHATTA HOBLI, YELAHANKA","branch":"ELECTRONICS AND COMMUNICATION ENGG","category":"SCK"},"similarBranch":null},"ELECTRONICS AND COMMUNICATION ENGG|SCR|ROK":{"similarCollege":{"college":"Smt. Kamala & Sri Venkappa M.Agadi College of Engineering & Technology, Gadag SAVANUR ROAD, GULAGANJIKOPPA,LAXMESHWAR DIST: GADAG","branch":"ELECTRONICS AND COMMUNICATION ENGG","category":"SCR"},"similarBranch":null},"ELECTRONICS AND COMMUNICATION ENGG|STG|ROK":{"similarCollege":{"college":"APS College of Engineering, Somanahalli, Bangalore 26 KM KANAKAPURA ROAD BANGALORE 82,BANGALORE URBAN","branch":"ELECTRONICS AND COMMUNICATION ENGG","category":"STG"},"similarBranch":{"college":"Jyothi Institute of Technology, Kanakapura Road,Bangalore ,BANGALORE","branch":"COMPUTER SCIENCE AND ENGINEERING","category":"STG"}},"ELECTRONICS AND COMMUNICATION ENGG|STR|ROK":{"similarCollege":{"college":"AGM Rural Engineering College, Varur, Hubli NH-4, P.B. ROAD OPP VRL HEAD OFFICE VARUR.,DHARWAD","branch":"ELECTRONICS AND COMMUNICATION ENGG","category":"STR"},"similarBranch":null},"INFORMATION SCIENCE AND ENGINEERING|1G|ROK":{"similarCollege":{"college":"BLDEA's VP. Dr.P.G. Hallakatti College of Engineering & Technology, Bijapur ASHRAM ROAD,BIJAPUR - 586103","branch":"INFORMATION SCIENCE AND ENGINEERING","category":"1G"},"similarBranch":{"college":"Jyothi Institute of Technology, Kanakapura Road,Bangalore ,BANGALORE","branch":"ELECTRONICS AND COMMUNICATION ENGG","category":"1G"}},"INFORMATION SCIENCE AND ENGINEERING|2AG|ROK":{"similarCollege":{"college":"Sai Vidya Institute of Technology, Rajanakunte, Bangalore RAJANUKUNTE,DODDBALLAPURA ROAD ,VIA: YELAHANKA,BANGALORE","branch":"INFORMATION SCIENCE AND ENGINEERING","category":"2AG"},"similarBranch":{"college":"Jyothi Institute of Technology, Kanakapura Road,Bangalore ,BANGALORE","branch":"ARTIFICIAL INTELLIGENCE AND DATA SCIENCE","category":"2AG"}},"INFORMATION SCIENCE AND ENGINEERING|2BG|ROK":{"similarCollege":{"college":"East Point College of Engineering & Technology, Bangalore(AUTONOMOUS) JNANA PRABHA, BIDARAHALLI,VIRGONAGAR POST,BANGALORE.","branch":"INFORMATION SCIENCE AND ENGINEERING","category":"2BG"},"similarBranch":{"college":"Jyothi Institute of Technology, Kanakapura Road,Bangalore ,BANGALORE","branch":"ELECTRONICS AND COMMUNICATION ENGG","category":"2BG"}},"INFORMATION SCIENCE AND ENGINEERING|3AG|ROK":{"similarCollege":{"college":"S J C Institute of Technology, Chickkaballapur(AUTONOMOUS) P B NO. 20, B B ROAD, CHICKBALLAPUR, CHICKBALLAPUR (DISTRICT)","branch":"INFORMATION SCIENCE AND ENGINEERING","category":"3AG"},"similarBranch":{"college":"Jyothi Institute of Technology, Kanakapura Road,Bangalore ,BANGALORE","branch":"ELECTRONICS AND COMMUNICATION ENGG","category":"3AG"}},"INFORMATION SCIENCE AND ENGINEERING|3BG|ROK":{"similarCollege":{"college":"East West Institute Of Technology,Bangalore(AUTONOMOUS) SY. NO.63, OFF MAGADI MAIN ROAD, VISHWANEEDAM POST,BANGALORE","branch":"INFORMATION SCIENCE AND ENGINEERING","category":"3BG"},"similarBranch":{"college":"Jyothi Institute of Technology, Kanakapura Road,Bangalore ,BANGALORE","branch":"ARTIFICIAL INTELLIGENCE AND DATA SCIENCE","category":"3BG"}},"INFORMATION SCIENCE AND ENGINEERING|3BKH|ROK":{"similarCollege":{"college":"ADITYA COLLEGE OF ENGINEERING AND TECHNOLOGY SURVEY NO 2/8 2/9 AND 2/2, KAMAKSHIPURA, SONNENAHALLI PANCHAYATH, HESARAGHATTA HOBLI, YELAHANKA","branch":"INFORMATION SCIENCE AND ENGINEERING","category":"3BKH"},"similarBranch":null},"INFORMATION SCIENCE AND ENGINEERING|GM|ROK":{"similarCollege":{"college":"East West Institute Of Technology,Bangalore(AUTONOMOUS) SY. NO.63, OFF MAGADI MAIN ROAD, VISHWANEEDAM POST,BANGALORE","branch":"INFORMATION SCIENCE AND ENGINEERING","category":"GM"},"similarBranch":{"college":"Jyothi Institute of Technology, Kanakapura Road,Bangalore ,BANGALORE","branch":"MECHANICAL ENGINEERING","category":"GM"}},"INFORMATION SCIENCE AND ENGINEERING|GMH|HK":{"similarCollege":{"college":"East West Institute Of Technology,Bangalore(AUTONOMOUS) SY. NO.63, OFF MAGADI MAIN ROAD, VISHWANEEDAM POST,BANGALORE","branch":"INFORMATION SCIENCE AND ENGINEERING","category":"GMH"},"similarBranch":{"college":"Jyothi Institute of Technology, Kanakapura Road,Bangalore ,BANGALORE","branch":"ARTIFICIAL INTELLIGENCE AND MACHINE LEARNING","category":"GMH"}},"INFORMATION SCIENCE AND ENGINEERING|GMH|ROK":{"similarCollege":{"college":"East West Institute Of Technology,Bangalore(AUTONOMOUS) SY. NO.63, OFF MAGADI MAIN ROAD, VISHWANEEDAM POST,BANGALORE","branch":"INFORMATION SCIENCE AND ENGINEERING","category":"GMH"},"similarBranch":{"college":"Jyothi Institute of Technology, Kanakapura Road,Bangalore ,BANGALORE","branch":"ELECTRONICS AND COMMUNICATION ENGG","category":"GMH"}},"INFORMATION SCIENCE AND ENGINEERING|GMR|ROK":{"similarCollege":{"college":"BLDEA's VP. Dr.P.G. Hallakatti College of Engineering & Technology, Bijapur ASHRAM ROAD,BIJAPUR - 586103","branch":"INFORMATION SCIENCE AND ENGINEERING","category":"GMR"},"similarBranch":{"college":"Jyothi Institute of Technology, Kanakapura Road,Bangalore ,BANGALORE","branch":"ARTIFICIAL INTELLIGENCE AND DATA SCIENCE","category":"GMR"}},"INFORMATION SCIENCE AND ENGINEERING|SCG|ROK":{"similarCollege":{"college":"Sai Vidya Institute of Technology, Rajanakunte, Bangalore RAJANUKUNTE,DODDBALLAPURA ROAD ,VIA: YELAHANKA,BANGALORE","branch":"INFORMATION SCIENCE AND ENGINEERING","category":"SCG"},"similarBranch":{"college":"Jyothi Institute of Technology, Kanakapura Road,Bangalore ,BANGALORE","branch":"ARTIFICIAL INTELLIGENCE AND MACHINE LEARNING","category":"SCG"}},"MECHANICAL ENGINEERING|GM|ROK":{"similarCollege":{"college":"S.S.E.T.S.S.G.Balekundri Institute of Technology, Shivabasavanagar, Belgaum SHIVABASAVA NAGAR, BELGAUM - 590010","branch":"MECHANICAL ENGINEERING","category":"GM"},"similarBranch":{"college":"Jyothi Institute of Technology, Kanakapura Road,Bangalore ,BANGALORE","branch":"CIVIL ENGINEERING","category":"GM"}}}}