{"cutoffs":[{"college_code":"G426","college_name":"Spatika College of Nursing, No.105/7, Sri Sainivas, Mallathalli, NGEF Layout, 60 Ft. Road, Bengaluru - 560 056 New Address Spatika college of Nursing , No. 21/5 , Doddabyalkere, Hessarghatta Road, Shivakote , Yelahanka , Bengaluru-560089","course_name":"BS.c Nursing Govt","category":"GM","seat_type":"ROK","rounds":{"2025_R1":151773,"2025_R2":171837,"2025_R3":165015},"min_rank":151773,"max_rank":171837}],"suggestions":{"BS.c Nursing Govt|GM|ROK":{"similarCollege":{"college":"Vijayanagar College of Nursing, No.43, 1st A Main Road, Nagarbhavi, Bengaluru - 560 072","branch":"BS.c Nursing Govt","category":"GM"},"similarBranch":null}}}