{"cutoffs":[{"college_code":"G477","college_name":"Suraksha College of Nursing, Suraksha Campus, Near Rangayyana Bagilu, Chitradurga - 577 501","course_name":"BS.c Nursing Govt","category":"2AG","seat_type":"ROK","rounds":{"2025_R1":125276,"2025_R2":154694,"2025_R3":182470},"min_rank":125276,"max_rank":182470},{"college_code":"G477","college_name":"Suraksha College of Nursing, Suraksha Campus, Near Rangayyana Bagilu, Chitradurga - 577 501","course_name":"BS.c Nursing Govt","category":"3BG","seat_type":"ROK","rounds":{"2025_R1":111224,"2025_R2":136619,"2025_R3":136619},"min_rank":111224,"max_rank":136619},{"college_code":"G477","college_name":"Suraksha College of Nursing, Suraksha Campus, Near Rangayyana Bagilu, Chitradurga - 577 501","course_name":"BS.c Nursing Govt","category":"GM","seat_type":"ROK","rounds":{"2025_R1":109708,"2025_R2":114927,"2025_R3":128843},"min_rank":109708,"max_rank":128843},{"college_code":"G477","college_name":"Suraksha College of Nursing, Suraksha Campus, Near Rangayyana Bagilu, Chitradurga - 577 501","course_name":"BS.c Nursing Govt","category":"GMR","seat_type":"ROK","rounds":{"2025_R1":118292,"2025_R2":128843,"2025_R3":129099},"min_rank":118292,"max_rank":129099},{"college_code":"G477","college_name":"Suraksha College of Nursing, Suraksha Campus, Near Rangayyana Bagilu, Chitradurga - 577 501","course_name":"BS.c Nursing Govt","category":"SCG","seat_type":"ROK","rounds":{"2025_R1":129819,"2025_R2":129819,"2025_R3":130762},"min_rank":129819,"max_rank":130762}],"suggestions":{"BS.c Nursing Govt|2AG|ROK":{"similarCollege":{"college":"Smt. Lakshmi Devi College of Nursing, Sy. No. 128/1, Siddhartha Nagar, Chintamani Road, Hoskote, Bengaluru - 562 114","branch":"BS.c Nursing Govt","category":"2AG"},"similarBranch":null},"BS.c Nursing Govt|3BG|ROK":{"similarCollege":{"college":"Rajarajeshwari College of Nursing, Kambipura, Mysore Road, Kengeri Hobli, Bengaluru - 560 074","branch":"BS.c Nursing Govt","category":"3BG"},"similarBranch":null},"BS.c Nursing Govt|GM|ROK":{"similarCollege":{"college":"Shree Bhagyavanti College of Nursing, Hunasagi Road, Near Ambedkar Circle, Dist. Vijayapur, Talikoti - 586 214","branch":"BS.c Nursing Govt","category":"GM"},"similarBranch":null},"BS.c Nursing Govt|GMR|ROK":{"similarCollege":{"college":"Mangala College of Nursing, Plot No 1A, KIADB Industrial Area, B Kathyhalli, B M Road, Hassan - 573 201","branch":"BS.c Nursing Govt","category":"GMR"},"similarBranch":null},"BS.c Nursing Govt|SCG|ROK":{"similarCollege":{"college":"B. R. Sangappagol College of Nursing, Majalatti ? Mugali Road, Near Govt. P U College, Majalatti Village, Belagavi, Chikkodi - 591 226","branch":"BS.c Nursing Govt","category":"SCG"},"similarBranch":null}}}