{"cutoffs":[{"college_code":"G997","college_name":"Sanjeevini College of Nursing, Bidar","course_name":"BS.c Nursing Govt","category":"GM","seat_type":"ROK","rounds":{"2025_R3":205249},"min_rank":205249,"max_rank":205249}],"suggestions":{"BS.c Nursing Govt|GM|ROK":{"similarCollege":{"college":"Diya College of Nursing, , No. 1924/1, Kammanahalli, Bengaluru - New Address Diya College of Nursing, No 4S, Avenue , 28 A, Ramamurthy Nagar Road, Kalkere Bengaluru-560043","college_code":"G285","branch":"BS.c Nursing Govt","category":"GM"},"similarBranch":null}}}